Workbook

Sheet Summary
A1: Column1 | B1: Column2 | C1: Column4 | D1: Column5 | E1: Profitability Dashboard | F1: Column7 | G1: Column8 | H1: Column9 | I1: Column10 | J1: Column11 | K1: Column12 | L1: Column13 | M1: Column14
A2: MASTERCARD FINANCIAL MODEL – EXECUTIVE SUMMARY | C2: Analyst | E2: Net Profit Margin (2020-2024) | F2: KPI Boxes
A3: (All figures in USD Millions unless stated otherwise) | C3: Item | D3: Value | E3: =Ratios!C16 -> 0.41899222 | F3: Revenue Growth
A4: Company Overview | B4: Description | C4: Market price | D4: =B36 -> 450 | E4: =Ratios!D28 -> 0.46001906 | F4: =B20 -> 0.16481028
A5: Company Name | B5: Mastercard Inc | C5: Target Price (12M) | D5: =B33 -> 389.90639 | E5: =Ratios!E28 -> 0.44655304 | F5: EBITDA Margin
A6: Industry | B6: Global Digital Payments | C6: Implied Downside: | D6: =B38 -> -0.13354135 | E6: =Ratios!F28 -> 0.44605148 | F6: 0.545
A7: Forecast Period | B7: 2025-2029 | E7: =Ratios!G28 -> 0.45705968 | F7: WACC
A8: Valuation Methods | B8: DCF,FCFE,FCFF,DDM,Relative Valuation | C8: Integrated Financial Model | D8: Revenue & EPS Growth Trend | F8: =WACC!B28 -> 0.094791294
A9: Key Players | B9: Visa, Mastercard, Paypal, American Express, Block inc, Global Payments | C9: Company: Mastercard Inc. | D9: Revenue (2020-2029 | E9: EPS (2020-2029) | F9: Intrinsic Value
A10: Downside is primarily driven by potential multiple compression as growth normalizes and valuation converges toward industry averages | C10: Analyst: Talla Varun Goud | D10: ='Profit Loss'!B4 -> 15301 | E10: ='Profit Loss'!B21 -> 6.4 | F10: =B37 -> 389.90639
A11: Financial Highlights | C11: Valuation Date: 2026 | D11: ='Profit Loss'!C4 -> 18884 | E11: ='Profit Loss'!C21 -> 8.79 | F11: Downside
A12: Metric | B12: Values | C12: Currency: USD Millions | D12: ='Profit Loss'!D4 -> 22237 | E12: ='Profit Loss'!D21 -> 10.26 | F12: =B38 -> -0.13354135
A13: Revenue Growth | B13: ='Valuation Dashboard'!B12 -> 0.11494394 | C13: DCF weighted higher due to intrinsic valuation reliability | D13: ='Profit Loss'!E4 -> 25098 | E13: ='Profit Loss'!E21 -> 11.86
A14: Net Profit Margin | B14: ='Profit Loss'!K20/'Profit Loss'!K4 -> 0.48585982 | D14: ='Profit Loss'!F4 -> 28167 | E14: ='Profit Loss'!F21 -> 13.91
A15: ROE | B15: ='Profit Loss'!K20/Balance_Sheet!K40 -> 1.235841 | C15: Recommendation Box | D15: ='Profit Loss'!G4 -> 31547.04 | E15: ='Profit Loss'!G21 -> 16.11343
A16: Free Cash Flow | B16: ='DCF Valuation'!G23 -> 111160.98 | C16: Recommendation: SELL | D16: ='Profit Loss'!H4 -> 35648.155 | E16: ='Profit Loss'!H21 -> 18.941557
C17: Target Price: $390 | D17: ='Profit Loss'!I4 -> 39925.934 | E17: ='Profit Loss'!I21 -> 21.862617
A18: Growth & Profitability | C18: Current Price: $450 | D18: ='Profit Loss'!J4 -> 44317.787 | E18: ='Profit Loss'!J21 -> 25.001704
A19: Key Insights | B19: Values | C19: Downside: -13.4% | D19: ='Profit Loss'!K4 -> 48749.565 | E19: ='Profit Loss'!K21 -> 28.32759
A20: Revenue CAGR | B20: ='CAGR Projections'!G4 -> 0.16481028 | C20: Key Reason: Overvaluation driven by high multiples despite strong fundamentals
A21: EPS CAGR | B21: ='CAGR Projections'!G7 -> 0.21419038 | C21: Key Investment Drivers | D21: Operating Margin (2020-2024) | E21: ROE (2020-2024) | F21: EBITDA (2020-2029)
A22: Average ROE | B22: =AVERAGE(Ratios!C13:G13) -> 1.4616261 | C22: Digital payment expansion | D22: =Ratios!C41 -> 0.52813542 | E22: =Ratios!C13 -> 0.98813194 | F22: ='Profit Loss'!B25 -> 8661
A23: Average Operating Margin | B23: =AVERAGE(Ratios!C41:G41) -> 0.54497449 | C23: Cross-border growth | D23: =Ratios!D41 -> 0.53389112 | E23: =Ratios!D13 -> 1.176622 | F23: ='Profit Loss'!C25 -> 10808
A24: High ROE driven by asset-light model and share buybacks | C24: High margins | D24: =Ratios!E41 -> 0.55151324 | E24: =Ratios!E13 -> 1.5623033 | F24: ='Profit Loss'!D25 -> 13014
C25: Network effects | D25: =Ratios!F41 -> 0.55813212 | E25: =Ratios!F13 -> 1.6050179 | F25: =Table1[[#This Row],[2023]] -> 14807
A26: Investment Summary & Recommendation | C26: Strong global payment network | D26: =Ratios!G41 -> 0.55320055 | E26: =Ratios!G13 -> 1.9760553 | F26: ='Profit Loss'!F25 -> 16479
A27: Method | B27: Implied Share Value ($) | D27: Final Investment Recommendation Chart | F27: ='Profit Loss'!G25 -> 18297.283
A28: DCF (Blended FCFF/FCFE) | B28: ='DCF Valuation'!B35 -> 386.11179 | C28: Valuation Methodology | D28: Method | E28: Final Investment Recommendation | F28: ='Profit Loss'!H25 -> 20996.763
A29: DCF (FCFF) | B29: ='Investment Recommendation'!D23 -> 118.33344 | C29: DCF and FCFF are weighted higher due to their | D29: Market Price | E29: 450 | F29: ='Profit Loss'!I25 -> 23676.079
A30: DCF (FCFE) | B30: ='Investment Recommendation'!B22 -> 335.44643 | C30: intrinsic valuation approach. | D30: DCF | E30: =B28 -> 386.11179 | F30: ='Profit Loss'!J25 -> 26457.719
A31: DDM | B31: DDM not applicable due to low dividend yield focus | C31: Relative valuation and DDM are used as | D31: FCFF | E31: =B29 -> 118.33344 | F31: ='Profit Loss'!K25 -> 29298.489
A32: Relative Valuation | B32: ='Investment Recommendation'!D21 -> 170.93903 | C32: supporting reference metrics. | D32: DDM | E32: =B31 -> DDM not applicable due to low dividend yield focus
A33: Valuation Weighting (Target Price) | B33: ='Investment Recommendation'!B25 -> 389.90639 | D33: Relative Valuation | E33: =B32 -> 170.93903
D34: Final Target Price | E34: =B33 -> 389.90639
A35: Final Investment Decision | B35: Values | C35: Free Cash Flow Trend
A36: Current Market Price | B36: ='DCF Valuation'!B36 -> 450 | C36: FCF | D36: Value
A37: Target Price | B37: =B33 -> 389.90639 | C37: 2025 | D37: ='DCF Valuation'!B23 -> 18784.948
A38: Upside/Downside | B38: =(B37-B36)/B36 -> -0.13354135 | C38: 2026 | D38: ='DCF Valuation'!C23 -> 19435.742
A39: Recommendation | B39: ='Investment Recommendation'!B45 -> SELL | C39: 2027 | D39: ='DCF Valuation'!D23 -> 21798.44
A40: Downside risk driven by valuation compression and sensitivity to WACC assumptions | C40: 2028 | D40: ='DCF Valuation'!E23 -> 24283.1
A41: Model Sheet Linkage Titles | C41: 2029 | D41: ='DCF Valuation'!F23 -> 26858.749
A42: 1. Raw Data Income | B42: Refer to linked model sheets
A43: 2.Raw Data Balance | B43: Refer to linked model sheets | C43: Football Field Table
A44: 3.Assumptions | B44: Refer to linked model sheets | C44: Method | D44: Low | E44: Base | F44: High
A45: 4.Investment Thesis | B45: Refer to linked model sheets | C45: DCF | D45: 120 | E45: 136.18 | F45: 160
A46: 5.Income Statement Projections | B46: Refer to linked model sheets | C46: FCFF | D46: 140 | E46: 156 | F46: 180
A47: 6.Balance Sheet Projections | B47: Refer to linked model sheets | C47: DDM | D47: 60 | E47: 64.5 | F47: 70
A48: 7.Cash Flow Projections | B48: Refer to linked model sheets | C48: Relative | D48: 55 | E48: 64 | F48: 75
A49: 8.Common Size | B49: Refer to linked model sheets | D49: Mastercard Valuation: OVERVALUED (–13% Downside)
A50: 9.Data Industry | B50: Refer to linked model sheets | C50: Football Field Valuation Chart
A51: 10.Industry Income Statement | B51: Refer to linked model sheets | C51: Method | D51: Low Value | E51: Range | F51: Target Marker | G51: High Value
A52: 11.Industry Balance Sheet | B52: Refer to linked model sheets | C52: DDM | D52: 60 | E52: =Table43[[#This Row],[Column8]]-Table43[[#This Row],[Column5]] -> 10 | F52: =D56 -> 389.90639 | G52: 70
A53: 12.Industry Cash Flow | B53: Refer to linked model sheets | C53: DCF | D53: 120 | E53: =Table43[[#This Row],[Column8]]-Table43[[#This Row],[Column5]] -> 40 | F53: =F52 -> 389.90639 | G53: 160
A54: 13.Beta Calculation | B54: Refer to linked model sheets | C54: FCFF | D54: 140 | E54: =Table43[[#This Row],[Column8]]-Table43[[#This Row],[Column5]] -> 40 | F54: =F53 -> 389.90639 | G54: 180
A55: 14.Regression | B55: Refer to linked model sheets | C55: Relative Valuation | D55: 55 | E55: =Table43[[#This Row],[Column8]]-Table43[[#This Row],[Column5]] -> 20 | F55: =F54 -> 389.90639 | G55: 75
A56: 15.DCF Valuation | B56: Refer to linked model sheets | C56: Target Price | D56: =E34 -> 389.90639 | E56: =Table43[[#This Row],[Column8]]-Table43[[#This Row],[Column5]] -> 18.163607 | F56: =F55 -> 389.90639 | G56: =408.07 -> 408.07
A57: 16.Valuation Dashboard | B57: Refer to linked model sheets | E57: Valuation Signal
A58: 17.DDM,FCFF,FCFE,Relative Valuation | B58: Refer to linked model sheets | C58: DCF Visual Valuation | D58: DCF Visual Valuation | E58: Intrinsic Value: $390 | F58: Metric | G58: CAGR
A59: 18.Competition (Comparable Company Analysis) | B59: Refer to linked model sheets | C59: Current Market Price | D59: ='DCF Valuation'!B36 -> 450 | E59: Market Price: $450 | F59: Revenue | G59: 0.165
A60: 19.Credit Ratio | B60: Refer to linked model sheets | C60: Target Price | D60: ='DCF Valuation'!B35 -> 386.11179 | E60: Mispricing: -13.4% 🔻 | F60: EPS | G60: 0.214
A61: 20.Ratio Analysis | B61: Refer to linked model sheets | E61: Signal: OVERVALUED
A62: 21.Risk Analysis | B62: Refer to linked model sheets | C62: Premium valuation (~28x EV/EBITDA) suggests limited upside, with ~11% downside despite strong fundamentals | E62: Action: SELL
A63: 22.Investment Recommendation | B63: Refer to linked model sheets
A64: 23.Executive Summary | B64: Refer to linked model sheets | C64: Step | D64: Waterfall Valuation Bridge | E64: Company | F64: EV/EBITDA
A65: 24.Model Flow | B65: Refer to linked model sheets | C65: Revenue | D65: ='Profit Loss'!K4 -> 48749.565 | E65: Visa | F65: 25x
A66: 25.Industry Outlook | B66: Refer to linked model sheets | C66: EBITDA | D66: ='Profit Loss'!K25 -> 29298.489 | E66: Mastercard | F66: 28x
A67: 26.Operational Drivers | B67: Refer to linked model sheets | C67: Taxes | D67: =Assumptions!B14 -> 0.16 | E67: PayPal | F67: 18x
A68: 27.Sensitivity Analysis | B68: Refer to linked model sheets | C68: Capex | D68: ='DCF Valuation'!F21 -> 313.96526 | E68: AmEx | F68: 14x
A69: 28.Scenario Analysis | B69: Refer to linked model sheets | C69: Working Capital | D69: =Balance_Sheet!K50 -> -6907.1686
A70: 29.Documentation Sheet | B70: Refer to linked model sheets | C70: FCF | D70: ='Cash Flow'!K61 -> 26858.749 | E70: Assumptions → Financial Statements → Valuation → Output
A71: 30.Return Metrics | B71: Refer to linked model sheets
A72: 31.WACC | B72: Refer to linked model sheets | C72: FINAL CALL: SELL
A73: 32.CAGR Projections | B73: Refer to linked model sheets | C73: Reason: Overvaluation + limited upside
A74: 33.Audit Checks | B74: Refer to linked model sheets
A75: 34.Assumption Notes | B75: Refer to linked model sheets
H84: +21% CAGR → Strong earnings acceleration
H85: EPS growth > Revenue → Margin expansion & efficiency gains
H86: EPS CAGR (~21%) exceeds revenue CAGR (~16%), indicating strong operating leverage; however, current valuation already prices in this growth.
H88: This model is highly sensitive to WACC and revenue growth assumptions, making accurate forecasting critical for valuation.
H89: Market price exceeds intrinsic value due to elevated valuation multiples despite strong fundamentals
H91: Valuation Insight:
H92: Mastercard demonstrates strong revenue and earnings growth (Revenue CAGR ~16%, EPS CAGR ~21%). However, the current market price ($450) exceeds intrinsic value ($390), indicating ~13% downside due to elevated valuation multiples

Sheet Executive Summary
A1: Financial Modelling & Valuation – Mastercard Inc. Executive Summary
A4: Business Overview
A5: Mastercard Inc. is a global payments technology company operating a global electronic payments network connecting consumers, financial institutions, merchants, and governments. The company earns revenue from transaction processing, cross-border payments, and value-added services. Its asset-light model enables strong scalability, high margins, and consistent growth driven by global digital payment adoption. Time Horizon: near-term (6–12 months) Key Competitors: Visa, PayPal, and emerging fintech disruptors
A11: Key Findings
A12: • Strong revenue and earnings growth • High operating margins and strong free cash flow • Industry leadership in profitability and efficiency • Stable financial position with manageable leverage • Beneficiary of global shift toward cashless transactions • Strong network effects creating high barriers to entry • Strong growth driven by cross-border transactions and digital payment adoption
A20: Fair Value Estimation
A21: Based on forecasted cash flows, growth assumptions, and WACC estimates, Mastercard’s intrinsic value is materially below the current market price, suggesting limited short-term upside despite strong long-term fundamentals. Sensitivity analysis indicates that valuation is moderately dependent on WACC and terminal growth assumptions.
A27: Investment Recommendation
A28: Mastercard demonstrates strong fundamentals, durable competitive advantages, and long-term growth potential within the global digital payments industry. However, the current market price exceeds intrinsic value estimates, resulting in limited upside and unfavorable risk-reward in the near term. Therefore, we recommend a SELL rating, implying ~11–12% downside from current levels.
A34: Numerical Valuation Box
A35: Current Market Price | C35: ='Investment Recommendation'!B42 -> 450 | E35: 🟢 Current Price
A36: Target Price | C36: ='Investment Recommendation'!B43 -> 389.90639 | E36: 🔴 Intrinsic Value
A37: Upside/Downside Potential | C37: ='Investment Recommendation'!B44 -> -0.13354135 | E37: ⚠️ Downside
A38: Recommendation | C38: ='Investment Recommendation'!B45 -> SELL
A40: Financial Highlights
A41: • Revenue CAGR | C41: =Summary!B20 -> 0.16481028
A42: • Operating Margin | C42: =Summary!B23 -> 0.54497449
A43: • ROE | C43: =Summary!B15 -> 1.235841
A44: • Projected Free Cash Flow | C44: =Summary!B16 -> 111160.98
A46: Key Risks
A47: • Regulatory pressure
A48: • Fintech competition
A49: • Global transaction slowdown
A50: • Cybersecurity or payment network disruption
A52: Conclusion: Mastercard remains a high-quality compounder, but current valuation limits near-term upside
A54: Valuation is primarily driven by terminal value, contributing ~65–70% of total enterprise value
A56: Re-entry recommended at $350–$370 range (or fair value band)
A58: Relative valuation (EV/EBITDA, P/E) also indicates a premium valuation, supporting the DCF conclusion.
A60: Investment Thesis
A61: Mastercard presents a strong long-term investment opportunity driven by:
A62: Global digital payments growth (shift from cash to cashless economy)
... A94: Based on DCF and relative valuation, Mastercard appears overvalued, with limited upside and potential downside risk under current assumptions.

Sheet Assumptions
A1: Assumptions | D1: Model Control | E1: Value
A2: 1. Revenue & Macroeconomic Assumptions | C2: Source-based reasoning (IMF, industry growth, etc.) | D2: Base Year | E2: 2024 | G2: Revenue Drivers | H2: 2025 | I2: 2026 | J2: 2027 | K2: 2028 | L2: 2029
A3: Assumption | B3: Value | C3: Basis | D3: Forecast Start | E3: 2025 | G3: Payment Volume Growth (%) | H3: 0.1 | I3: 0.11 | J3: 0.1 | K3: 0.09 | L3: 0.08
A4: Revenue Growth 2025E | B4: =H5 -> 0.12 | C4: Revenue growth is derived using a regression analysis between Mastercard’s historical revenue and GDP growth, indicating strong correlation with macroeconomic expansion and digital payment adoption. | D4: Forecast End | E4: 2029 | G4: Pricing Growth (%) | H4: 0.02 | I4: 0.02 | J4: 0.02 | K4: 0.02 | L4: 0.02
A5: Revenue Growth 2026E | B5: =I5 -> 0.13 | C5: Growth moderates as post-expansion effects stabilize, reflecting normalization after higher-than-trend growth in previous periods | D5: Currency | E5: USD Millions | G5: Total Revenue Growth (%) | H5: =H3+H4 -> 0.12 | I5: =I3+I4 -> 0.13 | J5: =J3+J4 -> 0.12 | K5: =K3+K4 -> 0.11 | L5: =L3+L4 -> 0.1
A6: Revenue Growth 2027E | B6: =J5 -> 0.12 | C6: Growth aligns with global digital payments industry trends, driven by steady transaction volume expansion and fintech adoption. | D6: Model Type: Integrated 3-Statement Financial Model | E6: Key Assumptions (Clean) | G6: Pricing growth is assumed to remain stable due to competitive pressures from Visa and emerging fintech players, which limit pricing expansion despite strong market positioning.
A7: Revenue Growth 2028E | B7: =K5 -> 0.11 | C7: As the company matures, growth gradually declines toward a sustainable long-term rate due to market saturation | D7: Valuation Approach: DCF + Relative Valuation | G7: Cost Driver | H7: 2025 | I7: 2026 | J7: 2027 | K7: 2028 | L7: 2029
A8: Revenue Growth 2029E | B8: =L5 -> 0.1 | C8: Growth approaches a steady-state level, reflecting stable economic expansion and a mature business lifecycle | D8: Forecast Horizon: 5 Years | E8: WACC: 9.48% | G8: Operating Expenses (% of Revenue) | H8: 0.25 | I8: 0.245 | J8: 0.24 | K8: 0.235 | L8: 0.23
A9: Terminal Growth (g) | B9: ='DCF Valuation'!B8 -> 0.03 | C9: Terminal growth reflects mature-stage growth aligned with inflation + GDP (~2–3%) | D9: Purpose: Investment Decision Analysis | E9: Terminal Growth: 3%
A10: Revenue Growth = Volume Growth + Pricing + Cross-border mix impact | C10: Key risk: deviation from GDP or cross-border slowdown can impact growth assumptions. | E10: EBITDA Margin: 55% → 57% | G10: The declining cost structure highlights operating leverage, where revenue growth outpaces cost growth, improving profitability over time
A11: 2. Income Statement Drivers
A12: Assumption | B12: Value | C12: Basis | D12: Revenue Drivers | E12: Investment View | G12: Margin Type | H12: Assumption | I12: Reason
C13: Operating Leverage | G13: EBITDA Margin | H13: Expanding from 55% → 57% | I13: Operating leverage
A14: Tax Rate | B14: 0.16 | C14: Based on the company’s historical effective tax rate, adjusted for global tax structure and geographic revenue mix | D14: Volume Growth: 8–10% | E14: Target Price: $373 | G14: Net Margin | H14: Stable | I14: Mature business
A15: Other Income | B15: -0.01 | C15: Assumes non-core income remains consistent with historical averages, reflecting minimal contribution to core operations. | D15: Pricing: ~2% | E15: Upside: Limited | G15: Margin expansion driven by scale in digital payments and cost efficiency
A16: EBIT Margin Trend | B16: Improving | C16: As revenue grows, fixed costs are spread over a larger base, improving margins due to operating leverage and high-margin digital business model. | D16: Cross-border: 1–2% | E16: Risk: Downside > Upside
A17: Opex Expansion Model | D17: Total Growth: ~11% | G17: Industry Linkage Section
A18: Year | B18: Opex % | C18: Operating Leverage & Automation Efficiency | G18: Factor | H18: Impact
A19: 2025 | B19: 0.45 | C19: 👉 Cost efficiency improves over time due to: | D19: Mastercard benefits from digital payment growth, but current valuation limits upside. | G19: Digital Payments Growth | H19: ↑ Revenue
A20: 2026 | B20: 0.44 | C20: Technology automation | G20: Fintech Competition | H20: ↓ Margins
A21: 2027 | B21: 0.435 | C21: Reduced marginal cost per transaction | G21: Regulation | H21: ↑ Costs
A22: 2028 | B22: 0.43 | C22: Scalable platform economics
A23: 2029 | B23: 0.425 | G23: Scenario | H23: Revenue Growth | I23: Margin | J23: WACC | K23: Terminal g | L23: Target Price
A24: 3.Working Capital Assumptions | G24: Bear | H24: -0.02 | I24: -0.01 | J24: 0.105 | K24: 0.025 | L24: $XXX
A25: Assumption | B25: Value | G25: Base | H25: 0 | I25: 0 | J25: 0.095 | K25: 0.03 | L25: $373
A26: Cash % Revenue | B26: 0.15 | C26: Maintained to ensure liquidity buffer and operational flexibility, consistent with historical treasury strategy. | G26: Bull | H26: 0.02 | I26: 0.01 | J26: 0.09 | K26: 0.035 | L26: $XXX
A27: Accounts Receivable % Revenue | B27: 0.0117 | C27: Low receivables due to fast settlement cycles in digital payment systems. | G27: Scenario analysis reflects sensitivity to key drivers including revenue growth, margins, discount rate, and terminal assumptions
A28: Settlement Assets % Revenue | B28: 0.134 | C28: Reflects funds in transit between institutions, a key characteristic of payment processing companies.
A29: Prepaid Assets % Revenue | B29: 0.08 | C29: Based on historical trends of advance payments and platform-related costs. | G29: Driver | H29: 2025 | I29: 2026 | J29: 2027 | K29: 2028 | L29: 2029
A30: Accrued Expenses % Revenue | B30: 0.369 | C30: High accruals due to transaction-related obligations and operational liabilities | G30: Payment Volume Growth | H30: 0.1 | I30: 0.11 | J30: 0.1 | K30: 0.09 | L30: 0.08
A31: 4. Asset & Investment Drivers | G31: Pricing / Take Rate | H31: 0.02 | I31: 0.02 | J31: 0.02 | K31: 0.02 | L31: 0.02
A32: Assumption | B32: Value | G32: Cross-border Mix | H32: 1–2% | I32: 1–2% | J32: 1–2% | K32: 1–2% | L32: 1–2%
A33: PPE Growth Rate | B33: 0.04 | C33: Moderate growth reflecting limited physical infrastructure needs (asset-light model) | G33: Total Revenue Growth | H33: 0.12 | I33: 0.13 | J33: 0.12 | K33: 0.11 | L33: 0.1
A34: Intangibles Growth Rate | B34: 0.03 | C34: Investment in technology, software, and intellectual property aligned with innovation strategy | G34: Revenue Growth = Payment Volume Growth + Pricing (Take Rate) + Cross-border Mix
A35: Depreciation % Revenue | B35: 0.055 | C35: Based on historical depreciation trends relative to asset base
A36: Capex % Revenue | B36: 0.07 | C36: Reflects continuous investment in:Technology Infrastructure Cyber Security Payment Network Expansion | G36: Driven by transaction volume, pricing power, and cross-border mix
A37: 5. Capital Allocation Assumptions
A38: Assumption | B38: Value
A39: Dividend Payout Ratio | B39: 0.3 | C39: Balanced policy to Reward Shareholders Retain Earnings for Growth | G39: As Mastercard is a mature, large-cap company, growth is expected to normalize over time.
A40: Share Buyback | B40: 0.02 | C40: Reflects consistent capital return strategy and confidence in future cash flows, also improving EPS | G40: This assumption reflects a stable, predictable cash flow profile without exceeding economic growth limits.
A41: 6.Cost of Capital Assumptions (CAPM)
A42: Assumption | B42: Value | G42: Terminal value represents ~70–75% of total enterprise value, making valuation highly sensitive to long-term growth assumptions
A43: Risk Free Rate (CAPM) | B43: 0.042 | C43: US 10-Year Government Bond Yield Represents a risk-free benchmark for long-term investments
A44: Beta | B44: {=Table23[Value]} -> 1.0354654 | C44: Measures stock volatility relative to the market.Slightly above 1 indicates Mastercard is marginally more volatile than the market | G44: A ±0.5% change in terminal growth or WACC can impact valuation by ~10–15%, highlighting the importance of conservative assumptions
A45: Market Return | B45: 0.1 | C45: Based on long-term equity market return expectations.
A46: Cost of Equity (Ke) (CAPM) | B46: =B43+B44*(B45-B43) -> 0.10205699 | C46: Derived using CAPM, representing required return by equity investors | G46: Valuation ranges from $310 (Bear) to $430 (Bull), implying asymmetric risk with limited upside and higher downside at current valuation.
A47: CAPM
A48: WACC Calculation | G48: Scenario | H48: Revenue | I48: Margin | J48: WACC | K48: g | L48: Target Price
A49: Cost of Equity (Ke) (CAPM) | B49: =B46 -> 0.10205699 | G49: Bear | H49: -0.02 | I49: -0.01 | J49: 0.105 | K49: 0.025 | L49: $310 (example)
A50: Cost of Debt | B50: 0.035 | C50: Cost of debt based on investment-grade credit spread over risk-free rate | G50: Base | H50: 0 | I50: 0 | J50: 0.095 | K50: 0.03 | L50: $373
A51: Equity Weight | B51: 0.9 | C51: Based on capital structure dominated by equity financing | G51: Bull | H51: 0.02 | I51: 0.01 | J51: 0.09 | K51: 0.035 | L51: $430 (example)
A52: Debt Weight | B52: 0.1 | C52: Reflects relatively low leverage | G52: Valuation ranges from ~$310 to ~$430, implying asymmetric risk with limited upside and meaningful downside at current levels
A53: WACC | B53: =B51*B49+B52*B50*(1-B14) -> 0.094791294 | C53: Represents overall required return for all capital providers.
G54: Relative valuation (EV/EBITDA, P/E) supports DCF conclusions, indicating premium valuation with limited upside.
A55: Formula
A56: CAPM | B56: Ke = Rf + Beta × (Rm − Rf) | G56: A margin of safety is limited at current levels, as valuation already reflects optimistic growth expectations.
A57: WACC | B57: WACC = E/V × Ke + D/V × Kd × (1 − Tax)
G58: Model outputs are internally consistent and economically grounded
A59: Macroeconomic Drivers
A60: Assumption | B60: Value | C60: Basis | G60: Scenario | H60: Price | I60: Upside/Downside
A61: Global GDP Growth | B61: 0.03 | C61: Source: International Monetary Fund – World Economic Outlook 2024 Rationale: Long-term global GDP trend used as baseline for terminal growth and macro alignment | G61: Bear | H61: 310 | I61: -0.15
A62: Digital Payments Industry Growth | B62: 12–15% | C62: Source: McKinsey & Company – Global Payments Report 2023Source: Statista – Digital Payments Forecast 2024–2028Rationale: Reflects strong structural shift from cash to digital payments | G62: Base | H62: 373 | I62: 0
A63: Equity Risk Premium | B63: 0.058 | C63: Source: Aswath Damodaran – Implied ERP (2024) | G63: Bull | H63: 430 | I63: 0.15
A64: Risk Free Rate | B64: 0.042 | C64: Source: U.S. Department of the Treasury – 10-Year Treasury Yield (2024 avg) | D64: Rationale: Cross-border transactions linked to global trade recovery
A65: Cross-border Volume Growth | B65: 10–12% | C65: Source: World Trade Organization – Global Trade Outlook 2024 Rationale: Cross-border transactions linked to global trade recovery | G65: Current price = $390 → implies -13.4% downside
A67: Sensitivity Inputs
A68: Revenue sensitivity ±1%
A69: Margin sensitivity ±1%
A70: WACC sensitivity ±0.5%
A72: Explanation: All projections are assumption-driven, economically justified, and linked to historical performance, industry dynamics, and macroeconomic expectations
A74: Sensitivity Flag | D74: Revenue Growth Trend (2020-2029
A75: Assumption | B75: Sensitivity | D75: ='Profit Loss'!B4 -> 15301
A76: Revenue Growth | B76: HIGH | D76: ='Profit Loss'!C4 -> 18884
A77: WACC | B77: HIGH | D77: ='Profit Loss'!D4 -> 22237
A78: Terminal Growth | B78: VERY HIGH | D78: ='Profit Loss'!E4 -> 25098
D79: ='Profit Loss'!F4 -> 28167
A80: WACC Section | D80: ='Profit Loss'!G4 -> 31547.04
A81: Component | B81: Value | C81: Source | D81: ='Profit Loss'!H4 -> 35648.155
A82: Risk-Free Rate | B82: 0.042 | C82: US 10Y Treasury | D82: ='Profit Loss'!I4 -> 39925.934
A83: Beta | B83: =B44 -> 1.0354654 | C83: Based on 5-year weekly regression vs S&P 500 | D83: ='Profit Loss'!J4 -> 44317.787
A84: ERP | B84: 0.058 | C84: Market estimate | D84: ='Profit Loss'!K4 -> 48749.565
A85: Cost of Equity | B85: =B46 -> 0.10205699 | C85: CAPM
A87: Sanity Check Section | G87: All assumptions are based on historical trends, industry benchmarks, and reasonable forward-looking estimates aligned with global digital payments growth.
A88: Metric | B88: Value | C88: Comment
A89: Revenue CAGR | B89: ~9% | C89: Reasonable
A90: EBITDA Margin | B90: Increasing | C90: Scale benefit
A91: WACC vs Growth | B91: WACC > g ✔ | C91: Valid
A94: Revenue Drivers (Mastercard Specific)
A95: Transaction Volume Growth 8%
A96: Pricing / Yield Growth 2%
A97: Cross-border Growth 3%
A98: Total Revenue Growth ≈ 10–11%
A99: Sensitive
A100: WACC ↓ / g → | B100: 0.025 | C100: 0.03 | D100: 0.035
A101: 0.09 | B101: High | C101: High | D101: Very High
A102: 0.095 | B102: Mid | C102: Base | D102: High
A103: 0.105 | B103: Low | C103: Low | D103: Mid
A106: Scenario | B106: Revenue Adj | C106: Margin Adj | D106: WACC
A107: Base | B107: 0 | C107: 0 | D107: 0.0952
A108: Bull | B108: 0.02 | C108: 0.01 | D108: 0.09
...

Sheet Assumption Notes
A1: Assumption Notes | J1: Assumption | K1: Value | L1: Explanation
A2: 1. Revenue Growth Assumptions | J2: Revenue Growth | K2: 0.1 | L2: Driven by digital payments growth
J3: Operating Margin | K3: 0.56 | L3: High-margin business model
A4: Base Case Growth Rate: 10% – 12% | J4: WACC | K4: 0.09 | L4: CAPM-based calculation
J5: Terminal Growth | K5: 0.03 | L5: GDP-linked growth
A6: Explanation:
J7: Sensitivity Insight
A8: Mastercard operates in the global digital payments industry, which is growing due to:
A9: Increasing shift from cash → digital payments | J9: “The model is most sensitive to changes in:
A10: E-commerce expansion
A11: Cross-border transactions recovery post-COVID | J11: Revenue growth rate
A12: Historical CAGR of Mastercard supports a double-digit growth range | J12: WACC
A13: Growth is slightly moderated vs past to reflect market maturity | J13: Terminal growth rate
J14: Even a 1% change in these variables significantly impacts valuation
A15: Bull Case: 14% – 16%
A17: Faster adoption of digital payments
A18: Expansion in emerging markets (India, Africa)
A20: Bear Case: 7% – 9%
A22: Economic slowdown
A23: Reduced consumer spending
A25: 2. Operating Margin Assumptions
A27: Base Case Margin: ~55% – 58%
A29: Explanation:
A31: Mastercard has a high-margin business model (asset-light)
A32: Margins are supported by:
A33: Strong pricing power
... A123: Industry positioning
A125: Scenario | B125: Growth | C125: Margin | D125: WACC
A126: Bull | B126: High | C126: Higher | D126: Lower
A127: Base | B127: Moderate | C127: Stable | D127: Normal
A128: Bear | B128: Low | C128: Declining | D128: Higher
A130: MACRO-ECONOMIC DRIVERS | J130: Driver | K130: Assumption | L130: Impact on Model
A131: 1. Global GDP Growth | J131: GDP Growth | K131: 0.03 | L131: Drives revenue growth
A132: Assumption: 2.5% – 3.5% | J132: Inflation | K132: 0.03 | L132: Impacts nominal revenue
J133: Interest Rate | K133: 0.05 | L133: Affects WACC
A134: Why it matters: | J134: Digital Payments Growth | K134: 0.12 | L134: Boosts revenue
J135: Consumer Spending | K135: Moderate | L135: Scenario driver
A136: Mastercard’s revenue is directly linked to consumer spending & economic activity | J136: Cross-border Transactions | K136: High | L136: Margin expansion
A137: Higher GDP → more transactions → higher payment volumes
A139: Model Link:
A140: Revenue Growth = Base Growth + GDP Sensitivity
A142: 2. Inflation Rate
A143: Assumption: 2% – 4%
A145: Why it matters:
A147: Moderate inflation → increases transaction value (positive)
A148: High inflation → reduces real spending (negative)
A150: Model Impact:
A152: Affects nominal revenue growth
A153: Impacts operating costs
A154: Adjusted Revenue Growth = Real Growth + Inflation
... A204: Revenue = Domestic Growth + Cross-border Growth Premium

Sheet WACC
A1: WACC Calculation | F1: WACC = (E/V × Ke) + (D/V × Kd × (1 – Tax))
A2: A | B2: B | F2: WACC reflects Mastercard’s low leverage, strong credit profile, and market-based capital structure
A3: Cost of Equity (CAPM)
A4: Risk Free Rate | B4: =Assumptions!B43 -> 0.042 | F4: DCF value is driven by terminal value discounted at WACC
A5: Market Return | B5: =Assumptions!B45 -> 0.1 | F5: Low cost of debt reflects strong creditworthiness and stable cash flows
A6: Beta | B6: {=Table23[Value]} -> 1.0354654
A7: Cost of Equity | B7: =B4+B6*(B5-B4) -> 0.10205699 | F7: Valuation is highly sensitive to WACC, as a large portion of
A8: Pre-tax Cost of Debt | F8: DCF value is driven by terminal value discounted at WACC
A9: A | B9: B
A10: Pre-tax Cost of Debt | F10: Low WACC is primarily driven by high operating margins and
A11: Interest Expense | B11: =-'Profit Loss'!G15 -> 301.875 | F11: predictable cash flows rather than financial leverage
A12: Total Debt | B12: =Balance_Sheet!G27+Balance_Sheet!G24 -> 17250
A13: Cost of Debt | B13: =Assumptions!B50 -> 0.035 | F13: Given Mastercard’s asset-light model, equity investors bear most of the risk,
A14: A | B14: B | F14: which explains the high equity weight in WACC
A15: Capital Structure
A16: Market Price | B16: 450 | F16: Parameter | G16: Value | H16: Source | I16: Date | J16: Notes
A17: Shares Outstanding | B17: ='Profit Loss'!K24 -> 837.93458 | F17: Risk-Free Rate | G17: 0.042 | H17: RBI / US Treasury | I17: 46082 | J17: 10Y Govt Bond
A18: Market Cap | B18: =B16*B17 -> 377070.56 | F18: Market Return | G18: 0.09 | H18: S&P 500 Historical Avg | I18: 2025 | J18: Long-term avg
A19: Total Debt | B19: =B12 -> 17250 | F19: Beta | G19: 1.15 | H19: Bloomberg / Yahoo Finance | I19: 46082 | J19: 2Y weekly beta
A20: Enterprise Value | B20: =B18+B19 -> 394320.56 | F20: ERP | G20: 0.05 | H20: Damodaran Data | I20: 2025 | J20: US Equity Risk Premium
A21: Capital Weights | F21: Tax Rate | G21: 0.21 | H21: Company Filings | I21: 2024 | J21: Effective tax rate
A22: A | B22: B
A23: Equity Weight | B23: 0.9 | F23: Scenario | G23: Rf | H23: Beta | I23: Market Return
A24: Debt Weight | B24: 0.1 | F24: Base | G24: 0.04 | H24: 1.1 | I24: 0.09
A25: WACC | F25: Bull | G25: 0.035 | H25: 1 | I25: 0.1
A26: A | B26: B | F26: Bear | G26: 0.05 | H26: 1.3 | I26: 0.08
A27: Tax Rate | B27: =Assumptions!B14 -> 0.16
A28: WACC | B28: =(B23*B7)+(B24*B13*(1-B27)) -> 0.094791294
A30: Sources
A31: Risk-Free Rate = 4.2%
A32: Source: US 10Y Treasury Yield (Bloomberg / FRED)
A33: Date: [Latest available date]
A35: Market Risk Premium = 5.8%
A36: Source: Damodaran implied ERP (2025) / Historical US equity returns
A37: Rationale: Long-term US equity premium average
A39: Beta = 1.04
A40: Source: Regression vs S&P 500 (5-year monthly)
A42: Interpretation:
A43: Mastercard is slightly more volatile than the market due to
A44: exposure to global payment volumes and macro cycles
... A75: but valuation remains sensitive to discount rate assumptions.

Sheet CAGR Projections
A1: CAGR Projections | N1: Item | O1: CAGR | P1: Insight
A2: Income Statement CAGR Projection | N2: Revenue | O2: 0.1648 | P2: Strong top-line growth
A3: Item | B3: 2020 | C3: 2021 | D3: 2022 | E3: 2023 | F3: 2024 | G3: CAGR | H3: 2025 | I3: 2026 | J3: 2027 | K3: 2028 | L3: 2029 | N3: Net Income | O3: 0.1904 | P3: Margin expansion
A4: Revenue | B4: =Table1[[#This Row],[2020]] -> 15301 | C4: =Table1[[#This Row],[2021]] -> 18884 | D4: =Table1[[#This Row],[2022]] -> 22237 | E4: =Table1[[#This Row],[2023]] -> 25098 | F4: =Table1[[#This Row],[2024]] -> 28167 | G4: =(Table51[[#This Row],[2024]] / Table51[[#This Row],[2020]])^(1/4)-1 -> 0.16481028 | H4: =F4*(1+$G4) -> 32809.211 | I4: =Table51[[#This Row],[2025]]*(1+Table51[[#This Row],[CAGR]]) -> 38216.506 | J4: =Table51[[#This Row],[2026]]*(1+Table51[[#This Row],[CAGR]]) -> 44514.98 | K4: =Table51[[#This Row],[2027]]*(1+Table51[[#This Row],[CAGR]]) -> 51851.506 | L4: =Table51[[#This Row],[2028]]*(1+Table51[[#This Row],[CAGR]]) -> 60397.167 | N4: FCF | O4: 0.1917 | P4: Strong cash generation
A5: Operating Income | B5: ='Profit Loss'!B11 -> 8081 | C5: ='Profit Loss'!C11 -> 10082 | D5: ='Profit Loss'!D11 -> 12264 | E5: ='Profit Loss'!E11 -> 14008 | F5: ='Profit Loss'!F11 -> 15582 | G5: =(Table51[[#This Row],[2024]] / Table51[[#This Row],[2020]])^(1/4)-1 -> 0.17839129 | H5: =F5*(1+$G5) -> 18361.693 | I5: =Table51[[#This Row],[2025]]*(1+Table51[[#This Row],[CAGR]]) -> 21637.259 | J5: =Table51[[#This Row],[2026]]*(1+Table51[[#This Row],[CAGR]]) -> 25497.158 | K5: =Table51[[#This Row],[2027]]*(1+Table51[[#This Row],[CAGR]]) -> 30045.629 | L5: =Table51[[#This Row],[2028]]*(1+Table51[[#This Row],[CAGR]]) -> 35405.507 | N5: Cash declining → Capital deployment (buybacks/dividends)
A6: Net Income | B6: ='Profit Loss'!B20 -> 6411 | C6: ='Profit Loss'!C20 -> 8687 | D6: ='Profit Loss'!D20 -> 9930 | E6: ='Profit Loss'!E20 -> 11195 | F6: ='Profit Loss'!F20 -> 12874 | G6: =(Table51[[#This Row],[2024]] / Table51[[#This Row],[2020]])^(1/4)-1 -> 0.190411 | H6: =F6*(1+$G6) -> 15325.351 | I6: =Table51[[#This Row],[2025]]*(1+Table51[[#This Row],[CAGR]]) -> 18243.467 | J6: =Table51[[#This Row],[2026]]*(1+Table51[[#This Row],[CAGR]]) -> 21717.223 | K6: =Table51[[#This Row],[2027]]*(1+Table51[[#This Row],[CAGR]]) -> 25852.422 | L6: =Table51[[#This Row],[2028]]*(1+Table51[[#This Row],[CAGR]]) -> 30775.007 | N6: 2020-2024 | O6: Historicals
A7: EPS | B7: ='Profit Loss'!B21 -> 6.4 | C7: ='Profit Loss'!C21 -> 8.79 | D7: ='Profit Loss'!D21 -> 10.26 | E7: ='Profit Loss'!E21 -> 11.86 | F7: ='Profit Loss'!F21 -> 13.91 | G7: =(Table51[[#This Row],[2024]] / Table51[[#This Row],[2020]])^(1/4)-1 -> 0.21419038 | H7: =F7*(1+$G7) -> 16.889388 | I7: =Table51[[#This Row],[2025]]*(1+Table51[[#This Row],[CAGR]]) -> 20.506933 | J7: =Table51[[#This Row],[2026]]*(1+Table51[[#This Row],[CAGR]]) -> 24.899321 | K7: =Table51[[#This Row],[2027]]*(1+Table51[[#This Row],[CAGR]]) -> 30.232516 | L7: =Table51[[#This Row],[2028]]*(1+Table51[[#This Row],[CAGR]]) -> 36.70803 | N7: 2025-2029 | O7: Projections
A9: Balance Sheet CAGR Projection
A10: Item | B10: 2020 | C10: 2021 | D10: 2022 | E10: 2023 | F10: 2024 | G10: CAGR | H10: 2025 | I10: 2026 | J10: 2027 | K10: 2028 | L10: 2029
A11: Total Assets | B11: =Balance_Sheet!B17 -> 33584 | C11: =Balance_Sheet!C17 -> 37669 | D11: =Balance_Sheet!D17 -> 38724 | E11: =Balance_Sheet!E17 -> 42448 | F11: =Balance_Sheet!F17 -> 48081 | G11: =(Table52[[#This Row],[2024]] / Table52[[#This Row],[2020]])^(1/4)-1 -> 0.093856288 | H11: =F11*(1+$G11) -> 52593.704 | I11: =Table52[[#This Row],[2025]]*(1+Table52[[#This Row],[CAGR]]) -> 57529.954 | J11: =Table52[[#This Row],[2026]]*(1+Table52[[#This Row],[CAGR]]) -> 62929.502 | K11: =Table52[[#This Row],[2027]]*(1+Table52[[#This Row],[CAGR]]) -> 68835.831 | L11: =Table52[[#This Row],[2028]]*(1+Table52[[#This Row],[CAGR]]) -> 75296.507
A12: Total Liabilities | B12: =Balance_Sheet!B30 -> 27067 | C12: =Balance_Sheet!C30 -> 30257 | D12: =Balance_Sheet!D30 -> 32347 | E12: =Balance_Sheet!E30 -> 35451 | F12: =Balance_Sheet!F30 -> 41566 | G12: =(Table52[[#This Row],[2024]] / Table52[[#This Row],[2020]])^(1/4)-1 -> 0.11320341 | H12: =F12*(1+$G12) -> 46271.413 | I12: =Table52[[#This Row],[2025]]*(1+Table52[[#This Row],[CAGR]]) -> 51509.495 | J12: =Table52[[#This Row],[2026]]*(1+Table52[[#This Row],[CAGR]]) -> 57340.545 | K12: =Table52[[#This Row],[2027]]*(1+Table52[[#This Row],[CAGR]]) -> 63831.69 | L12: =Table52[[#This Row],[2028]]*(1+Table52[[#This Row],[CAGR]]) -> 71057.655
A13: Shareholders Equity | B13: =Balance_Sheet!B40 -> 6488 | C13: =Balance_Sheet!C40 -> 7383 | D13: =Balance_Sheet!D40 -> 6356 | E13: =Balance_Sheet!E40 -> 6975 | F13: =Balance_Sheet!F40 -> 6515 | G13: =(Table52[[#This Row],[2024]] / Table52[[#This Row],[2020]])^(1/4)-1 -> 0.0010387626 | H13: =F13*(1+$G13) -> 6521.7675 | I13: =Table52[[#This Row],[2025]]*(1+Table52[[#This Row],[CAGR]]) -> 6528.5421 | J13: =Table52[[#This Row],[2026]]*(1+Table52[[#This Row],[CAGR]]) -> 6535.3237 | K13: =Table52[[#This Row],[2027]]*(1+Table52[[#This Row],[CAGR]]) -> 6542.1124 | L13: =Table52[[#This Row],[2028]]*(1+Table52[[#This Row],[CAGR]]) -> 6548.9081
A14: Cash & Cash Equivalents | B14: =Balance_Sheet!B4 -> 10113 | C14: =Balance_Sheet!C4 -> 7421 | D14: =Balance_Sheet!D4 -> 7008 | E14: =Balance_Sheet!E4 -> 8588 | F14: =Balance_Sheet!F4 -> 8442 | G14: =(Table52[[#This Row],[2024]] / Table52[[#This Row],[2020]])^(1/4)-1 -> -0.044146499 | H14: =F14*(1+$G14) -> 8069.3153 | I14: =Table52[[#This Row],[2025]]*(1+Table52[[#This Row],[CAGR]]) -> 7713.0832 | J14: =Table52[[#This Row],[2026]]*(1+Table52[[#This Row],[CAGR]]) -> 7372.5776 | K14: =Table52[[#This Row],[2027]]*(1+Table52[[#This Row],[CAGR]]) -> 7047.1041 | L14: =Table52[[#This Row],[2028]]*(1+Table52[[#This Row],[CAGR]]) -> 6735.9991
A16: Cash Flow Statement CAGR Projection
A17: Item | B17: 2020 | C17: 2021 | D17: 2022 | E17: 2023 | F17: 2024 | G17: CAGR | H17: 2025 | I17: 2026 | J17: 2027 | K17: 2028 | L17: 2029
A18: Operating Cash Flow | B18: ='Cash Flow'!B25 -> 7224 | C18: ='Cash Flow'!C25 -> 9463 | D18: ='Cash Flow'!D25 -> 11195 | E18: ='Cash Flow'!E25 -> 11980 | F18: ='Cash Flow'!F25 -> 14780 | G18: =(Table53[[#This Row],[2024]] / Table53[[#This Row],[2020]])^(1/4)-1 -> 0.19598071 | H18: =F18*(1+$G18) -> 17676.595 | I18: =Table53[[#This Row],[2025]]*(1+Table53[[#This Row],[CAGR]]) -> 21140.866 | J18: =Table53[[#This Row],[2026]]*(1+Table53[[#This Row],[CAGR]]) -> 25284.068 | K18: =Table53[[#This Row],[2027]]*(1+Table53[[#This Row],[CAGR]]) -> 30239.258 | L18: =Table53[[#This Row],[2028]]*(1+Table53[[#This Row],[CAGR]]) -> 36165.569
A19: Investing Cash Flow | B19: ='Cash Flow'!B39 -> -1879 | C19: ='Cash Flow'!C39 -> -5272 | D19: ='Cash Flow'!D39 -> -1470 | E19: ='Cash Flow'!E39 -> -1351 | F19: ='Cash Flow'!F39 -> -3402 | G19: =(Table53[[#This Row],[2024]] / Table53[[#This Row],[2020]])^(1/4)-1 -> 0.15998369 | H19: =AVERAGE(Table53[[#This Row],[2020]:[2024]]) -> -2674.8 | I19: =AVERAGE(Table53[[#This Row],[2020]:[2024]]) -> -2674.8 | J19: =AVERAGE(Table53[[#This Row],[2020]:[2024]]) -> -2674.8 | K19: =AVERAGE(Table53[[#This Row],[2020]:[2024]]) -> -2674.8 | L19: =AVERAGE(Table53[[#This Row],[2020]:[2024]]) -> -2674.8
A20: Financing Cash Flow | B20: ='Cash Flow'!B55 -> -2152 | C20: ='Cash Flow'!C55 -> -6555 | D20: ='Cash Flow'!D55 -> -10328 | E20: ='Cash Flow'!E55 -> -9488 | F20: ='Cash Flow'!F55 -> -10836 | G20: =(Table53[[#This Row],[2024]] / Table53[[#This Row],[2020]])^(1/4)-1 -> 0.4979823 | H20: =AVERAGE(Table53[[#This Row],[2020]:[2024]]) -> -7871.8 | I20: =AVERAGE(Table53[[#This Row],[2020]:[2024]]) -> -7871.8 | J20: =AVERAGE(Table53[[#This Row],[2020]:[2024]]) -> -7871.8 | K20: =AVERAGE(Table53[[#This Row],[2020]:[2024]]) -> -7871.8 | L20: =AVERAGE(Table53[[#This Row],[2020]:[2024]]) -> -7871.8
A21: Free Cash Flow | B21: ='Cash Flow'!B61 -> 7563 | C21: ='Cash Flow'!C61 -> 9870 | D21: ='Cash Flow'!D61 -> 11637 | E21: ='Cash Flow'!E61 -> 12351 | F21: ='Cash Flow'!F61 -> 15254 | G21: =(Table53[[#This Row],[2024]] / Table53[[#This Row],[2020]])^(1/4)-1 -> 0.19171501 | H21: =F21*(1+$G21) -> 18178.421 | I21: =Table53[[#This Row],[2025]]*(1+Table53[[#This Row],[CAGR]]) -> 21663.497 | J21: =Table53[[#This Row],[2026]]*(1+Table53[[#This Row],[CAGR]]) -> 25816.715 | K21: =Table53[[#This Row],[2027]]*(1+Table53[[#This Row],[CAGR]]) -> 30766.166 | L21: =Table53[[#This Row],[2028]]*(1+Table53[[#This Row],[CAGR]]) -> 36664.502
A23: Mastercard demonstrates strong double-digit growth across revenue, earnings, and cash flows, supported by operating leverage and a scalable business model.

Sheet Return Metrics
A1: Return Metrics | I1: Forecast CAGR Summary
A2: Metric | B2: 2024 | C2: 2025E | D2: 2026E | E2: 2027E | F2: 2028E | G2: 2029E | I2: Metrics | J2: 2024 | K2: 2029 | L2: CAGR
A3: ROE | B3: ='Profit Loss'!F20/Balance_Sheet!F40 -> 1.9760553 | C3: ='Profit Loss'!G20/Balance_Sheet!G40 -> 1.4481093 | D3: ='Profit Loss'!H20/Balance_Sheet!H40 -> 1.3672673 | E3: ='Profit Loss'!I20/Balance_Sheet!I40 -> 1.3114309 | F3: ='Profit Loss'!J20/Balance_Sheet!J40 -> 1.2688681 | G3: ='Profit Loss'!K20/Balance_Sheet!K40 -> 1.235841 | I3: Revenue | J3: ='Profit Loss'!F4 -> 28167 | K3: ='Profit Loss'!K4 -> 48749.565 | L3: =(K3/J3)^(1/4)-1 -> 0.14698447
A4: ROA | B4: ='Profit Loss'!F20/Balance_Sheet!F17 -> 0.26775649 | C4: ='Profit Loss'!G20/Balance_Sheet!G17 -> 0.27509523 | D4: ='Profit Loss'!H20/Balance_Sheet!H17 -> 0.29386809 | E4: ='Profit Loss'!I20/Balance_Sheet!I17 -> 0.30930307 | F4: ='Profit Loss'!J20/Balance_Sheet!J17 -> 0.32326605 | G4: ='Profit Loss'!K20/Balance_Sheet!K17 -> 0.33586271 | I4: EBITDA | J4: ='Profit Loss'!F25 -> 16479 | K4: ='Profit Loss'!K25 -> 29298.489 | L4: =(K4/J4)^(1/4)-1 -> 0.15472506
A5: FCF | B5: ='Cash Flow'!F61 -> 15254 | C5: ='Cash Flow'!G61 -> 18784.948 | D5: ='Cash Flow'!H61 -> 19435.742 | E5: ='Cash Flow'!I61 -> 21798.44 | F5: ='Cash Flow'!J61 -> 24283.1 | G5: ='Cash Flow'!K61 -> 26858.749 | I5: EPS | J5: ='Profit Loss'!F23 -> 13.89 | K5: ='Profit Loss'!K23 -> 28.266473 | L5: =(K5/J5)^(1/4)-1 -> 0.19437951
A6: EBIT | B6: ='Profit Loss'!F11 -> 15582 | C6: ='Profit Loss'!G11 -> 17350.872 | D6: ='Profit Loss'!H11 -> 19962.967 | E6: ='Profit Loss'!I11 -> 22558.153 | F6: ='Profit Loss'!J11 -> 25261.138 | G6: ='Profit Loss'!K11 -> 28031 | I6: FCF | J6: ='Cash Flow'!F61 -> 15254 | K6: =G5 -> 26858.749 | L6: =(K6/J6)^(1/4)-1 -> 0.15192846
A7: NOPAT | B7: ='Profit Loss'!F11*(1-Assumptions!B14) -> 13088.88 | C7: ='Profit Loss'!G11*(1-Assumptions!B14) -> 14574.732 | D7: ='Profit Loss'!H11*(1-Assumptions!B14) -> 16768.892 | E7: ='Profit Loss'!I11*(1-Assumptions!B14) -> 18948.848 | F7: ='Profit Loss'!J11*(1-Assumptions!B14) -> 21219.356 | G7: ='Profit Loss'!K11*(1-Assumptions!B14) -> 23546.04
A8: Invested Capital | B8: =(Balance_Sheet!F27+Balance_Sheet!F24)+Balance_Sheet!F40-Balance_Sheet!F4+'Cash Flow'!F25 -> 31079 | C8: =(Balance_Sheet!G27+Balance_Sheet!G24)+Balance_Sheet!G40-Balance_Sheet!G4+'Cash Flow'!G25 -> 36191.725 | D8: =(Balance_Sheet!H27+Balance_Sheet!H24)+Balance_Sheet!H40-Balance_Sheet!H4+'Cash Flow'!H25 -> 38245.39 | E8: =(Balance_Sheet!I27+Balance_Sheet!I24)+Balance_Sheet!I40-Balance_Sheet!I4+'Cash Flow'!I25 -> 42004.924 | F8: =(Balance_Sheet!J27+Balance_Sheet!J24)+Balance_Sheet!J40-Balance_Sheet!J4+'Cash Flow'!J25 -> 45981.971 | G8: =(Balance_Sheet!K27+Balance_Sheet!K24)+Balance_Sheet!K40-Balance_Sheet!K4+'Cash Flow'!K25 -> 50107.434
A9: Average Invested Capital (Beginning + Ending) / 2 | C9: =(B8+C8)/2 -> 33635.362 | D9: =(C8+D8)/2 -> 37218.558 | E9: =(D8+E8)/2 -> 40125.157 | F9: =(E8+F8)/2 -> 43993.448 | G9: =(F8+G8)/2 -> 48044.702
A10: ROIC = NOPAT / Average Invested Capital | B10: =B7/B8 -> 0.42114869 | C10: =C7/B8 -> 0.46895758 | D10: =D7/C8 -> 0.46333498 | E10: =E7/D8 -> 0.49545443 | F10: =F7/E8 -> 0.50516354 | G10: =G7/F8 -> 0.51207113
A11: WACC | B11: 0.0953 | C11: 0.0953 | D11: 0.0953 | E11: 0.0953 | F11: 0.0953 | G11: 0.0953
A12: NOTE
A13: NOPAT = EBIT × (1 − Tax Rate)
A14: ROIC = NOPAT / Average Invested Capital
A15: Invested Capital = Debt + Equity − Excess Cash
A17: Returns Chart
A18: Year | B18: ROIC | C18: ROE | D18: ROA
A19: 2024 | B19: =B10 -> 0.42114869 | C19: =B3 -> 1.9760553 | D19: =B4 -> 0.26775649
A20: 2025 | B20: =C10 -> 0.46895758 | C20: =C3 -> 1.4481093 | D20: =C4 -> 0.27509523
A21: 2026 | B21: =D10 -> 0.46333498 | C21: =D3 -> 1.3672673 | D21: =D4 -> 0.29386809
A22: 2027 | B22: =E10 -> 0.49545443 | C22: =E3 -> 1.3114309 | D22: =E4 -> 0.30930307
A23: 2028 | B23: =F10 -> 0.50516354 | C23: =F3 -> 1.2688681 | D23: =F4 -> 0.32326605
A24: 2029 | B24: =G10 -> 0.51207113 | C24: =G3 -> 1.235841 | D24: =G4 -> 0.33586271
A26: FCF Yield of Invested Capital | D26: Cost of Capital
A27: year | B27: Values | D27: year | E27: Values
A28: 2024 | B28: =B5/B8 -> 0.49081373 | D28: 2024 | E28: =B8*B11 -> 2961.8287
A29: 2025 | B29: =C5/C8 -> 0.51903987 | D29: 2025 | E29: =C8*B11 -> 3449.0714
A30: 2026 | B30: =D5/D8 -> 0.50818521 | D30: 2026 | E30: =D8*B11 -> 3644.7857
A31: 2027 | B31: =E5/E8 -> 0.51894964 | D31: 2027 | E31: =E8*B11 -> 4003.0693
A32: 2028 | B32: =F5/F8 -> 0.52810047 | D32: 2028 | E32: =F8*B11 -> 4382.0818
A33: 2029 | B33: =G5/G8 -> 0.53602323 | D33: 2029 | E33: =G8*B11 -> 4775.2384
A35: Economic Profit | D35: Value Spread
A36: year | B36: Values | D36: year | E36: Values
A37: 2024 | B37: =B7-E28 -> 10127.051 | D37: 2024 | E37: =B10-B11 -> 0.32584869
A38: 2025 | B38: =C7-E29 -> 11125.661 | D38: 2025 | E38: =C10-C11 -> 0.37365758
A39: 2026 | B39: =D7-E30 -> 13124.106 | D39: 2026 | E39: =D10-D11 -> 0.36803498
A40: 2027 | B40: =E7-E31 -> 14945.779 | D40: 2027 | E40: =E10-E11 -> 0.40015443
A41: 2028 | B41: =F7-E32 -> 16837.274 | D41: 2028 | E41: =F10-F11 -> 0.40986354
A42: 2029 | B42: =G7-E33 -> 18770.802 | D42: 2029 | E42: =G10-G11 -> 0.41677113
A44: Note: Declining ROIC due to reinvestment at scale and market maturity

Sheet Audit Checks
A1: Model Audit Checks | B1: =NOW() -> 46123.97
A2: Check | B2: Formula | C2: Status | D2: Description
A3: Balance Sheet | B3: =IF((Balance_Sheet!K36 - (Balance_Sheet!J36 + 'Profit Loss'!K20 + 'Cash Flow'!K42))<1, "OK", IF(ABS(Balance_Sheet!K36 - (Balance_Sheet!J36 + 'Profit Loss'!K20 + 'Cash Flow'!K42))<100, "WARNING", "ERROR")) -> OK | C3: =B3 -> OK | D3: Ensures Assets = Liabilities + Equity; validates overall financial balance
A4: Cash Flow | B4: =IF(ABS('Cash Flow'!K7-'Profit Loss'!K8)<1, "OK", IF(ABS('Cash Flow'!K7-'Profit Loss'!K8)<100, "WARNING", "ERROR")) -> OK | C4: =B4 -> OK | D4: Validates that ending cash equals beginning cash plus net cash flow
A5: Retained Earnings | B5: =IF((Balance_Sheet!K27-(Balance_Sheet!J27+'Cash Flow'!K43-'Cash Flow'!K48))<1, "OK", IF(ABS(Balance_Sheet!K27-(Balance_Sheet!J27+'Cash Flow'!K43-'Cash Flow'!K48))<100, "WARNING", "ERROR")) -> OK | C5: =B5 -> OK | D5: Checks retained earnings roll-forward: Opening RE + Net Income − Dividends
A6: Depreciation Link | B6: =IF(AND(ISNUMBER('Cash Flow'!K23),'Cash Flow'!K23<>0),"OK","ERROR") -> OK | C6: =B6 -> OK | D6: Ensures depreciation is consistently linked across all financial statements
A7: Debt Schedule | B7: =IF((Balance_Sheet!K27-(Balance_Sheet!J27+'Cash Flow'!K43-'Cash Flow'!K48))<1, "OK", IF(ABS(Balance_Sheet!K27-(Balance_Sheet!J27+'Cash Flow'!K43-'Cash Flow'!K48))<100, "WARNING", "ERROR")) -> OK | C7: =B7 -> OK | D7: Validates debt roll-forward: Opening Debt + Borrowings − Repayments
A8: Working Capital | B8: =IF(AND(ISNUMBER('Cash Flow'!K23),'Cash Flow'!K23<>0),"OK","ERROR") -> OK | C8: =B8 -> OK | D8: Ensures change in working capital is correctly calculated and linked
A9: FCFF Check | B9: =IF(ABS('DDM FCFF FCFE RelativeValuation'!H129 - ('DDM FCFF FCFE RelativeValuation'!B129*(1-'DDM FCFF FCFE RelativeValuation'!B116) + 'DDM FCFF FCFE RelativeValuation'!E129 - 'DDM FCFF FCFE RelativeValuation'!F129 - 'DDM FCFF FCFE RelativeValuation'!G129))<1, "OK", IF(ABS('DDM FCFF FCFE RelativeValuation'!H129 - ('DDM FCFF FCFE RelativeValuation'!B129*(1-'DDM FCFF FCFE RelativeValuation'!B116) + 'DDM FCFF FCFE RelativeValuation'!E129 - 'DDM FCFF FCFE RelativeValuation'!F129 - 'DDM FCFF FCFE RelativeValuation'!G129))<100, "WARNING","ERROR")) -> OK | C9: =B9 -> OK | D9: Validates FCFF using NOPAT + D&A − Capex − Change in Working Capital
A10: WACC Check | B10: =IF('DCF Valuation'!B13<=0, "ERROR", IF('DCF Valuation'!B13>1000000000, "WARNING", "OK")) -> OK | C10: =B10 -> OK | D10: Ensures appropriate discount rate based on capital structure
A11: Valuation Check | B11: =IF('Investment Recommendation'!B25<=0, "ERROR", IF('Investment Recommendation'!B25>10000, "WARNING", "OK")) -> OK | C11: =B11 -> OK | D11: Validates DCF outputs to ensure logical and positive valuation results
A12: Master Status | B12: =IF(COUNTIF(C:C,"ERROR")>0, "❌ MODEL HAS ERRORS", IF(COUNTIF(C:C,"WARNING")>0, "⚠️ MODEL HAS WARNINGS", "✅ MODEL IS CLEAN")) -> ✅ MODEL IS CLEAN | C12: =IF(COUNTIF(D:D,"ERROR")>0, "❌ MODEL HAS ERRORS", IF(COUNTIF(D:D,"WARNING")>0, "⚠️ MODEL HAS WARNINGS", "✅ MODEL IS CLEAN")) -> ✅ MODEL IS CLEAN | D12: Summarizes all audit checks to confirm overall model integrity
A13: Errors | B13: =COUNTIF(C:C,"ERROR") -> 0 | C13: =COUNTIF(D:D,"ERROR") -> 0 | D13: Counts critical issues that must be resolved before using the model
A14: Warnings | B14: =COUNTIF(C:C,"WARNING") -> 0 | C14: =COUNTIF(D:D,"WARNING") -> 0 | D14: Highlights non-critical issues or assumptions requiring review
A15: Dynamic Message | B15: =IF(COUNTIF(C:C,"ERROR")>0, "❌ Fix Errors", IF(COUNTIF(C:C,"WARNING")>0, "⚠️ Review Warnings", "✅ Model Ready for Use")) -> ✅ Model Ready for Use | C15: =IF(COUNTIF(D:D,"ERROR")>0, "❌ Fix Errors", IF(COUNTIF(D:D,"WARNING")>0, "⚠️ Review Warnings", "✅ Model Ready for Use")) -> ✅ Model Ready for Use | D15: Displays final model status: ready for use, review warnings, or fix errors
A17: Status Column:
A18: ✅ OK
A19: ⚠️ WARNING
A20: ❌ ERROR

Sheet Profit Loss
A1: Consolidated Statement of Operations - USD ($) shares in Millions, $ in Millions | B1: 2020 | C1: 2021 | D1: 2022 | E1: 2023 | F1: 2024 | G1: 2025E | H1: 2026E | I1: 2027E | J1: 2028E | K1: 2029E
A2: Mastercard Inc | M2: 2020-2024 | N2: Historicals
A3: Income Statement [Abstract] | M3: 2025-2029 | N3: Projections
A4: Net revenue | B4: 15301 | C4: 18884 | D4: 22237 | E4: 25098 | F4: 28167 | G4: =Table1[[#This Row],[2024]]*(1+Assumptions!H5) -> 31547.04 | H4: =Table1[[#This Row],[2025E]]*(1+Assumptions!I5) -> 35648.155 | I4: =Table1[[#This Row],[2026E]]*(1+Assumptions!J5) -> 39925.934 | J4: =Table1[[#This Row],[2027E]]*(1+Assumptions!K5) -> 44317.787 | K4: =Table1[[#This Row],[2028E]]*(1+Assumptions!L5) -> 48749.565
A5: Operating Expenses
A6: General and administrative | B6: 5910 | C6: 7087 | D6: 8078 | E6: 8927 | F6: 10193 | G6: =G4*10% -> 3154.704 | H6: =H4*10% -> 3564.8155 | I6: =I4*10% -> 3992.5934 | J6: =J4*10% -> 4431.7787 | K6: =K4*10% -> 4874.9565
A7: Advertising and marketing | B7: 657 | C7: 895 | D7: 789 | E7: 825 | F7: 815 | G7: =G4*3% -> 946.4112 | H7: =H4*3% -> 1069.4447 | I7: =I4*3% -> 1197.778 | J7: =J4*3% -> 1329.5336 | K7: =K4*3% -> 1462.487
A8: Depreciation and amortization | B8: 580 | C8: 726 | D8: 750 | E8: 799 | F8: 897 | G8: =G4*3% -> 946.4112 | H8: =H4*2.9% -> 1033.7965 | I8: =I4*2.8% -> 1117.9261 | J8: =J4*2.7% -> 1196.5802 | K8: =K4*2.6% -> 1267.4887
A9: Provision for litigation | B9: 73 | C9: 94 | D9: 356 | E9: 539 | F9: 680 | G9: =G4*2% -> 630.9408 | H9: =H4*2% -> 712.9631 | I9: =I4*2% -> 798.51868 | J9: =J4*2% -> 886.35573 | K9: =K4*2% -> 974.9913
A10: Total operating expenses | B10: 7220 | C10: 8802 | D10: 9973 | E10: 11090 | F10: 12585 | G10: =G4*Assumptions!B19 -> 14196.168 | H10: =H4*Assumptions!B20 -> 15685.188 | I10: =I4*Assumptions!B21 -> 17367.781 | J10: =J4*Assumptions!B22 -> 19056.648 | K10: =K4*Assumptions!B23 -> 20718.565
A11: Operating income (EBIT) | B11: 8081 | C11: 10082 | D11: 12264 | E11: 14008 | F11: 15582 | G11: =(G4-G10) -> 17350.872 | H11: =(H4-H10) -> 19962.967 | I11: =(I4-I10) -> 22558.153 | J11: =(J4-J10) -> 25261.138 | K11: =(K4-K10) -> 28031
A12: Other Income (Expense)
A13: Investment income | B13: 24 | C13: 11 | D13: 61 | E13: 274 | F13: 327 | G13: =Table1[[#This Row],[2024]]*1.04 -> 340.08 | H13: =Table1[[#This Row],[2025E]]*1.04 -> 353.6832 | I13: =Table1[[#This Row],[2026E]]*1.04 -> 367.83053 | J13: =Table1[[#This Row],[2027E]]*1.04 -> 382.54375 | K13: =Table1[[#This Row],[2028E]]*1.04 -> 397.8455
A14: Gains (losses) on equity investments, net | B14: 30 | C14: 645 | D14: -145 | E14: -61 | F14: -29 | G14: 0 | H14: 0 | I14: 0 | J14: 0 | K14: 0
A15: Interest expense | B15: -380 | C15: -431 | D15: -471 | E15: -575 | F15: -646 | G15: =G38 -> -301.875 | H15: =H38 -> -284.375 | I15: =I38 -> -266.875 | J15: =J38 -> -249.375 | K15: =K38 -> -231.875
A16: Other income (expense), net | B16: 5 | C16: 0 | D16: 23 | E16: -7 | F16: 20 | G16: 0 | H16: 0 | I16: 0 | J16: 0 | K16: 0
A17: Total other income (expense) | B17: -321 | C17: 225 | D17: -532 | E17: -369 | F17: -328 | G17: =G13+G14+G15+G16 -> 38.205 | H17: =H13+H14+H15+H16 -> 69.3082 | I17: =I13+I14+I15+I16 -> 100.95553 | J17: =J13+J14+J15+J16 -> 133.16875 | K17: =K13+K14+K15+K16 -> 165.9705
A18: Income before income taxes | B18: 7760 | C18: 10307 | D18: 11732 | E18: 13639 | F18: 15254 | G18: =G11+G17 -> 17389.077 | H18: =H11+H17 -> 20032.275 | I18: =I11+I17 -> 22659.108 | J18: =J11+J17 -> 25394.307 | K18: =K11+K17 -> 28196.97
A19: Income tax expense | B19: 1349 | C19: 1620 | D19: 1802 | E19: 2444 | F19: 2380 | G19: =G18*16% -> 2782.2523 | H19: =H18*16% -> 3205.164 | I19: =I18*16% -> 3625.4573 | J19: =J18*16% -> 4063.0891 | K19: =K18*16% -> 4511.5153
A20: Net Income | B20: 6411 | C20: 8687 | D20: 9930 | E20: 11195 | F20: 12874 | G20: =G18-G19 -> 14606.825 | H20: =H18-H19 -> 16827.111 | I20: =I18-I19 -> 19033.651 | J20: =J18-J19 -> 21331.218 | K20: =K18-K19 -> 23685.455
A21: Basic Earnings per Share | B21: 6.4 | C21: 8.79 | D21: 10.26 | E21: 11.86 | F21: 13.91 | G21: =G20/G22 -> 16.11343 | H21: =H20/H22 -> 18.941557 | I21: =I20/I22 -> 21.862617 | J21: =J20/J22 -> 25.001704 | K21: =K20/K22 -> 28.32759
A22: Basic weighted-average shares outstanding | B22: 1002 | C22: 988 | D22: 968 | E22: 944 | F22: 925 | G22: =Table1[[#This Row],[2024]]*(1-2%) -> 906.5 | H22: =Table1[[#This Row],[2025E]]*(1-2%) -> 888.37 | I22: =Table1[[#This Row],[2026E]]*(1-2%) -> 870.6026 | J22: =Table1[[#This Row],[2027E]]*(1-2%) -> 853.19055 | K22: =Table1[[#This Row],[2028E]]*(1-2%) -> 836.12674
A23: Diluted Earnings per Share | B23: 6.37 | C23: 8.76 | D23: 10.22 | E23: 11.83 | F23: 13.89 | G23: =G20/G24 -> 16.078666 | H23: =H20/H24 -> 18.900691 | I23: =I20/I24 -> 21.815448 | J23: =J20/J24 -> 24.947763 | K23: =K20/K24 -> 28.266473
A24: Diluted weighted-average shares outstanding | B24: 1006 | C24: 992 | D24: 971 | E24: 946 | F24: 927 | G24: =Table1[[#This Row],[2024]]*(1-Assumptions!B40) -> 908.46 | H24: =Table1[[#This Row],[2025E]]*(1-Assumptions!B40) -> 890.2908 | I24: =Table1[[#This Row],[2026E]]*(1-Assumptions!B40) -> 872.48498 | J24: =Table1[[#This Row],[2027E]]*(1-Assumptions!B40) -> 855.03528 | K24: =Table1[[#This Row],[2028E]]*(1-Assumptions!B40) -> 837.93458
A25: EBITDA | B25: =B11+B8 -> 8661 | C25: =C11+C8 -> 10808 | D25: =D11+D8 -> 13014 | E25: =E11+E8 -> 14807 | F25: =F11+F8 -> 16479 | G25: =G11+G8 -> 18297.283 | H25: =H11+H8 -> 20996.763 | I25: =I11+I8 -> 23676.079 | ... K25: =K11+K8 -> 29298.489
A26: Operating Margin | B26: =B11/B4 -> 0.52813542 | C26: =C11/C4 -> 0.53389112 | D26: =D11/D4 -> 0.55151324 | E26: =E11/E4 -> 0.55813212 | F26: =F11/F4 -> 0.55320055 | G26: =G11/G4 -> 0.55 | H26: =H11/H4 -> 0.56 | I26: =I11/I4 -> 0.565 | ... K26: =K11/K4 -> 0.575
A27: Net Margin | B27: =B20/B4 -> 0.41899222 | C27: =C20/C4 -> 0.46001906 | D27: =D20/D4 -> 0.44655304 | E27: =E20/E4 -> 0.44605148 | F27: =F20/F4 -> 0.45705968 | G27: =G20/G4 -> 0.46301728 | H27: =H20/H4 -> 0.47203315 | I27: =I20/I4 -> 0.476724 | ... K27: =K20/K4 -> 0.48585982
A28: Total | B28: =SUM(B4:B27) -> 63382.717 | C28: =SUM(C4:C27) -> 80440.544 | D28: =SUM(D4:D27) -> 91821.478 | E28: =SUM(E4:E27) -> 104547.69 | F28: =SUM(F4:F27) -> 117130.81 | G28: =SUM(G4:G27) -> 123772.56 | H28: =SUM(H4:H27) -> 140694.8 | I28: =SUM(I4:I27) -> 157942.7 | ... K28: =SUM(K4:K27) -> 193835.14
A29: Revenue growth is driven by increasing payment volumes and pricing power, while margin expansion reflects operating leverage in a scalable payment network. Share buybacks enhance EPS growth, reinforcing Mastercard’s strong earnings compounding profile.
A30: Interest expense increases in line with projected debt levels and higher interest rates
A31: Model assumes stable competitive positioning and continued global shift toward digital payments
A32: Mastercard benefits from strong network effects and an asset-light model, enabling high margins and predictable long-term cash flows
A34: Interest Expense | B34: 2020 | C34: 2021 | D34: 2022 | E34: 2023 | F34: 2024 | G34: 2025 | H34: 2026 | I34: 2027 | J34: 2028 | K34: 2029
A35: =Balance_Sheet!A27 -> Long-term debt | B35: =Balance_Sheet!B27 -> 12023 | C35: =Balance_Sheet!C27 -> 13109 | D35: =Balance_Sheet!D27 -> 13749 | E35: =Balance_Sheet!E27 -> 14344 | F35: =Balance_Sheet!F27 -> 17476 | G35: =Balance_Sheet!G27 -> 16500 | H35: =Balance_Sheet!H27 -> 15500 | ... K35: =Balance_Sheet!K27 -> 12500
A36: =Balance_Sheet!A24 -> Current portion of long-term debt | B36: =Balance_Sheet!B24 -> 649 | C36: =Balance_Sheet!C24 -> 792 | D36: =Balance_Sheet!D24 -> 274 | E36: =Balance_Sheet!E24 -> 1337 | F36: =Balance_Sheet!F24 -> 750 | G36: =Balance_Sheet!G24 -> 750 | H36: =Balance_Sheet!H24 -> 750 | ... K36: =Balance_Sheet!K24 -> 750
A37: Average Debt | B37: =(B35+B36)/2 -> 6336 | C37: =(C35+C36)/2 -> 6950.5 | D37: =(D35+D36)/2 -> 7011.5 | E37: =(E35+E36)/2 -> 7840.5 | F37: =(F35+F36)/2 -> 9113 | G37: =(G35+G36)/2 -> 8625 | H37: =(H35+H36)/2 -> 8125 | I37: =(I35+I36)/2 -> 7625 | ... K37: =(K35+K36)/2 -> 6625
A38: Interest Expense*Cost of Debt Assumption | B38: =-B37*Assumptions!B50 -> -221.76 | C38: =-C37*Assumptions!B50 -> -243.2675 | D38: =-D37*Assumptions!B50 -> -245.4025 | E38: =-E37*Assumptions!B50 -> -274.4175 | F38: =-F37*Assumptions!B50 -> -318.955 | G38: =-G37*Assumptions!B50 -> -301.875 | H38: =-H37*Assumptions!B50 -> -284.375 | I38: =-I37*Assumptions!B50 -> -266.875 | J38: =-J37*Assumptions!B50 -> -249.375 | K38: =-K37*Assumptions!B50 -> -231.875

Sheet Balance_Sheet
A1: Consolidated Balance Sheet - USD ($) $ in Millions | B1: 2020 | C1: 2021 | D1: 2022 | E1: 2023 | F1: 2024 | G1: 2025E | H1: 2026E | I1: 2027E | J1: 2028E | K1: 2029E
A2: Mastercard Inc | M2: 2020-2024 | N2: Historicals
A3: Assets | M3: 2025-2029 | N3: Projections
A4: Cash and cash equivalents | B4: 10113 | C4: 7421 | D4: 7008 | E4: 8588 | F4: 8442 | G4: ='Cash Flow'!G59 -> 9432.348 | H4: ='Cash Flow'!H59 -> 9224.8772 | I4: ='Cash Flow'!I59 -> 9008.4526 | J4: ='Cash Flow'!J59 -> 8786.1974 | K4: ='Cash Flow'!K59 -> 8561.8128
A5: Restricted Cash | B5: 586 | C5: 586 | D5: 589 | E5: 32 | F5: 492 | G5: 492 | H5: 492 | I5: 492 | J5: 492 | K5: 492
A6: Investments | B6: 483 | C6: 473 | D6: 400 | E6: 1845 | F6: 1874 | G6: 1874 | H6: 1874 | I6: 1874 | J6: 1874 | K6: 1874
A7: Accounts receivable | B7: 2646 | C7: 3006 | D7: 3425 | E7: 592 | F7: 330 | G7: ='Profit Loss'!G4*Assumptions!B27 -> 369.10037 | H7: ='Profit Loss'!H4*Assumptions!B27 -> 417.08342 | I7: ='Profit Loss'!I4*Assumptions!B27 -> 467.13343 | J7: ='Profit Loss'!J4*Assumptions!B27 -> 518.5181 | K7: ='Profit Loss'!K4*Assumptions!B27 -> 570.36991
A8: Settlement assets | B8: 1706 | C8: 1319 | D8: 1270 | E8: 4060 | F8: 3773 | G8: ='Profit Loss'!G4*Assumptions!B28 -> 4227.3034 | H8: ='Profit Loss'!H4*Assumptions!B28 -> 4776.8528 | I8: ='Profit Loss'!I4*Assumptions!B28 -> 5350.0751 | J8: ='Profit Loss'!J4*Assumptions!B28 -> 5938.5834 | K8: ='Profit Loss'!K4*Assumptions!B28 -> 6532.4417
A9: Restricted security deposits held for customers | B9: 1696 | C9: 1873 | D9: 1568 | E9: 1233 | F9: 1821 | G9: 1821 | H9: 1821 | I9: 1821 | J9: 1821 | K9: 1821
A10: Prepaid expenses and other current assets | B10: 1883 | C10: 2271 | D10: 2346 | E10: 2611 | F10: 2992 | G10: ='Profit Loss'!G4*Assumptions!B29 -> 2523.7632 | H10: ='Profit Loss'!H4*Assumptions!B29 -> 2851.8524 | I10: ='Profit Loss'!I4*Assumptions!B29 -> 3194.0747 | J10: ='Profit Loss'!J4*Assumptions!B29 -> 3545.4229 | K10: ='Profit Loss'!K4*Assumptions!B29 -> 3899.9652
A11: Total current assets | B11: =SUM(B4:B10) -> 19113 | C11: =SUM(C4:C10) -> 16949 | D11: =SUM(D4:D10) -> 16606 | E11: =SUM(E4:E10) -> 18961 | F11: =SUM(F4:F10) -> 19724 | G11: =SUM(G4:G10) -> 20739.515 | H11: =SUM(H4:H10) -> 21457.666 | I11: =SUM(I4:I10) -> 22206.736 | ... K11: =SUM(K4:K10) -> 23751.59
A12: Property, equipment and right-of-use assets, net | B12: 1902 | C12: 1907 | D12: 2006 | E12: 2061 | F12: 2138 | G12: =Table2[[#This Row],[2024]]*(1+4%) -> 2223.52 | H12: =Table2[[#This Row],[2025E]]*(1+4%) -> 2312.4608 | I12: =Table2[[#This Row],[2026E]]*(1+4%) -> 2404.9592 | J12: =Table2[[#This Row],[2027E]]*(1+4%) -> 2501.1576 | K12: =Table2[[#This Row],[2028E]]*(1+4%) -> 2601.2039
A13: Deferred income taxes | B13: 491 | C13: 486 | D13: 1151 | E13: 1355 | F13: 1614 | G13: 1614 | H13: 1614 | I13: 1614 | J13: 1614 | K13: 1614
A14: Goodwill | B14: 4960 | C14: 7662 | D14: 7522 | E14: 7660 | F14: 9193 | G14: 9193 | H14: 9193 | I14: 9193 | J14: 9193 | K14: 9193
A15: Other intangible assets, net | B15: 1753 | C15: 3671 | D15: 3859 | E15: 4086 | F15: 5453 | G15: =Table2[[#This Row],[2024]]*(1+3%) -> 5616.59 | H15: =Table2[[#This Row],[2025E]]*(1+3%) -> 5785.0877 | I15: =Table2[[#This Row],[2026E]]*(1+3%) -> 5958.6403 | J15: =Table2[[#This Row],[2027E]]*(1+3%) -> 6137.3995 | K15: =Table2[[#This Row],[2028E]]*(1+3%) -> 6321.5215
A16: Other assets | B16: 5365 | C16: 6994 | D16: 7580 | E16: 8325 | F16: 9959 | G16: ='Profit Loss'!G4*Assumptions!H5 -> 3785.6448 | H16: ='Profit Loss'!H4*Assumptions!I5 -> 4634.2602 | I16: ='Profit Loss'!I4*Assumptions!J5 -> 4791.1121 | J16: ='Profit Loss'!J4*Assumptions!K5 -> 4874.9565 | K16: ='Profit Loss'!K4*Assumptions!L5 -> 4874.9565
A17: Total Assets | B17: 33584 | C17: 37669 | D17: 38724 | E17: 42448 | F17: 48081 | G17: =G30+G40 -> 53097.339 | H17: =H30+H40 -> 57260.762 | I17: =I30+I40 -> 61537.22 | J17: =J30+J40 -> 65986.57 | K17: =K30+K40 -> 70521.242
A18: Liabilities, Redeemable Non-controlling Interests and Equity
A19: Accounts payable | B19: 527 | C19: 738 | D19: 926 | E19: 834 | F19: 929 | G19: ='Profit Loss'!G4*3.3% -> 1041.0523 | H19: ='Profit Loss'!H4*3.3% -> 1176.3891 | I19: ='Profit Loss'!I4*3.3% -> 1317.5558 | J19: ='Profit Loss'!J4*3.3% -> 1462.487 | K19: ='Profit Loss'!K4*3.3% -> 1608.7357
A20: Settlement obligations | B20: 1475 | C20: 913 | D20: 1111 | E20: 1399 | F20: 2316 | G20: ='Profit Loss'!G4*8.2% -> 2586.8573 | H20: ='Profit Loss'!H4*8.2% -> 2923.1487 | I20: ='Profit Loss'!I4*8.2% -> 3273.9266 | J20: ='Profit Loss'!J4*8.2% -> 3634.0585 | K20: ='Profit Loss'!K4*8.2% -> 3997.4643
A21: Restricted security deposits held for customers | B21: 1696 | C21: 1873 | D21: 1568 | E21: 1845 | F21: 1874 | G21: 1874 | H21: 1874 | I21: 1874 | J21: 1874 | K21: 1874
A22: Accrued litigation | B22: 842 | C22: 840 | D22: 1094 | E22: 723 | F22: 930 | G22: 930 | H22: 930 | I22: 930 | J22: 930 | K22: 930
A23: Accrued expenses | B23: 5430 | C23: 6642 | D23: 7801 | E23: 8517 | F23: 10393 | G23: ='Profit Loss'!G4*36.9% -> 11640.858 | H23: ='Profit Loss'!H4*36.9% -> 13154.169 | I23: ='Profit Loss'!I4*36.9% -> 14732.67 | J23: ='Profit Loss'!J4*36.9% -> 16353.263 | K23: ='Profit Loss'!K4*36.9% -> 17988.59
A24: Current portion of long-term debt | B24: 649 | C24: 792 | D24: 274 | E24: 1337 | F24: 750 | G24: 750 | H24: 750 | I24: 750 | J24: 750 | K24: 750
A25: Other current liabilities | B25: 1228 | C25: 1364 | D25: 1397 | E25: 1609 | F25: 2028 | G25: ='Profit Loss'!G4*7.2% -> 2271.3869 | H25: ='Profit Loss'!H4*7.2% -> 2566.6672 | I25: ='Profit Loss'!I4*7.2% -> 2874.6672 | J25: ='Profit Loss'!J4*7.2% -> 3190.8806 | K25: ='Profit Loss'!K4*7.2% -> 3509.9687
A26: Total current liabilities | B26: 11847 | C26: 13162 | D26: 14171 | E26: 16264 | F26: 19220 | G26: =SUM(G19:G25) -> 21094.154 | H26: =SUM(H19:H25) -> 23374.374 | I26: =SUM(I19:I25) -> 25752.819 | J26: =SUM(J19:J25) -> 28194.689 | K26: =SUM(K19:K25) -> 30658.758
A27: Long-term debt | B27: 12023 | C27: 13109 | D27: 13749 | E27: 14344 | F27: 17476 | G27: 16500 | H27: 15500 | I27: 14500 | J27: 13500 | K27: 12500
A28: Deferred income taxes | B28: 86 | C28: 395 | D28: 393 | E28: 369 | F28: 317 | G28: 317 | H28: 317 | I28: 317 | J28: 317 | K28: 317
A29: Other liabilities | B29: 3111 | C29: 3591 | D29: 4034 | E29: 4474 | F29: 4553 | G29: =Table2[[#This Row],[2024]]*(1+Assumptions!B4) -> 5099.36 | H29: =Table2[[#This Row],[2025E]]*(1+Assumptions!B5) -> 5762.2768 | I29: =Table2[[#This Row],[2026E]]*(1+Assumptions!B6) -> 6453.75 | J29: =Table2[[#This Row],[2027E]]*(1+Assumptions!B7) -> 7163.6625 | K29: =Table2[[#This Row],[2028E]]*(1+Assumptions!B8) -> 7880.0288
A30: Total Liabilities | B30: 27067 | C30: 30257 | D30: 32347 | E30: 35451 | F30: 41566 | G30: =G26+G27+G28+G29 -> 43010.514 | H30: =H26+H27+H28+H29 -> 44953.651 | I30: =I26+I27+I28+I29 -> 47023.569 | J30: =J26+J27+J28+J29 -> 49175.352 | K30: =K26+K27+K28+K29 -> 51355.787
A31: Commitments and Contingencies
A32: Redeemable non-controlling interests | B32: 29 | C32: 29 | D32: 21 | E32: 22 | F32: 0 | G32: 0 | H32: 0 | I32: 0 | J32: 0 | K32: 0
A33: Stockholders’ Equity
A34: Additional paid-in-capital | B34: 4982 | C34: 5061 | D34: 5298 | E34: 5893 | F34: 6442 | G34: 6442 | H34: 6442 | I34: 6442 | J34: 6442 | K34: 6442
A35: Class A treasury stock, at cost, 425 and 409 shares, respectively | B35: -36658 | C35: -42588 | D35: -51354 | E35: -60429 | F35: -71431 | G35: =Table2[[#This Row],[2024]]+('Cash Flow'!G41) -> -78083.953 | H35: =Table2[[#This Row],[2024]]+('Cash Flow'!H41) -> -77417.867 | I35: =Table2[[#This Row],[2024]]+('Cash Flow'!I41) -> -76755.905 | J35: =Table2[[#This Row],[2024]]+('Cash Flow'!J41) -> -76066.635 | K35: =Table2[[#This Row],[2024]]+('Cash Flow'!K41) -> -75360.363
A36: Retained earnings | B36: 38747 | C36: 45648 | D36: 53607 | E36: 62564 | F36: 72907 | G36: =Table2[[#This Row],[2024]]+'Profit Loss'!G20+'Cash Flow'!G42 -> 83131.777 | H36: =Table2[[#This Row],[2024]]+'Profit Loss'!H20+'Cash Flow'!H42 -> 84685.978 | I36: =Table2[[#This Row],[2024]]+'Profit Loss'!I20+'Cash Flow'!I42 -> 86230.556 | J36: =Table2[[#This Row],[2024]]+'Profit Loss'!J20+'Cash Flow'!J42 -> 87838.853 | K36: =Table2[[#This Row],[2024]]+'Profit Loss'!K20+'Cash Flow'!K42 -> 89486.819
A37: Accumulated other comprehensive income (loss) | B37: -680 | C37: -809 | D37: -1253 | E37: -1099 | F37: -1433 | G37: -1433 | H37: -1433 | I37: -1433 | J37: -1433 | K37: -1433
A38: Mastercard Incorporated Stockholders' Equity | B38: 6391 | C38: 7312 | D38: 6298 | E38: 6929 | F38: 6485 | G38: =G34+G36+G35+G37 -> 10056.825 | H38: =H34+H36+H35+H37 -> 12277.111 | I38: =I34+I36+I35+I37 -> 14483.651 | J38: =J34+J36+J35+J37 -> 16781.218 | K38: =K34+K36+K35+K37 -> 19135.455
A39: Non-controlling interests | B39: 97 | C39: 71 | D39: 58 | E39: 46 | F39: 30 | G39: 30 | H39: 30 | I39: 30 | J39: 30 | K39: 30
A40: Total Equity | B40: =B38+B39 -> 6488 | C40: =C38+C39 -> 7383 | D40: =D38+D39 -> 6356 | E40: =E38+E39 -> 6975 | F40: =F38+F39 -> 6515 | G40: =G38+G39 -> 10086.825 | H40: =H38+H39 -> 12307.111 | I40: =I38+I39 -> 14513.651 | ... K40: =K38+K39 -> 19165.455
A41: Total Liabilities, Redeemable Non-controlling Interests and Equity | B41: 33584 | C41: 37669 | D41: 38724 | E41: 42448 | F41: 48081 | G41: =G30+G40 -> 53097.339 | H41: =H30+H40 -> 57260.762 | I41: =I30+I40 -> 61537.22 | J41: =J30+J40 -> 65986.57 | K41: =K30+K40 -> 70521.242
A42: Class A Common Stock
A43: Stockholders’ Equity
A44: Common stock value | B44: 0 | C44: 0 | D44: 0 | E44: 0 | F44: 0 | G44: 0 | H44: 0 | I44: 0 | J44: 0 | K44: 0
A45: Class B Common Stock
A46: Stockholders’ Equity
A47: NOPAT | B47: ='Profit Loss'!B11*(1-0.25) -> 6060.75 | C47: ='Profit Loss'!C11*(1-0.25) -> 7561.5 | D47: ='Profit Loss'!D11*(1-0.25) -> 9198 | E47: ='Profit Loss'!E11*(1-0.25) -> 10506 | F47: ='Profit Loss'!F11*(1-0.25) -> 11686.5 | G47: ='Profit Loss'!G11*(1-0.25) -> 13013.154 | H47: ='Profit Loss'!H11*(1-0.25) -> 14972.225 | I47: ='Profit Loss'!I11*(1-0.25) -> 16918.614 | ... K47: ='Profit Loss'!K11*(1-0.25) -> 21023.25
A48: Invested Capital | B48: =B50+B12+B15+B16 -> 16286 | C48: =C50+C12+C15+C16 -> 16359 | D48: =D50+D12+D15+D16 -> 15880 | E48: =E50+E12+E15+E16 -> 17169 | F48: =F50+F12+F15+F16 -> 18054 | G48: =G50+G12+G15+G16 -> 11271.115 | H48: =H50+H12+H15+H16 -> 10815.1 | I48: =I50+I12+I15+I16 -> 9608.6282 | ... K48: =K50+K12+K15+K16 -> 6890.5134
A49: ROIC | B49: =B47/B48 -> 0.37214479 | C49: =C47/C48 -> 0.46222263 | D49: =D47/D48 -> 0.57921914 | E49: =E47/E48 -> 0.61191683 | F49: =F47/F48 -> 0.64730808 | G49: =MIN(G47/G48,C63) -> 0.76 | H49: =MIN(H47/H48,C64) -> 0.78 | I49: =MIN(I47/I48,C65) -> 0.76 | J49: =MIN(J47/J48,C66) -> 0.72 | K49: =MIN(K47/K48,C67) -> 0.7
A50: Total Working Capital | B50: =B11-B26 -> 7266 | C50: =C11-C26 -> 3787 | D50: =D11-D26 -> 2435 | E50: =E11-E26 -> 2697 | F50: =F11-F26 -> 504 | G50: =G11-G26 -> -354.63931 | H50: =H11-H26 -> -1916.7084 | I50: =I11-I26 -> -3546.0834 | ... K50: =K11-K26 -> -6907.1686
A51: Change in Working Capital | B51: =B50 -> 7266 | C51: =-B50-(C50) -> -11053 | D51: =-C50-(D50) -> -6222 | E51: =-D50-(E50) -> -5132 | F51: =-E50-(F50) -> -3201 | G51: =-F50-(G50) -> -149.36069 | H51: =-G50-(H50) -> 2271.3477 | I51: =-H50-(I50) -> 5462.7918 | J51: =-I50-(J50) -> 8765.0509 | K51: =-J50-(K50) -> 12126.136
A52: Common stock value | B52: 0 | C52: 0 | D52: 0 | E52: 0 | F52: 0 | G52: 0 | H52: 0 | I52: 0 | J52: 0 | K52: 0
A53: Total | B53: =B17-B30+B40 -> 13005 | C53: =C17-C30+C40 -> 14795 | D53: =D17-D30+D40 -> 12733 | E53: =E17-E30+E40 -> 13972 | F53: =F17-F30+F40 -> 13030 | G53: =G17-G30+G40 -> 20173.649 | H53: =H17-H30+H40 -> 24614.222 | I53: =I17-I30+I40 -> 29027.302 | ... K53: =K17-K30+K40 -> 38330.91
A54: Fluctuations in working capital are driven by settlement balances and timing differences in customer transactions
A55: Debt remains stable due to strong internal cash generation
A56: The balance sheet reflects a capital-light business model with strong cash generation, increasing retained earnings, and consistent shareholder returns through buybacks. Negative working capital dynamics enhance liquidity, while stable debt levels indicate limited reliance on external financing.
A57: Assumes excess free cash flow is used to repay debt before buybacks
A58: ROIC normalizes to ~70% in the long term, reflecting sustained competitive advantages while incorporating realistic assumptions on competition and market maturity
A59: The significant ROIC–WACC spread indicates strong value creation and justifies Mastercard’s premium valuation multiples.
A62: ROIC Normalization | B62: Old ROIC | C62: ✅ Fixed ROIC | E62: Metrics | F62: Value
A63: 2025 | B63: 0.76 | C63: 0.76 | E63: ROIC | F63: 0.7
A64: 2026 | B64: 0.81 | C64: 0.78 | E64: WACC | F64: 0.09
A65: 2027 | B65: 0.85 | C65: 0.76 | E65: Spread | F65: 0.61
A66: 2028 | B66: 0.88 | C66: 0.72
A67: 2029 | B67: 0.91 | C67: 0.7 | E67: KPI | F67: Value
A68: ROIC = NOPAT / Invested Capital | E68: Revenue CAGR | F68: ~12%
A69: Invested Capital = | E69: EBITDA Margin | F69: ~58%
A70: Total Debt + Equity - Cash | E70: ROIC | F70: 0.7
A71: Invested Capital = Operating Assets – Operating Liabilities | E71: WACC | F71: 0.09
A72: (Proxy: Debt + Equity – Excess Cash)

Sheet Cash Flow
A1: Consolidated Statement of Cash Flows - USD ($) $ in Millions | B1: 2020 | C1: 2021 | D1: 2022 | E1: 2023 | F1: 2024 | G1: 2025E | H1: 2026E | I1: 2027E | J1: 2028E | K1: 2029E
A2: Mastercard Inc | M2: 2020-2024 | N2: Historicals
A3: Operating Activities | M3: 2025-2029 | N3: Projections
A4: Net income | B4: 6411 | C4: 8687 | D4: 9930 | E4: 11195 | F4: 12874 | G4: ='Profit Loss'!G20 -> 14606.825 | H4: ='Profit Loss'!H20 -> 16827.111 | I4: ='Profit Loss'!I20 -> 19033.651 | J4: ='Profit Loss'!J20 -> 21331.218 | K4: ='Profit Loss'!K20 -> 23685.455
A5: Adjustments to reconcile net income to net cash provided by operating activities:
A6: Amortization of customer and merchant incentives | B6: 1072 | C6: 1371 | D6: 1586 | E6: 1622 | F6: 1830 | G6: =Table3[[#This Row],[2024]]*1.05 -> 1921.5 | H6: =Table3[[#This Row],[2025E]]*1.05 -> 2017.575 | I6: =Table3[[#This Row],[2026E]]*1.05 -> 2118.4538 | J6: =Table3[[#This Row],[2027E]]*1.05 -> 2224.3764 | K6: =Table3[[#This Row],[2028E]]*1.05 -> 2335.5953
A7: Depreciation and amortization | B7: 580 | C7: 726 | D7: 750 | E7: 799 | F7: 897 | G7: ='Profit Loss'!G8 -> 946.4112 | H7: ='Profit Loss'!H8 -> 1033.7965 | I7: ='Profit Loss'!I8 -> 1117.9261 | J7: ='Profit Loss'!J8 -> 1196.5802 | K7: ='Profit Loss'!K8 -> 1267.4887
A8: (Gains) losses on equity investments, net | B8: -30 | C8: -645 | D8: 145 | E8: 61 | F8: 29 | G8: 29 | H8: 29 | I8: 29 | J8: 29 | K8: 29
A9: Share-based compensation | B9: 254 | C9: 273 | D9: 295 | E9: 460 | F9: 526 | G9: =Table3[[#This Row],[2024]]*1.06 -> 557.56 | H9: =Table3[[#This Row],[2025E]]*1.06 -> 591.0136 | I9: =Table3[[#This Row],[2026E]]*1.06 -> 626.47442 | J9: =Table3[[#This Row],[2027E]]*1.06 -> 664.06288 | K9: =Table3[[#This Row],[2028E]]*1.06 -> 703.90665
A10: Deferred income taxes | B10: 73 | C10: -69 | D10: -651 | E10: -236 | F10: -527 | G10: =Table3[[#This Row],[2024]]*1.03 -> -542.81 | H10: =Table3[[#This Row],[2025E]]*1.03 -> -559.0943 | I10: =Table3[[#This Row],[2026E]]*1.03 -> -575.86713 | J10: =Table3[[#This Row],[2027E]]*1.03 -> -593.14314 | K10: =Table3[[#This Row],[2028E]]*1.03 -> -610.93744
A11: Other | B11: 14 | C11: 36 | D11: 44 | E11: 22 | F11: 191 | G11: =Table3[[#This Row],[2024]]*1.03 -> 196.73 | H11: =Table3[[#This Row],[2025E]]*1.03 -> 202.6319 | I11: =Table3[[#This Row],[2026E]]*1.03 -> 208.71086 | J11: =Table3[[#This Row],[2027E]]*1.03 -> 214.97218 | K11: =Table3[[#This Row],[2028E]]*1.03 -> 221.42135
A12: Changes in operating assets and liabilities:
A13: Accounts receivable | B13: -86 | C13: -397 | D13: -481 | E13: -546 | F13: 186 | G13: =Balance_Sheet!F7-Balance_Sheet!G7 -> -39.100368 | H13: =Balance_Sheet!G7-Balance_Sheet!H7 -> -47.983048 | I13: =Balance_Sheet!H7-Balance_Sheet!I7 -> -50.05001 | J13: =Balance_Sheet!I7-Balance_Sheet!J7 -> -51.384677 | K13: =Balance_Sheet!J7-Balance_Sheet!K7 -> -51.85181
A14: Income taxes receivable | B14: -2 | C14: -87 | D14: 12 | E14: -171 | F14: -165 | G14: -165 | H14: -165 | I14: -165 | J14: -165 | K14: -165
A15: Settlement assets | B15: 1288 | C15: 390 | D15: 48 | E15: 40 | F15: -593 | G15: =Balance_Sheet!F8-Balance_Sheet!G8 -> -454.30336 | H15: =Balance_Sheet!G8-Balance_Sheet!H8 -> -549.54944 | I15: =Balance_Sheet!H8-Balance_Sheet!I8 -> -573.22234 | J15: =Balance_Sheet!I8-Balance_Sheet!J8 -> -588.50826 | K15: =Balance_Sheet!J8-Balance_Sheet!K8 -> -593.85834
A16: Prepaid expenses | B16: -1552 | C16: -2087 | D16: -2175 | E16: -2438 | F16: -3225 | G16: =Balance_Sheet!F10-Balance_Sheet!G10 -> 468.2368 | H16: =Balance_Sheet!G10-Balance_Sheet!H10 -> -328.08922 | I16: =Balance_Sheet!H10-Balance_Sheet!I10 -> -342.22229 | J16: =Balance_Sheet!I10-Balance_Sheet!J10 -> -351.34822 | K16: =Balance_Sheet!J10-Balance_Sheet!K10 -> -354.54229
A17: Accrued litigation and legal settlements | B17: -73 | C17: -1 | D17: 240 | E17: -375 | F17: 205 | G17: 205 | H17: 205 | I17: 205 | J17: 205 | K17: 205
A18: Restricted security deposits held for customers | B18: 326 | C18: 177 | D18: -305 | E18: 277 | F18: 29 | G18: 29 | H18: 29 | I18: 29 | J18: 29 | K18: 29
A19: Accounts payable | B19: 26 | C19: 100 | D19: 190 | E19: -99 | F19: 75 | G19: =Balance_Sheet!G19-Balance_Sheet!F19 -> 112.05232 | H19: =Balance_Sheet!H19-Balance_Sheet!G19 -> 135.3368 | I19: =Balance_Sheet!I19-Balance_Sheet!H19 -> 141.16669 | J19: =Balance_Sheet!J19-Balance_Sheet!I19 -> 144.93114 | K19: =Balance_Sheet!K19-Balance_Sheet!J19 -> 146.2487
A20: Settlement obligations | B20: -1242 | C20: -568 | D20: 201 | E20: 282 | F20: 922 | G20: =Balance_Sheet!G20-Balance_Sheet!F20 -> 270.85728 | H20: =Balance_Sheet!H20-Balance_Sheet!G20 -> 336.29145 | I20: =Balance_Sheet!I20-Balance_Sheet!H20 -> 350.77785 | J20: =Balance_Sheet!J20-Balance_Sheet!I20 -> 360.13192 | K20: =Balance_Sheet!K20-Balance_Sheet!J20 -> 363.40585
A21: Accrued expenses | B21: -114 | C21: 1355 | D21: 1188 | E21: 571 | F21: 1587 | G21: =Balance_Sheet!G23-Balance_Sheet!F23 -> 1247.8578 | H21: =Balance_Sheet!H23-Balance_Sheet!G23 -> 1513.3115 | I21: =Balance_Sheet!I23-Balance_Sheet!H23 -> 1578.5003 | J21: =Balance_Sheet!J23-Balance_Sheet!I23 -> 1620.5937 | K21: =Balance_Sheet!K23-Balance_Sheet!J23 -> 1635.3263
A22: Long-term taxes payable | B22: -37 | C22: -52 | D22: -121 | E22: -129 | F22: -163 | G22: -163 | H22: -163 | I22: -163 | J22: -163 | K22: -163
A23: Change in Operating Working Capital | B23: =(B13+B16+B15)-(B19+B21+B20) -> 980 | C23: =(C13+C16+C15)-(C19+C21+C20) -> -2981 | D23: =(D13+D16+D15)-(D19+D21+D20) -> -4187 | E23: =(E13+E16+E15)-(E19+E21+E20) -> -3698 | F23: =(F13+F16+F15)-(F19+F21+F20) -> -6216 | G23: =(G13+G16+G15)-(G19+G21+G20) -> -1655.9343 | H23: =(H13+H16+H15)-(H19+H21+H20) -> -2910.5615 | I23: =(I13+I16+I15)-(I19+I21+I20) -> -3035.9395 | ... K23: =(K13+K16+K15)-(K19+K21+K20) -> -3145.2333
A24: Net change in other assets and liabilities | B24: 316 | C24: 254 | D24: 299 | E24: 645 | F24: 102 | G24: =-(Balance_Sheet!K16-Balance_Sheet!J16)+(Balance_Sheet!K29-Balance_Sheet!J29) -> 716.36625 | H24: =-(Balance_Sheet!K16-Balance_Sheet!J16)+(Balance_Sheet!K29-Balance_Sheet!J29) -> 716.36625 | I24: =-(Balance_Sheet!K16-Balance_Sheet!J16)+(Balance_Sheet!K29-Balance_Sheet!J29) -> 716.36625 | J24: =-(Balance_Sheet!K16-Balance_Sheet!J16)+(Balance_Sheet!K29-Balance_Sheet!J29) -> 716.36625 | K24: =-(Balance_Sheet!K16-Balance_Sheet!J16)+(Balance_Sheet!K29-Balance_Sheet!J29) -> 716.36625
A25: Net cash provided by operating activities | B25: 7224 | C25: 9463 | D25: 11195 | E25: 11980 | F25: 14780 | G25: =SUM(G4:G24) -> 18287.248 | H25: =SUM(H4:H24) -> 18913.157 | I25: =SUM(I4:I24) -> 21249.726 | J25: =SUM(J4:J24) -> 23706.95 | K25: =SUM(K4:K24) -> 26253.791
A26: Investing Activities
A27: Purchases of investment securities available-for-sale | B27: -220 | C27: -389 | D27: -267 | E27: -300 | F27: -508 | G27: =Table3[[#This Row],[2024]]*1.05 -> -533.4 | H27: =Table3[[#This Row],[2025E]]*1.05 -> -560.07 | I27: =Table3[[#This Row],[2026E]]*1.05 -> -588.0735 | J27: =Table3[[#This Row],[2027E]]*1.05 -> -617.47718 | K27: =Table3[[#This Row],[2028E]]*1.05 -> -648.35103
A28: Purchases of investments held-to-maturity | B28: -198 | C28: -294 | D28: -239 | E28: -347 | F28: -108 | G28: =Table3[[#This Row],[2024]]*1.05 -> -113.4 | H28: =Table3[[#This Row],[2025E]]*1.05 -> -119.07 | I28: =Table3[[#This Row],[2026E]]*1.05 -> -125.0235 | J28: =Table3[[#This Row],[2027E]]*1.05 -> -131.27468 | K28: =Table3[[#This Row],[2028E]]*1.05 -> -137.83841
A29: Proceeds from sales of investment securities available-for-sale | B29: 361 | C29: 83 | D29: 54 | E29: 87 | F29: 199 | G29: =Table3[[#This Row],[2024]]*1.05 -> 208.95 | H29: =Table3[[#This Row],[2025E]]*1.05 -> 219.3975 | I29: =Table3[[#This Row],[2026E]]*1.05 -> 230.36738 | J29: =Table3[[#This Row],[2027E]]*1.05 -> 241.88574 | K29: =Table3[[#This Row],[2028E]]*1.05 -> 253.98003
A30: Proceeds from maturities of investment securities available-for-sale | B30: 140 | C30: 291 | D30: 211 | E30: 191 | F30: 262 | G30: =Table3[[#This Row],[2024]]*1.05 -> 275.1 | H30: =Table3[[#This Row],[2025E]]*1.05 -> 288.855 | I30: =Table3[[#This Row],[2026E]]*1.05 -> 303.29775 | J30: =Table3[[#This Row],[2027E]]*1.05 -> 318.46264 | K30: =Table3[[#This Row],[2028E]]*1.05 -> 334.38577
A31: Proceeds from maturities of investments held-to-maturity | B31: 121 | C31: 296 | D31: 265 | E31: 157 | F31: 378 | G31: =Table3[[#This Row],[2024]]*1.05 -> 396.9 | H31: =Table3[[#This Row],[2025E]]*1.05 -> 416.745 | I31: =Table3[[#This Row],[2026E]]*1.05 -> 437.58225 | J31: =Table3[[#This Row],[2027E]]*1.05 -> 459.46136 | K31: =Table3[[#This Row],[2028E]]*1.05 -> 482.43443
A32: Purchases of property and equipment | B32: -339 | C32: -407 | D32: -442 | E32: -371 | F32: -474 | G32: =Table3[[#This Row],[2024]]*1.05 -> -497.7 | H32: =Table3[[#This Row],[2025E]]*1.05 -> -522.585 | I32: =Table3[[#This Row],[2026E]]*1.05 -> -548.71425 | J32: =Table3[[#This Row],[2027E]]*1.05 -> -576.14996 | K32: =Table3[[#This Row],[2028E]]*1.05 -> -604.95746
A33: Capitalized software | B33: -369 | C33: -407 | D33: -655 | E33: -717 | F33: -720 | G33: =Table3[[#This Row],[2024]]*1.05 -> -756 | H33: =Table3[[#This Row],[2025E]]*1.05 -> -793.8 | I33: =Table3[[#This Row],[2026E]]*1.05 -> -833.49 | J33: =Table3[[#This Row],[2027E]]*1.05 -> -875.1645 | K33: =Table3[[#This Row],[2028E]]*1.05 -> -918.92273
A34: Purchases of equity investments | B34: -214 | C34: -228 | D34: -88 | E34: -89 | F34: -42 | G34: =Table3[[#This Row],[2024]]*1.05 -> -44.1 | H34: =Table3[[#This Row],[2025E]]*1.05 -> -46.305 | I34: =Table3[[#This Row],[2026E]]*1.05 -> -48.62025 | J34: =Table3[[#This Row],[2027E]]*1.05 -> -51.051263 | K34: =Table3[[#This Row],[2028E]]*1.05 -> -53.603826
A35: Proceeds from sales of equity investments | B35: 0 | C35: 186 | D35: 7 | E35: 44 | F35: 125 | G35: =Table3[[#This Row],[2024]]*1.05 -> 131.25 | H35: =Table3[[#This Row],[2025E]]*1.05 -> 137.8125 | I35: =Table3[[#This Row],[2026E]]*1.05 -> 144.70312 | J35: =Table3[[#This Row],[2027E]]*1.05 -> 151.93828 | K35: =Table3[[#This Row],[2028E]]*1.05 -> 159.5352
A36: Acquisition of businesses, net of cash acquired | B36: -989 | C36: -4436 | D36: -313 | E36: 0 | F36: -2511 | G36: 0 | H36: 0 | I36: 0 | J36: 0 | K36: 0
A37: Settlement of interest rate derivative contracts | B37: -175 | C37: 0 | D37: 0 | E37: 0 | F37: 0 | G37: 0 | H37: 0 | I37: 0 | J37: 0 | K37: 0
A38: Other investing activities | B38: 3 | C38: 33 | D38: -3 | E38: -6 | F38: -3 | G38: -3 | H38: -3 | I38: -3 | J38: -3 | K38: -3
A39: Net cash used in investing activities | B39: -1879 | C39: -5272 | D39: -1470 | E39: -1351 | F39: -3402 | G39: =SUM(G27:G38) -> -935.4 | H39: =SUM(H27:H38) -> -982.02 | I39: =SUM(I27:I38) -> -1030.971 | J39: =SUM(J27:J38) -> -1082.3696 | K39: =SUM(K27:K38) -> -1136.338
A40: Financing Activities
A41: Purchases of treasury stock | B41: -4473 | C41: -5904 | D41: -8753 | E41: -9032 | F41: -11035 | G41: =Table3[[#This Row],[2024]]-G42 -> -6652.9526 | H41: =Table3[[#This Row],[2024]]-H42 -> -5986.8667 | I41: =Table3[[#This Row],[2024]]-I42 -> -5324.9047 | J41: =Table3[[#This Row],[2024]]-J42 -> -4635.6346 | K41: =Table3[[#This Row],[2024]]-K42 -> -3929.3634
A42: Dividends paid | B42: -1605 | C42: -1741 | D42: -1903 | E42: -2158 | F42: -2448 | G42: =-'Profit Loss'!G20*Assumptions!B39 -> -4382.0474 | H42: =-'Profit Loss'!H20*Assumptions!B39 -> -5048.1333 | I42: =-'Profit Loss'!I20*Assumptions!B39 -> -5710.0953 | J42: =-'Profit Loss'!J20*Assumptions!B39 -> -6399.3654 | K42: =-'Profit Loss'!K20*Assumptions!B39 -> -7105.6366
A43: Proceeds from debt, net | B43: 3959 | C43: 2024 | D43: 1123 | E43: 1554 | F43: 3960 | G43: =G68 -> 0 | H43: =H68 -> 0 | I43: =I68 -> 0 | J43: =J68 -> 0 | K43: =K68 -> 0
A44: Minimum Cash | B44: ='Profit Loss'!B4*5% -> 765.05 | C44: ='Profit Loss'!C4*5% -> 944.2 | D44: ='Profit Loss'!D4*5% -> 1111.85 | E44: ='Profit Loss'!E4*5% -> 1254.9 | F44: ='Profit Loss'!F4*5% -> 1408.35 | G44: ='Profit Loss'!G4*5% -> 1577.352 | H44: ='Profit Loss'!H4*5% -> 1782.4078 | I44: ='Profit Loss'!I4*5% -> 1996.2967 | ... K44: ='Profit Loss'!K4*5% -> 2437.4783
A45: Cash Available Before Financing | B45: =B58+B25+B39 -> 14314 | C45: =C58+C25+C39 -> 16610 | D45: =D58+D25+D39 -> 19627 | E45: =E58+E25+E39 -> 19825 | F45: =F58+F25+F39 -> 21843 | G45: =G58+G25+G39 -> 25793.848 | H45: =H58+H25+H39 -> 27363.485 | I45: =I58+I25+I39 -> 29443.632 | ... K45: =K58+K25+K39 -> 33903.65
A46: Excess Cash | B46: =MAX(0, B45-B44) -> 13548.95 | C46: =MAX(0, C45-C44) -> 15665.8 | D46: =MAX(0, D45-D44) -> 18515.15 | E46: =MAX(0, E45-E44) -> 18570.1 | F46: =MAX(0, F45-F44) -> 20434.65 | G46: =MAX(0, G45-G44) -> 24216.496 | H46: =MAX(0, H45-H44) -> 25581.077 | I46: =MAX(0, I45-I44) -> 27447.335 | ... K46: =MAX(0, K45-K44) -> 31466.172
A47: Buybacks | B47: =-B46-B69 -> -13548.95 | C47: =-C46-C69 -> -15015.8 | D47: =-D46-D69 -> -17791.15 | E47: =-E46-E69 -> -18570.1 | F47: =-F46-F69 -> -19098.65 | G47: =-G46-G69 -> -23216.496 | H47: =-H46-H69 -> -24581.077 | I47: =-I46-I69 -> -26447.335 | ... K47: =-K46-K69 -> -30466.172
A48: Payment of debt | B48: 0 | C48: -650 | D48: -724 | E48: 0 | F48: -1336 | G48: =G69 -> -1000 | H48: =H69 -> -1000 | I48: =I69 -> -1000 | J48: =J69 -> -1000 | K48: =K69 -> -1000
A49: Acquisition of redeemable non-controlling interests | B49: -49 | C49: 0 | D49: -4 | E49: 0 | F49: 0 | G49: 0 | H49: 0 | I49: 0 | J49: 0 | K49: 0
A50: Acquisition of non-controlling interest | B50: 0 | C50: -133 | D50: 0 | E50: 0 | F50: 0 | G50: 0 | H50: 0 | I50: 0 | J50: 0 | K50: 0
A51: Contingent consideration paid | B51: 0 | C51: -64 | D51: 0 | E51: 0 | F51: 0 | G51: 0 | H51: 0 | I51: 0 | J51: 0 | K51: 0
A52: Tax withholdings related to share-based payments | B52: -150 | C52: -133 | D52: -141 | E52: -89 | F52: -178 | G52: =Table3[[#This Row],[2024]]*1.05 -> -186.9 | H52: =Table3[[#This Row],[2025E]]*1.05 -> -196.245 | I52: =Table3[[#This Row],[2026E]]*1.05 -> -206.05725 | J52: =Table3[[#This Row],[2027E]]*1.05 -> -216.36011 | K52: =Table3[[#This Row],[2028E]]*1.05 -> -227.17812
A53: Cash proceeds from exercise of stock options | B53: 97 | C53: 61 | D53: 90 | E53: 237 | F53: 224 | G53: =Table3[[#This Row],[2024]]*1.05 -> 235.2 | H53: =Table3[[#This Row],[2025E]]*1.05 -> 246.96 | I53: =Table3[[#This Row],[2026E]]*1.05 -> 259.308 | J53: =Table3[[#This Row],[2027E]]*1.05 -> 272.2734 | K53: =Table3[[#This Row],[2028E]]*1.05 -> 285.88707
A54: Other financing activities | B54: 69 | C54: -15 | D54: -16 | E54: 0 | F54: -23 | G54: -23 | H54: -23 | I54: -23 | J54: -23 | K54: -23
A55: Net cash used in financing activities | B55: -2152 | C55: -6555 | D55: -10328 | E55: -9488 | F55: -10836 | G55: =-SUM(G41:G54) -> -16361.5 | H55: =-SUM(H41:H54) -> -18138.607 | I55: =-SUM(I41:I54) -> -20435.18 | J55: =-SUM(J41:J54) -> -22846.836 | K55: =-SUM(K41:K54) -> -25341.838
A56: Effect of exchange rate changes on cash, cash equivalents, restricted cash and restricted cash equivalents | B56: 257 | C56: -153 | D56: -103 | E56: 128 | F56: -199 | G56: 0 | H56: 0 | I56: 0 | J56: 0 | K56: 0
A57: Net increase (decrease) in cash, cash equivalents, restricted cash and restricted cash equivalents | B57: 3450 | C57: -2517 | D57: -706 | E57: 1269 | F57: 343 | G57: =G25+G39+G55+G56 -> 990.348 | H57: =H25+H39+H55+H56 -> -207.47076 | I57: =I25+I39+I55+I56 -> -216.42468 | J57: =J25+J39+J55+J56 -> -222.25517 | K57: =K25+K39+K55+K56 -> -224.3846
A58: Cash, cash equivalents, restricted cash and restricted cash equivalents - beginning of period | B58: 8969 | C58: 12419 | D58: 9902 | E58: 9196 | F58: 10465 | G58: =Balance_Sheet!F4 -> 8442 | H58: =G59 -> 9432.348 | I58: =H59 -> 9224.8772 | J58: =I59 -> 9008.4526 | K58: =J59 -> 8786.1974
A59: Cash, cash equivalents, restricted cash and restricted cash equivalents - end of period | B59: 12419 | C59: 9902 | D59: 9196 | E59: 10465 | F59: 10808 | G59: =G58+G57 -> 9432.348 | H59: =H58+H57 -> 9224.8772 | I59: =I58+I57 -> 9008.4526 | J59: =J58+J57 -> 8786.1974 | K59: =K58+K57 -> 8561.8128
A60: FCF Conversion | B60: =B4/B61 -> 0.84767949 | C60: =C4/C61 -> 0.88014184 | D60: =D4/D61 -> 0.85331271 | E60: =E4/E61 -> 0.90640434 | F60: =F4/F61 -> 0.84397535 | G60: =G4/G61 -> 0.77758131 | H60: =H4/H61 -> 0.86578178 | I60: =I4/I61 -> 0.87316573 | ... K60: =K4/K61 -> 0.88185252
A61: Free Cash Flow of Firm | B61: =B25-B32 -> 7563 | C61: =C25-C32 -> 9870 | D61: =D25-D32 -> 11637 | E61: =E25-E32 -> 12351 | F61: =F25-F32 -> 15254 | G61: =G25-G32 -> 18784.948 | H61: =H25-H32 -> 19435.742 | I61: =I25-I32 -> 21798.44 | ... K61: =K25-K32 -> 26858.749
A62: Total | B62: =SUM(B4:B61) -> 55103.898 | C62: =SUM(C4:C61) -> 40017.08 | D62: =SUM(D4:D61) -> 45996.703 | E62: =SUM(E4:E61) -> 53073.806 | F62: =SUM(F4:F61) -> 56127.194 | G62: =SUM(G4:G61) -> 72354.118 | H62: =SUM(H4:H61) -> 73748.635 | I62: =SUM(I4:I61) -> 80253.728 | ... K62: =SUM(K4:K61) -> 94218.162
A64: Conclusion: Mastercard demonstrates strong and growing free cash flow driven by high margins, negative working capital dynamics, and a capital-light business model, supporting its positioning as a high-quality cash compounding franchise
A66: Debt Schedule | B66: 2020 | C66: 2021 | D66: 2022 | E66: 2023 | F66: 2024 | G66: 2025 | H66: 2026 | I66: 2027 | J66: 2028 | K66: 2029
A67: Opening Debt | B67: =Balance_Sheet!B27 -> 12023 | C67: =B70 -> 12023 | D67: =C70 -> 11373 | E67: =D70 -> 10649 | F67: =Balance_Sheet!F27 -> 17476 | G67: =F70 -> 16140 | H67: =G70 -> 15140 | I67: =H70 -> 14140 | J67: =I70 -> 13140 | K67: =J70 -> 12140
A68: + New Debt | B68: =IF(B45 < B44, B44 - B45, 0) -> 0 | C68: =IF(C45 < C44, C44 - C45, 0) -> 0 | D68: =IF(D45 < D44, D44 - D45, 0) -> 0 | E68: =IF(E45 < E44, E44 - E45, 0) -> 0 | F68: =IF(F45 < F44, F44 - F45, 0) -> 0 | G68: =IF(G45 < G44, G44 - G45, 0) -> 0 | H68: =IF(H45 < H44, H44 - H45, 0) -> 0 | I68: =IF(I45 < I44, I44 - I45, 0) -> 0 | ... K68: =IF(K45 < K44, K44 - K45, 0) -> 0
A69: – Payment of Debt | B69: =B48 -> 0 | C69: =C48 -> -650 | D69: =D48 -> -724 | E69: =E48 -> 0 | F69: =F48 -> -1336 | G69: -1000 | H69: -1000 | I69: -1000 | J69: -1000 | K69: -1000
A70: Closing Debt | B70: =B67+B68-B69 -> 12023 | C70: =C67+C68+C69 -> 11373 | D70: =D67+D68+D69 -> 10649 | E70: =E67+E68-E69 -> 10649 | F70: =F67+F68+F69 -> 16140 | G70: =G67+G68+G69 -> 15140 | H70: =H67+H68+H69 -> 14140 | I70: =I67+I68+I69 -> 13140 | J70: =J67+J68+J69 -> 12140 | K70: =K67+K68+K69 -> 11140

Sheet Common Size
A1: DCF Valuation Model – Mastercard Inc. (2020–2029)
A2: Common Size Income Statement – Mastercard | B2: 2020 | C2: 2021 | D2: 2022 | E2: 2023 | F2: 2024 | G2: 2025 | H2: 2026 | I2: 2027 | J2: 2028 | K2: 2029 | L2: Assumptions
A3: Variables | B3: 2020 | C3: 2021 | D3: 2022 | E3: 2023 | F3: 2024 | G3: 2025E | H3: 2026E | I3: 2027E | J3: 2028E | K3: 2029E | L3: Item | M3: 2025 | N3: 2026 | O3: 2027 | P3: 2028 | Q3: 2029
A4: Net Revenue | B4: ='Profit Loss'!B4/'Profit Loss'!B4 -> 1 | C4: ='Profit Loss'!C4/'Profit Loss'!C4 -> 1 | D4: ='Profit Loss'!D4/'Profit Loss'!D4 -> 1 | E4: ='Profit Loss'!E4/'Profit Loss'!E4 -> 1 | F4: ='Profit Loss'!F4/'Profit Loss'!F4 -> 1 | G4: ='Profit Loss'!G4/'Profit Loss'!G4 -> 1 | H4: ='Profit Loss'!H4/'Profit Loss'!H4 -> 1 | I4: ='Profit Loss'!I4/'Profit Loss'!I4 -> 1 | ... K4: ='Profit Loss'!K4/'Profit Loss'!K4 -> 1 | L4: Revenue Growth | M4: =Assumptions!H5 -> 0.12 | N4: =Assumptions!I5 -> 0.13 | O4: =Assumptions!J5 -> 0.12 | P4: =Assumptions!K5 -> 0.11 | Q4: =Assumptions!L5 -> 0.1
A5: General & Administrative | B5: ='Profit Loss'!B6/'Profit Loss'!B4 -> 0.38624926 | C5: =Table10[[#This Row],[2020]]*(1+2%) -> 0.39397425 | D5: =Table10[[#This Row],[2021]]*(1+2%) -> 0.40185374 | E5: =Table10[[#This Row],[2022]]*(1+2%) -> 0.40989081 | F5: =Table10[[#This Row],[2023]]*(1+2%) -> 0.41808863 | G5: =G4*Table35[[#This Row],[2025]] -> 0.43 | H5: =H4*Table35[[#This Row],[2026]] -> 0.445 | I5: =I4*Table35[[#This Row],[2027]] -> 0.45 | J5: =J4*Table35[[#This Row],[2028]] -> 0.455 | K5: =K4*Table35[[#This Row],[2029]] -> 0.46 | L5: G&A % | M5: 0.43 | N5: 0.445 | O5: 0.45 | P5: 0.455 | Q5: 0.46
A6: Advertising & Marketing | B6: ='Profit Loss'!B7/'Profit Loss'!B4 -> 0.04293837 | C6: ='Profit Loss'!C7/'Profit Loss'!C4 -> 0.04739462 | D6: ='Profit Loss'!D7/'Profit Loss'!D4 -> 0.035481405 | E6: ='Profit Loss'!E7/'Profit Loss'!E4 -> 0.032871145 | F6: ='Profit Loss'!F7/'Profit Loss'!F4 -> 0.028934569 | G6: =Table35[[#This Row],[2025]] -> 0.03 | H6: =Table35[[#This Row],[2025]] -> 0.03 | I6: =Table35[[#This Row],[2025]] -> 0.03 | J6: =Table35[[#This Row],[2025]] -> 0.03 | K6: =Table35[[#This Row],[2025]] -> 0.03 | L6: Marketing % | M6: 0.03 | N6: 0.03 | O6: 0.03 | P6: 0.03 | Q6: 0.03
A7: Depreciation & Amortization | B7: ='Profit Loss'!B8/'Profit Loss'!B4 -> 0.037906019 | C7: ='Profit Loss'!C8/'Profit Loss'!C4 -> 0.038445245 | D7: ='Profit Loss'!D8/'Profit Loss'!D4 -> 0.033727571 | E7: ='Profit Loss'!E8/'Profit Loss'!E4 -> 0.031835206 | F7: ='Profit Loss'!F8/'Profit Loss'!F4 -> 0.031845777 | G7: =G4*Table35[[#This Row],[2025]] -> 0.03 | H7: =H4*Table35[[#This Row],[2026]] -> 0.029 | I7: =I4*Table35[[#This Row],[2027]] -> 0.028 | J7: =J4*Table35[[#This Row],[2028]] -> 0.027 | K7: =K4*Table35[[#This Row],[2029]] -> 0.026 | L7: Depreciation % | M7: 0.03 | N7: 0.029 | O7: 0.028 | P7: 0.027 | Q7: 0.026
A8: Provision for Litigation | B8: ='Profit Loss'!B9/'Profit Loss'!B4 -> 0.00477093 | C8: ='Profit Loss'!C9/'Profit Loss'!C4 -> 0.0049777589 | D8: ='Profit Loss'!D9/'Profit Loss'!D4 -> 0.016009354 | E8: ='Profit Loss'!E9/'Profit Loss'!E4 -> 0.021475815 | F8: ='Profit Loss'!F9/'Profit Loss'!F4 -> 0.024141726 | G8: ='Profit Loss'!G9/'Profit Loss'!G4 -> 0.02 | H8: ='Profit Loss'!H9/'Profit Loss'!H4 -> 0.02 | I8: ='Profit Loss'!I9/'Profit Loss'!I4 -> 0.02 | ... K8: ='Profit Loss'!K9/'Profit Loss'!K4 -> 0.02 | L8: Capex % | M8: 0.075 | N8: 0.075 | O8: 0.075 | P8: 0.075 | Q8: 0.075
A9: Total Operating Expenses | B9: ='Profit Loss'!B10/'Profit Loss'!B4 -> 0.47186458 | C9: ='Profit Loss'!C10/'Profit Loss'!C4 -> 0.46610888 | D9: ='Profit Loss'!D10/'Profit Loss'!D4 -> 0.44848676 | E9: ='Profit Loss'!E10/'Profit Loss'!E4 -> 0.44186788 | F9: ='Profit Loss'!F10/'Profit Loss'!F4 -> 0.44679945 | G9: ='Profit Loss'!G10/'Profit Loss'!G4 -> 0.45 | H9: ='Profit Loss'!H10/'Profit Loss'!H4 -> 0.44 | I9: ='Profit Loss'!I10/'Profit Loss'!I4 -> 0.435 | ... K9: ='Profit Loss'!K10/'Profit Loss'!K4 -> 0.425 | L9: Working Capital % | M9: 0.065 | N9: 0.065 | O9: 0.065 | P9: 0.065 | Q9: 0.065
A10: Operating Income | B10: ='Profit Loss'!B11/'Profit Loss'!B4 -> 0.52813542 | C10: ='Profit Loss'!C11/'Profit Loss'!C4 -> 0.53389112 | D10: ='Profit Loss'!D11/'Profit Loss'!D4 -> 0.55151324 | E10: ='Profit Loss'!E11/'Profit Loss'!E4 -> 0.55813212 | F10: ='Profit Loss'!F11/'Profit Loss'!F4 -> 0.55320055 | G10: ='Profit Loss'!G11/'Profit Loss'!G4 -> 0.55 | H10: ='Profit Loss'!H11/'Profit Loss'!H4 -> 0.56 | I10: ='Profit Loss'!I11/'Profit Loss'!I4 -> 0.565 | ... K10: ='Profit Loss'!K11/'Profit Loss'!K4 -> 0.575 | L10: Cash % of Assets | M10: 0.3 | N10: 0.32 | O10: 0.33 | P10: 0.34 | Q10: 0.35
A11: Investment Income | B11: ='Profit Loss'!B13/'Profit Loss'!B4 -> 0.0015685249 | C11: ='Profit Loss'!C13/'Profit Loss'!C4 -> 0.00058250371 | D11: ='Profit Loss'!D13/'Profit Loss'!D4 -> 0.0027431758 | E11: ='Profit Loss'!E13/'Profit Loss'!E4 -> 0.010917205 | F11: ='Profit Loss'!F13/'Profit Loss'!F4 -> 0.01160933 | G11: ='Profit Loss'!G13/'Profit Loss'!G4 -> 0.010780092 | H11: ='Profit Loss'!H13/'Profit Loss'!H4 -> 0.0099215008 | I11: ='Profit Loss'!I13/'Profit Loss'!I4 -> 0.0092128222 | ... K11: ='Profit Loss'!K13/'Profit Loss'!K4 -> 0.0081610061 | L11: Interest Rate | M11: 0.035 | N11: 0.035 | O11: 0.035 | P11: 0.035 | Q11: 0.035
A12: Interest Expense | B12: ='Profit Loss'!B15/'Profit Loss'!B4 -> -0.024834978 | C12: ='Profit Loss'!C15/'Profit Loss'!C4 -> -0.022823554 | D12: ='Profit Loss'!D15/'Profit Loss'!D4 -> -0.021180915 | E12: ='Profit Loss'!E15/'Profit Loss'!E4 -> -0.022910192 | F12: ='Profit Loss'!F15/'Profit Loss'!F4 -> -0.02293464 | G12: ='Profit Loss'!G15/'Profit Loss'!G4 -> -0.0095690436 | H12: ='Profit Loss'!H15/'Profit Loss'!H4 -> -0.0079772711 | I12: ='Profit Loss'!I15/'Profit Loss'!I4 -> -0.0066842519 | ... K12: ='Profit Loss'!K15/'Profit Loss'!K4 -> -0.0047564527 | L12: Tax Rate | M12: 0.16 | N12: 0.16 | O12: 0.16 | P12: 0.16 | Q12: 0.16
A13: Total Other Income | B13: ='Profit Loss'!B17/'Profit Loss'!B4 -> -0.020979021 | C13: ='Profit Loss'!C17/'Profit Loss'!C4 -> 0.011914849 | D13: ='Profit Loss'!D17/'Profit Loss'!D4 -> -0.02392409 | E13: ='Profit Loss'!E17/'Profit Loss'!E4 -> -0.014702367 | F13: ='Profit Loss'!F17/'Profit Loss'!F4 -> -0.011644833 | G13: ='Profit Loss'!G17/'Profit Loss'!G4 -> 0.0012110486 | H13: ='Profit Loss'!H17/'Profit Loss'!H4 -> 0.0019442296 | I13: ='Profit Loss'!I17/'Profit Loss'!I4 -> 0.0025285702 | ... K13: ='Profit Loss'!K17/'Profit Loss'!K4 -> 0.0034045534 | L13: Revenue growth is driven by transaction volume expansion and stable take rate (~0.39%), reflecting pricing power and network scale
A14: Income Before Tax | B14: ='Profit Loss'!B18/'Profit Loss'!B4 -> 0.5071564 | C14: ='Profit Loss'!C18/'Profit Loss'!C4 -> 0.54580597 | D14: ='Profit Loss'!D18/'Profit Loss'!D4 -> 0.52758915 | E14: ='Profit Loss'!E18/'Profit Loss'!E4 -> 0.54342976 | F14: ='Profit Loss'!F18/'Profit Loss'!F4 -> 0.54155572 | G14: ='Profit Loss'!G18/'Profit Loss'!G4 -> 0.55121105 | H14: ='Profit Loss'!H18/'Profit Loss'!H4 -> 0.56194423 | I14: ='Profit Loss'!I18/'Profit Loss'!I4 -> 0.56752857 | ... K14: ='Profit Loss'!K18/'Profit Loss'!K4 -> 0.57840455 | M14: 2020-2024 | N14: Historicals
A15: Income Tax Expense | B15: ='Profit Loss'!B19/'Profit Loss'!B4 -> 0.088164172 | C15: ='Profit Loss'!C19/'Profit Loss'!C4 -> 0.08578691 | D15: ='Profit Loss'!D19/'Profit Loss'!D4 -> 0.081036111 | E15: ='Profit Loss'!E19/'Profit Loss'!E4 -> 0.097378277 | F15: ='Profit Loss'!F19/'Profit Loss'!F4 -> 0.084496041 | G15: ='Profit Loss'!G19/'Profit Loss'!G4 -> 0.088193768 | H15: ='Profit Loss'!H19/'Profit Loss'!H4 -> 0.089911077 | I15: ='Profit Loss'!I19/'Profit Loss'!I4 -> 0.090804571 | ... K15: ='Profit Loss'!K19/'Profit Loss'!K4 -> 0.092544729 | M15: 2025-2029 | N15: Projections
A16: Net Income | B16: ='Profit Loss'!B20/'Profit Loss'!B4 -> 0.41899222 | C16: ='Profit Loss'!C20/'Profit Loss'!C4 -> 0.46001906 | D16: ='Profit Loss'!D20/'Profit Loss'!D4 -> 0.44655304 | E16: ='Profit Loss'!E20/'Profit Loss'!E4 -> 0.44605148 | F16: ='Profit Loss'!F20/'Profit Loss'!F4 -> 0.45705968 | G16: ='Profit Loss'!G20/'Profit Loss'!G4 -> 0.46301728 | H16: ='Profit Loss'!H20/'Profit Loss'!H4 -> 0.47203315 | I16: ='Profit Loss'!I20/'Profit Loss'!I4 -> 0.476724 | ... K16: ='Profit Loss'!K20/'Profit Loss'!K4 -> 0.48585982
A17: EBITDA | B17: ='Profit Loss'!B25/'Profit Loss'!B4 -> 0.56604144 | C17: ='Profit Loss'!C25/'Profit Loss'!C4 -> 0.57233637 | D17: ='Profit Loss'!D25/'Profit Loss'!D4 -> 0.58524081 | E17: ='Profit Loss'!E25/'Profit Loss'!E4 -> 0.58996733 | F17: ='Profit Loss'!F25/'Profit Loss'!F4 -> 0.58504633 | G17: ='Profit Loss'!G25/'Profit Loss'!G4 -> 0.58 | H17: ='Profit Loss'!H25/'Profit Loss'!H4 -> 0.589 | I17: ='Profit Loss'!I25/'Profit Loss'!I4 -> 0.593 | ... K17: ='Profit Loss'!K25/'Profit Loss'!K4 -> 0.601
A19: Common Size Balance Sheet – Mastercard | B19: 2020 | C19: 2021 | D19: 2022 | E19: 2023 | F19: 2024 | G19: 2025 | H19: 2026 | I19: 2027 | J19: 2028 | K19: 2029
A20: Variables | B20: 2020 | C20: 2021 | D20: 2022 | E20: 2023 | F20: 2024 | G20: 2025E | H20: 2026E | I20: 2027E | J20: 2028E | K20: 2029E
A21: Cash & Cash Equivalents | B21: =Balance_Sheet!B4/Balance_Sheet!B17 -> 0.30112554 | C21: =Balance_Sheet!C4/Balance_Sheet!C17 -> 0.1970055 | D21: =Balance_Sheet!D4/Balance_Sheet!D17 -> 0.18097304 | E21: =Balance_Sheet!E4/Balance_Sheet!E17 -> 0.20231813 | F21: =Balance_Sheet!F4/Balance_Sheet!F17 -> 0.17557871 | G21: =M10 -> 0.3 | H21: =N10 -> 0.32 | I21: =O10 -> 0.33 | J21: =P10 -> 0.34 | K21: =Q10 -> 0.35
A22: Accounts Receivable | B22: =Balance_Sheet!B7/Balance_Sheet!B17 -> 0.078787518 | C22: =Balance_Sheet!C7/Balance_Sheet!C17 -> 0.079800366 | D22: =Balance_Sheet!D7/Balance_Sheet!D17 -> 0.088446441 | E22: =Balance_Sheet!E7/Balance_Sheet!E17 -> 0.013946476 | F22: =Balance_Sheet!F7/Balance_Sheet!F17 -> 0.006863418 | G22: =Balance_Sheet!G7/Balance_Sheet!G17 -> 0.0069513911 | H22: =Balance_Sheet!H7/Balance_Sheet!H17 -> 0.0072839306 | I22: =Balance_Sheet!I7/Balance_Sheet!I17 -> 0.0075910713 | ... K22: =Balance_Sheet!K7/Balance_Sheet!K17 -> 0.0080879164
A23: Settlement Assets | B23: =Balance_Sheet!B8/Balance_Sheet!B17 -> 0.050797999 | C23: =Balance_Sheet!C8/Balance_Sheet!C17 -> 0.03501553 | D23: =Balance_Sheet!D8/Balance_Sheet!D17 -> 0.032796199 | E23: =Balance_Sheet!E8/Balance_Sheet!E17 -> 0.095646438 | F23: =Balance_Sheet!F8/Balance_Sheet!F17 -> 0.078471746 | G23: =Balance_Sheet!G8/Balance_Sheet!G17 -> 0.079614223 | H23: =Balance_Sheet!H8/Balance_Sheet!H17 -> 0.083422795 | I23: =Balance_Sheet!I8/Balance_Sheet!I17 -> 0.086940475 | ... K23: =Balance_Sheet!K8/Balance_Sheet!K17 -> 0.092630838
A24: Total Current Assets | B24: =SUM(B21:B23) -> 0.43071105 | C24: =SUM(C21:C23) -> 0.31182139 | D24: =SUM(D21:D23) -> 0.30221568 | E24: =SUM(E21:E23) -> 0.31191104 | F24: =SUM(F21:F23) -> 0.26091387 | G24: =SUM(G21:G23) -> 0.38656561 | H24: =SUM(H21:H23) -> 0.41070673 | I24: =SUM(I21:I23) -> 0.42453155 | ... K24: =SUM(K21:K23) -> 0.45071875
A25: PPE | B25: =Balance_Sheet!B12/Balance_Sheet!B17 -> 0.056634111 | C25: =Balance_Sheet!C12/Balance_Sheet!C17 -> 0.050625183 | D25: =Balance_Sheet!D12/Balance_Sheet!D17 -> 0.0518025 | E25: =Balance_Sheet!E12/Balance_Sheet!E17 -> 0.048553524 | F25: =Balance_Sheet!F12/Balance_Sheet!F17 -> 0.044466629 | G25: =Balance_Sheet!G12/Balance_Sheet!G17 -> 0.041876298 | H25: =Balance_Sheet!H12/Balance_Sheet!H17 -> 0.040384737 | I25: =Balance_Sheet!I12/Balance_Sheet!I17 -> 0.039081376 | ... K25: =Balance_Sheet!K12/Balance_Sheet!K17 -> 0.036885395
A26: Intangible Assets | B26: =Balance_Sheet!B14/Balance_Sheet!B17 -> 0.14768938 | C26: =Balance_Sheet!C14/Balance_Sheet!C17 -> 0.20340333 | D26: =Balance_Sheet!D14/Balance_Sheet!D17 -> 0.19424646 | E26: =Balance_Sheet!E14/Balance_Sheet!E17 -> 0.18045609 | F26: =Balance_Sheet!F14/Balance_Sheet!F17 -> 0.19119819 | G26: =Balance_Sheet!G14/Balance_Sheet!G17 -> 0.17313485 | H26: =Balance_Sheet!H14/Balance_Sheet!H17 -> 0.16054624 | I26: =Balance_Sheet!I14/Balance_Sheet!I17 -> 0.14938926 | ... K26: =Balance_Sheet!K14/Balance_Sheet!K17 -> 0.13035789
A27: Other Assets | B27: =Balance_Sheet!B16/Balance_Sheet!B17 -> 0.15974869 | C27: =Balance_Sheet!C16/Balance_Sheet!C17 -> 0.18566991 | D27: =Balance_Sheet!D16/Balance_Sheet!D17 -> 0.19574424 | E27: =Balance_Sheet!E16/Balance_Sheet!E17 -> 0.19612231 | F27: =Balance_Sheet!F16/Balance_Sheet!F17 -> 0.20712964 | G27: =Balance_Sheet!G16/Balance_Sheet!G17 -> 0.071296319 | H27: =Balance_Sheet!H16/Balance_Sheet!H17 -> 0.080932562 | I27: =Balance_Sheet!I16/Balance_Sheet!I17 -> 0.077857142 | ... K27: =Balance_Sheet!K16/Balance_Sheet!K17 -> 0.069127491
A28: Total Assets | B28: 1 | C28: 1 | D28: 1 | E28: 1 | F28: 1 | G28: 1 | H28: 1 | I28: 1 | J28: 1 | K28: 1
A29: Liabilities
A30: Accounts Payable | B30: =Balance_Sheet!B19/Balance_Sheet!B17 -> 0.015691996 | C30: =Balance_Sheet!C19/Balance_Sheet!C17 -> 0.019591707 | D30: =Balance_Sheet!D19/Balance_Sheet!D17 -> 0.023912819 | E30: =Balance_Sheet!E19/Balance_Sheet!E17 -> 0.019647569 | F30: =Balance_Sheet!F19/Balance_Sheet!F17 -> 0.019321562 | G30: =Balance_Sheet!G19/Balance_Sheet!G17 -> 0.019606488 | H30: =Balance_Sheet!H19/Balance_Sheet!H17 -> 0.02054442 | I30: =Balance_Sheet!I19/Balance_Sheet!I17 -> 0.021410714 | ... K30: =Balance_Sheet!K19/Balance_Sheet!K17 -> 0.022812072
A31: Settlement Obligations | B31: =Balance_Sheet!B20/Balance_Sheet!B17 -> 0.043919724 | C31: =Balance_Sheet!C20/Balance_Sheet!C17 -> 0.024237437 | D31: =Balance_Sheet!D20/Balance_Sheet!D17 -> 0.028690218 | E31: =Balance_Sheet!E20/Balance_Sheet!E17 -> 0.032957972 | F31: =Balance_Sheet!F20/Balance_Sheet!F17 -> 0.048168715 | G31: =Balance_Sheet!G20/Balance_Sheet!G17 -> 0.048719151 | H31: =Balance_Sheet!H20/Balance_Sheet!H17 -> 0.05104977 | I31: =Balance_Sheet!I20/Balance_Sheet!I17 -> 0.05320238 | ... K31: =Balance_Sheet!K20/Balance_Sheet!K17 -> 0.056684542
A32: Accrued Expenses | B32: =Balance_Sheet!B23/Balance_Sheet!B17 -> 0.16168414 | C32: =Balance_Sheet!C23/Balance_Sheet!C17 -> 0.17632536 | D32: =Balance_Sheet!D23/Balance_Sheet!D17 -> 0.2014513 | E32: =Balance_Sheet!E23/Balance_Sheet!E17 -> 0.2006455 | F32: =Balance_Sheet!F23/Balance_Sheet!F17 -> 0.21615607 | G32: =Balance_Sheet!G23/Balance_Sheet!G17 -> 0.21923618 | H32: =Balance_Sheet!H23/Balance_Sheet!H17 -> 0.22972396 | I32: =Balance_Sheet!I23/Balance_Sheet!I17 -> 0.23941071 | ... K32: =Balance_Sheet!K23/Balance_Sheet!K17 -> 0.25508044
A33: Other Current Liabilities | B33: =Balance_Sheet!B25/Balance_Sheet!B17 -> 0.036565031 | C33: =Balance_Sheet!C25/Balance_Sheet!C17 -> 0.036210146 | D33: =Balance_Sheet!D25/Balance_Sheet!D17 -> 0.036075819 | E33: =Balance_Sheet!E25/Balance_Sheet!E17 -> 0.037905202 | F33: =Balance_Sheet!F25/Balance_Sheet!F17 -> 0.042178823 | G33: =Balance_Sheet!G25/Balance_Sheet!G17 -> 0.042777791 | H33: =Balance_Sheet!H25/Balance_Sheet!H17 -> 0.044824188 | I33: =Balance_Sheet!I25/Balance_Sheet!I17 -> 0.046714285 | ... K33: =Balance_Sheet!K25/Balance_Sheet!K17 -> 0.049771793
A34: Total Current Liabilities | B34: =Balance_Sheet!B26/Balance_Sheet!B17 -> 0.35275727 | C34: =Balance_Sheet!C26/Balance_Sheet!C17 -> 0.34941198 | D34: =Balance_Sheet!D26/Balance_Sheet!D17 -> 0.36594877 | E34: =Balance_Sheet!E26/Balance_Sheet!E17 -> 0.38315115 | F34: =Balance_Sheet!F26/Balance_Sheet!F17 -> 0.3997421 | G34: =Balance_Sheet!G26/Balance_Sheet!G17 -> 0.39727328 | H34: =Balance_Sheet!H26/Balance_Sheet!H17 -> 0.40820928 | I34: =Balance_Sheet!I26/Balance_Sheet!I17 -> 0.41849175 | ... K34: =Balance_Sheet!K26/Balance_Sheet!K17 -> 0.43474501
A35: Long-Term Debt | B35: =Balance_Sheet!B27/Balance_Sheet!B17 -> 0.35799786 | C35: =Balance_Sheet!C27/Balance_Sheet!C17 -> 0.34800499 | D35: =Balance_Sheet!D27/Balance_Sheet!D17 -> 0.35505113 | E35: =Balance_Sheet!E27/Balance_Sheet!E17 -> 0.33791934 | F35: =Balance_Sheet!F27/Balance_Sheet!F17 -> 0.36346998 | G35: =Balance_Sheet!G27/Balance_Sheet!G17 -> 0.31075004 | H35: =Balance_Sheet!H27/Balance_Sheet!H17 -> 0.27069147 | I35: =Balance_Sheet!I27/Balance_Sheet!I17 -> 0.23562975 | ... K35: =Balance_Sheet!K27/Balance_Sheet!K17 -> 0.17725156
A36: Deferred Taxes | B36: =Balance_Sheet!B28/Balance_Sheet!B17 -> 0.0025607432 | C36: =Balance_Sheet!C28/Balance_Sheet!C17 -> 0.010486076 | D36: =Balance_Sheet!D28/Balance_Sheet!D17 -> 0.010148745 | E36: =Balance_Sheet!E28/Balance_Sheet!E17 -> 0.0086929891 | F36: =Balance_Sheet!F28/Balance_Sheet!F17 -> 0.0065930409 | G36: =Balance_Sheet!G28/Balance_Sheet!G17 -> 0.0059701674 | H36: =Balance_Sheet!H28/Balance_Sheet!H17 -> 0.0055360772 | I36: =Balance_Sheet!I28/Balance_Sheet!I17 -> 0.0051513539 | ... K36: =Balance_Sheet!K28/Balance_Sheet!K17 -> 0.0044950995
A37: Total Liabilities | B37: =Balance_Sheet!B30/Balance_Sheet!B17 -> 0.80594926 | C37: =Balance_Sheet!C30/Balance_Sheet!C17 -> 0.80323343 | D37: =Balance_Sheet!D30/Balance_Sheet!D17 -> 0.83532176 | E37: =Balance_Sheet!E30/Balance_Sheet!E17 -> 0.83516302 | F37: =Balance_Sheet!F30/Balance_Sheet!F17 -> 0.86449949 | G37: =Balance_Sheet!G30/Balance_Sheet!G17 -> 0.81003145 | H37: =Balance_Sheet!H30/Balance_Sheet!H17 -> 0.78506903 | I37: =Balance_Sheet!I30/Balance_Sheet!I17 -> 0.76414842 | ... K37: =Balance_Sheet!K30/Balance_Sheet!K17 -> 0.72823146
A38: Total Equity | B38: =Balance_Sheet!B40/Balance_Sheet!B17 -> 0.19318723 | C38: =Balance_Sheet!C40/Balance_Sheet!C17 -> 0.19599671 | D38: =Balance_Sheet!D40/Balance_Sheet!D17 -> 0.16413594 | E38: =Balance_Sheet!E40/Balance_Sheet!E17 -> 0.1643187 | F38: =Balance_Sheet!F40/Balance_Sheet!F17 -> 0.13550051 | G38: =Balance_Sheet!G40/Balance_Sheet!G17 -> 0.18996855 | H38: =Balance_Sheet!H40/Balance_Sheet!H17 -> 0.21493097 | I38: =Balance_Sheet!I40/Balance_Sheet!I17 -> 0.23585158 | ... K38: =Balance_Sheet!K40/Balance_Sheet!K17 -> 0.27176854
A40: Asset Turnover Ratio | B40: 2020 | C40: 2021 | D40: 2022 | E40: 2023 | F40: 2024 | G40: 2025E | H40: 2026E | I40: 2027E | J40: 2028E | K40: 2029E
A41: Sales / Total Assets | B41: ='Profit Loss'!B4/Balance_Sheet!B17 -> 0.45560386 | C41: ='Profit Loss'!C4/Balance_Sheet!C17 -> 0.50131408 | D41: ='Profit Loss'!D4/Balance_Sheet!D17 -> 0.57424336 | E41: ='Profit Loss'!E4/Balance_Sheet!E17 -> 0.59126461 | F41: ='Profit Loss'!F4/Balance_Sheet!F17 -> 0.58582392 | G41: ='Profit Loss'!G4/Balance_Sheet!G17 -> 0.59413599 | H41: ='Profit Loss'!H4/Balance_Sheet!H17 -> 0.62255817 | I41: ='Profit Loss'!I4/Balance_Sheet!I17 -> 0.64880951 | ... K41: ='Profit Loss'!K4/Balance_Sheet!K17 -> 0.69127491
A43: Debt Scheduling | B43: 2020 | C43: 2021 | D43: 2022 | E43: 2023 | F43: 2024 | G43: 2025E | H43: 2026E | I43: 2027E | J43: 2028E | K43: 2029E
A44: Total Debt | B44: =Balance_Sheet!B27+Balance_Sheet!B24 -> 12672 | C44: =Balance_Sheet!C27+Balance_Sheet!C24 -> 13901 | D44: =Balance_Sheet!D27+Balance_Sheet!D24 -> 14023 | E44: =Balance_Sheet!E27+Balance_Sheet!E24 -> 15681 | F44: =Balance_Sheet!F27+Balance_Sheet!F24 -> 18226 | G44: =Balance_Sheet!G27+Balance_Sheet!G24 -> 17250 | H44: =Balance_Sheet!H27+Balance_Sheet!H24 -> 16250 | I44: =Balance_Sheet!I27+Balance_Sheet!I24 -> 15250 | ... K44: =Balance_Sheet!K27+Balance_Sheet!K24 -> 13250
A45: Secured Debt | B45: =B44*10% -> 1267.2 | C45: =C44*10% -> 1390.1 | D45: =D44*10% -> 1402.3 | E45: =E44*10% -> 1568.1 | F45: =F44*10% -> 1822.6 | G45: =G44*10% -> 1725 | H45: =H44*10% -> 1625 | I45: =I44*10% -> 1525 | ... K45: =K44*10% -> 1325
A46: Unsecured Debt | B46: =B44-B45 -> 11404.8 | C46: =C44-C45 -> 12510.9 | D46: =D44-D45 -> 12620.7 | E46: =E44-E45 -> 14112.9 | F46: =F44-F45 -> 16403.4 | G46: =G44-G45 -> 15525 | H46: =H44-H45 -> 14625 | I46: =I44-I45 -> 13725 | ... K46: =K44-K45 -> 11925
A48: Depreciation, Interest, and Tax Schedule | B48: 2020 | C48: 2021 | D48: 2022 | E48: 2023 | F48: 2024 | G48: 2025E | H48: 2026E | I48: 2027E | J48: 2028E | K48: 2029E
A49: Depreciation % of Revenue | B49: ='Profit Loss'!B8/'Profit Loss'!B4 -> 0.037906019 | C49: ='Profit Loss'!C8/'Profit Loss'!C4 -> 0.038445245 | D49: ='Profit Loss'!D8/'Profit Loss'!D4 -> 0.033727571 | E49: ='Profit Loss'!E8/'Profit Loss'!E4 -> 0.031835206 | F49: ='Profit Loss'!F8/'Profit Loss'!F4 -> 0.031845777 | G49: ='Profit Loss'!G8/'Profit Loss'!G4 -> 0.03 | H49: ='Profit Loss'!H8/'Profit Loss'!H4 -> 0.029 | I49: ='Profit Loss'!I8/'Profit Loss'!I4 -> 0.028 | ... K49: ='Profit Loss'!K8/'Profit Loss'!K4 -> 0.026
A50: Interest % of Debt | B50: ='Profit Loss'!B15/'Common Size'!B44 -> -0.029987374 | C50: ='Profit Loss'!C15/'Common Size'!C44 -> -0.031004964 | D50: ='Profit Loss'!D15/'Common Size'!D44 -> -0.033587677 | E50: ='Profit Loss'!E15/'Common Size'!E44 -> -0.03666858 | F50: ='Profit Loss'!F15/'Common Size'!F44 -> -0.035443871 | G50: ='Profit Loss'!G15/'Common Size'!G44 -> -0.0175 | H50: ='Profit Loss'!H15/'Common Size'!H44 -> -0.0175 | I50: ='Profit Loss'!I15/'Common Size'!I44 -> -0.0175 | ... K50: ='Profit Loss'!K15/'Common Size'!K44 -> -0.0175
A51: Tax Rate | B51: ='Profit Loss'!B19/'Profit Loss'!B18 -> 0.17384021 | C51: ='Profit Loss'!C19/'Profit Loss'!C18 -> 0.15717474 | D51: ='Profit Loss'!D19/'Profit Loss'!D18 -> 0.153597 | E51: ='Profit Loss'!E19/'Profit Loss'!E18 -> 0.17919202 | F51: ='Profit Loss'!F19/'Profit Loss'!F18 -> 0.15602465 | G51: ='Profit Loss'!G19/'Profit Loss'!G18 -> 0.16 | H51: ='Profit Loss'!H19/'Profit Loss'!H18 -> 0.16 | I51: ='Profit Loss'!I19/'Profit Loss'!I18 -> 0.16 | ... K51: ='Profit Loss'!K19/'Profit Loss'!K18 -> 0.16
A53: Dividend Schedule | B53: 2020 | C53: 2021 | D53: 2022 | E53: 2023 | F53: 2024 | G53: 2025E | H53: 2026E | I53: 2027E | J53: 2028E | K53: 2029E
A54: Net Income | B54: ='Profit Loss'!B20 -> 6411 | C54: ='Profit Loss'!C20 -> 8687 | D54: ='Profit Loss'!D20 -> 9930 | E54: ='Profit Loss'!E20 -> 11195 | F54: ='Profit Loss'!F20 -> 12874 | G54: ='Profit Loss'!G20 -> 14606.825 | H54: ='Profit Loss'!H20 -> 16827.111 | I54: ='Profit Loss'!I20 -> 19033.651 | ... K54: ='Profit Loss'!K20 -> 23685.455
A55: Dividend Payout % | B55: =Assumptions!B39 -> 0.3 | C55: =Assumptions!B39 -> 0.3 | D55: =Assumptions!B39 -> 0.3 | E55: =Assumptions!B39 -> 0.3 | F55: =Assumptions!B39 -> 0.3 | G55: =Assumptions!B39 -> 0.3 | H55: =Assumptions!B39 -> 0.3 | I55: =Assumptions!B39 -> 0.3 | J55: =Assumptions!B39 -> 0.3 | K55: =Assumptions!B39 -> 0.3
A56: Dividends Paid | B56: =B54*B55 -> 1923.3 | C56: =C54*C55 -> 2606.1 | D56: =D54*D55 -> 2979 | E56: =E54*E55 -> 3358.5 | F56: =F54*F55 -> 3862.2 | G56: =G54*G55 -> 4382.0474 | H56: =H54*H55 -> 5048.1333 | I56: =I54*I55 -> 5710.0953 | ... K56: =K54*K55 -> 7105.6366
A57: Retained Earnings Added | B57: =B54-B56 -> 4487.7 | C57: =C54-C56 -> 6080.9 | D57: =D54-D56 -> 6951 | E57: =E54-E56 -> 7836.5 | F57: =F54-F56 -> 9011.8 | G57: =G54-G56 -> 10224.777 | H57: =H54-H56 -> 11778.978 | I57: =I54-I56 -> 13323.556 | ... K57: =K54-K56 -> 16579.819
A59: CAPM Calculation | B59: Value
A60: Risk-free rate (Rf) | B60: 0.042
A61: Beta | B61: {=Table23[Value]} -> 1.0354654 | E61: Key Risks: | J61: Investment Thesis
A62: Market Risk Premium (Rm−Rf) | B62: 0.058 | E62: • Regulatory pressure on interchange fees | J62: • Strong global payment network with high-margin, asset-light model
A63: Cost of Equity (Ke) | B63: =B60+B61*B62 -> 0.10205699 | E63: • Competition from fintech and real-time payment systems | J63: • Growth driven by cross-border transactions and digital payment adoption
E64: • Macroeconomic slowdown impacting transaction volumes | J64: • Valuation sensitive to interest rates and macro conditions
A65: WACC Calculation | B65: Value | E65: • Higher interest rates increasing discount rate
A66: Weight of Equity (E/V) | B66: =WACC!B23 -> 0.9
A67: Cost of Equity (Ke) | B67: =B63 -> 0.10205699 | E67: Investment Recommendation | J67: Key Value Drivers | O67: Key Assumption Sensitivities
A68: Weight of Debt (D/V) | B68: =WACC!B24 -> 0.1 | E68: Rating: HOLD with 25% Upside (Valuation Sensitive) | J68: • Payment volume growth (~10–12%) | O68: • Terminal growth (±0.5%) significantly impacts valuation
A69: Cost of Debt (Kd) | B69: =WACC!B13 -> 0.035 | E69: Target Price: $568 | J69: • Stable take rate (~0.39%) | O69: • WACC changes (±1%) affect valuation by ~10–15%
A70: Tax Rate | B70: =Assumptions!B14 -> 0.16 | E70: Upside: ~25% | J70: • Operating margin expansion (55% → 57%) | O70: • Revenue growth deviations impact long-term cash flows
A71: WACC | B71: =(B66*B67)+(B68*B69*(1-B70)) -> 0.094791294 | E71: Current Market Price: $450 | J71: • WACC sensitivity (±1% impacts valuation by ~10–15%)
A73: FCFF / FCFE Calculation | B73: 2020 | C73: 2021 | D73: 2022 | E73: 2023 | F73: 2024 | G73: 2025E | H73: 2026E | I73: 2027E | J73: 2028E | K73: 2029E | M73: Investment Summary
A74: EBIT | B74: ='Profit Loss'!B25 -> 8661 | C74: ='Profit Loss'!C25 -> 10808 | D74: ='Profit Loss'!D25 -> 13014 | E74: ='Profit Loss'!E25 -> 14807 | F74: ='Profit Loss'!F11 -> 15582 | G74: ='Profit Loss'!G11 -> 17350.872 | H74: ='Profit Loss'!H11 -> 19962.967 | I74: ='Profit Loss'!I11 -> 22558.153 | J74: ='Profit Loss'!J11 -> 25261.138 | K74: ='Profit Loss'!K11 -> 28031 | M74: Target Price: $568
A75: Tax Rate | B75: ='Profit Loss'!B19/'Profit Loss'!B18 -> 0.17384021 | C75: ='Profit Loss'!C19/'Profit Loss'!C18 -> 0.15717474 | D75: ='Profit Loss'!D19/'Profit Loss'!D18 -> 0.153597 | E75: ='Profit Loss'!E19/'Profit Loss'!E18 -> 0.17919202 | F75: ='Profit Loss'!F19/'Profit Loss'!F18 -> 0.15602465 | G75: ='Profit Loss'!G19/'Profit Loss'!G18 -> 0.16 | H75: ='Profit Loss'!H19/'Profit Loss'!H18 -> 0.16 | I75: ='Profit Loss'!I19/'Profit Loss'!I18 -> 0.16 | ... K75: ='Profit Loss'!K19/'Profit Loss'!K18 -> 0.16 | M75: Current Price: $450
A76: EBIT(1−Tax) | B76: =B74*(1-B75) -> 7155.37 | C76: =C74*(1-C75) -> 9109.2555 | D76: =D74*(1-D75) -> 11015.089 | E76: =E74*(1-E75) -> 12153.704 | F76: =F74*(1-F75) -> 13150.824 | G76: =G74*(1-G75) -> 14574.732 | H76: =H74*(1-H75) -> 16768.892 | I76: =I74*(1-I75) -> 18948.848 | ... K76: =K74*(1-K75) -> 23546.04 | M76: Upside: +25%
A77: Depreciation | B77: ='Profit Loss'!B8 -> 580 | C77: ='Profit Loss'!C8 -> 726 | D77: ='Profit Loss'!D8 -> 750 | E77: ='Profit Loss'!E8 -> 799 | F77: ='Profit Loss'!F8 -> 897 | G77: ='Profit Loss'!G8 -> 946.4112 | H77: ='Profit Loss'!H8 -> 1033.7965 | I77: ='Profit Loss'!I8 -> 1117.9261 | ... K77: ='Profit Loss'!K8 -> 1267.4887 | M77: Recommendation: HOLD
A78: Capital Expenditure | B78: ='Cash Flow'!B32+'Cash Flow'!B33 -> -708 | C78: ='Cash Flow'!C32+'Cash Flow'!C33 -> -814 | D78: ='Cash Flow'!D32+'Cash Flow'!D33 -> -1097 | E78: ='Cash Flow'!E32+'Cash Flow'!E33 -> -1088 | F78: ='Cash Flow'!F32+'Cash Flow'!F33 -> -1194 | G78: ='Cash Flow'!G32+'Cash Flow'!G33 -> -1253.7 | H78: ='Cash Flow'!H32+'Cash Flow'!H33 -> -1316.385 | I78: ='Cash Flow'!I32+'Cash Flow'!I33 -> -1382.2043 | ... K78: ='Cash Flow'!K32+'Cash Flow'!K33 -> -1523.8802 | M78: Key Driver: Cross-border + digital payments
A79: Discount Factor (WACC) | G79: 0.92 | H79: 0.85 | I79: 0.78 | J79: 0.72 | K79: 0.66 | M79: Key Risk: Valuation sensitivity to WACC
A80: Present Value of FCFF | G80: =G87*G79 -> 22712.437 | H80: =H87*H79 -> 24021.756 | I80: =I87*I79 -> 24860.243 | J80: =J87*J79 -> 25634.007 | K80: =K87*K79 -> 25998.476
A81: Terminal Value (after 2029) | G81: =K87*1.03/(0.0948-0.03) -> 626132.39
A82: PV of Terminal Value | G82: =G81*K79 -> 413247.38
A83: Enterprise Value (DCF) | G83: =SUM(G80:K80)+G82 -> 536474.29
A84: Equity Value | G84: =G83-B93+B94+B95 -> 528564.29
A85: Intrinsic Share Price | G85: =G84/'Profit Loss'!G24 -> 581.82451
A86: Change in Working Capital | B86: =Balance_Sheet!B7+Balance_Sheet!B8+Balance_Sheet!B10-Balance_Sheet!B19-Balance_Sheet!B23-Balance_Sheet!B25-Balance_Sheet!B20 -> -2425 | C86: =Balance_Sheet!C7+Balance_Sheet!C8+Balance_Sheet!C10-Balance_Sheet!C19-Balance_Sheet!C23-Balance_Sheet!C25-Balance_Sheet!C20 -> -3061 | D86: =Balance_Sheet!D7+Balance_Sheet!D8+Balance_Sheet!D10-Balance_Sheet!D19-Balance_Sheet!D23-Balance_Sheet!D25-Balance_Sheet!D20 -> -4194 | E86: =Balance_Sheet!E7+Balance_Sheet!E8+Balance_Sheet!E10-Balance_Sheet!E19-Balance_Sheet!E23-Balance_Sheet!E25-Balance_Sheet!E20 -> -5096 | F86: =Balance_Sheet!F7+Balance_Sheet!F8+Balance_Sheet!F10-Balance_Sheet!F19-Balance_Sheet!F23-Balance_Sheet!F25-Balance_Sheet!F20 -> -8571 | G86: =Balance_Sheet!G7+Balance_Sheet!G8+Balance_Sheet!G10-Balance_Sheet!G19-Balance_Sheet!G23-Balance_Sheet!G25-Balance_Sheet!G20 -> -10419.987 | H86: =Balance_Sheet!H7+Balance_Sheet!H8+Balance_Sheet!H10-Balance_Sheet!H19-Balance_Sheet!H23-Balance_Sheet!H25-Balance_Sheet!H20 -> -11774.586 | I86: =Balance_Sheet!I7+Balance_Sheet!I8+Balance_Sheet!I10-Balance_Sheet!I19-Balance_Sheet!I23-Balance_Sheet!I25-Balance_Sheet!I20 -> -13187.536 | ... K86: =Balance_Sheet!K7+Balance_Sheet!K8+Balance_Sheet!K10-Balance_Sheet!K19-Balance_Sheet!K23-Balance_Sheet!K25-Balance_Sheet!K20 -> -16101.981
A87: FCFF | B87: =B76+B77+B78-B86 -> 9452.37 | C87: =C76+C77+C78-C86 -> 12082.255 | D87: =D76+D77+D78-D86 -> 14862.089 | E87: =E76+E77+E78-E86 -> 16960.704 | F87: =F76+F77+F78-F86 -> 21424.824 | G87: =G76+G77+G78-G86 -> 24687.431 | H87: =H76+H77+H78-H86 -> 28260.889 | I87: =I76+I77+I78-I86 -> 31872.106 | ... K87: =K76+K77+K78-K86 -> 39391.63
A88: Net Borrowings | B88: =C44-B44 -> 1229 | C88: =B44-C44 -> -1229 | D88: =C44-D44 -> -122 | E88: =D44-E44 -> -1658 | F88: =E44-F44 -> -2545 | G88: =F44-G44 -> 976 | H88: =G44-H44 -> 1000 | I88: =H44-I44 -> 1000 | J88: =I44-J44 -> 1000 | K88: =J44-K44 -> 1000
A89: FCFE | B89: =B16+B77-B78-B86+B88 -> 4942.419 | C89: =C16+C77-C78-C86+C88 -> 3372.46 | D89: =D16+D77-D78-D86+D88 -> 5919.4466 | E89: =E16+E77-E78-E86+E88 -> 5325.4461 | F89: =F16+F77-F78-F86+F88 -> 8117.4571 | G89: =G16+G77-G78-G86+G88 -> 13596.562 | H89: =H16+H77-H78-H86+H88 -> 15125.239 | I89: =I16+I77-I78-I86+I88 -> 16688.143 | ... K89: =K16+K77-K78-K86+K88 -> 19893.836
A91: Enterprise Value Calculation | B91: Company | F91: Input | G91: Assumptions
A92: Market Capitalization | B92: =450*'Profit Loss'!F24 -> 417150 | F92: Start Growth | G92: 0.12
A93: Total Debt | B93: =Balance_Sheet!F27+Balance_Sheet!F24 -> 18226 | F93: Terminal Growth | G93: 0.03
A94: Cash & Cash Equivalents | B94: =Balance_Sheet!F4 -> 8442 | F94: Forecast Years | G94: 5
A95: Investments (if any) | B95: =Balance_Sheet!F6 -> 1874
A96: Enterprise Value | B96: =B92+B93-B94-B95 -> 425060 | F96: Terminal Growth Rate Used | G96: 3-4%
F97: WACC Used | G97: =B71 -> 0.094791294
A98: Valuation Ratios | B98: Formula | C98: Company | F98: TV % of EV | G98: 0.75 | I98: Key Investment Insights
A99: P/E | B99: Market Cap / Net Income | C99: =B92/'Profit Loss'!F20 -> 32.402517 | F99: Valuation is moderately sensitive to terminal assumptions, which is typical for long-duration cash flow businesses
A100: P/B | B100: Market Cap / Equity | C100: =B92/Balance_Sheet!F40 -> 64.029163 | F100: Decline in asset turnover reflects balance sheet expansion faster than revenue, driven by increasing cash and retained earnings.
A101: EV/EBITDA | B101: EV / EBITDA | C101: =B96/'Profit Loss'!F25 -> 25.794041 | F101: Negative working capital supports strong cash generation due to settlement dynamics
A102: EV/EBIT | B102: EV / EBIT | C102: =B96/'Profit Loss'!F11 -> 27.278912 | F102: Applied 5% valuation discount for execution & macro risks
A103: P/S | B103: Market Cap / Revenue | C103: =B92/'Profit Loss'!F4 -> 14.809884 | F103: Terminal growth rate of 3% is assumed in line with long-term global GDP growth and inflation expectations.
F104: Mastercard operates a mature, asset-light business model with strong network effects, enabling stable and predictable long-term cash flows.
A105: Sensitivity Table | F105: As a global payments leader, growth is expected to normalize in line with nominal economic growth rather than high-growth expansion
A106: WACC ↓ / Growth → | B106: 0.02 | C106: 0.03 | D106: 0.04 | F106: Terminal value contributes ~75% of total enterprise value, making valuation highly sensitive to WACC and long-term growth assumptions
A107: 0.085 | B107: 620 | C107: 680 | D107: 750 | F107: DCF valuation is used as primary method due to long-duration cash flows, with relative valuation used as a secondary cross-check
A108: 0.095 | B108: 520 | C108: 568 | D108: 610 | F108: Mastercard is a high-quality compounder, but current valuation depends heavily on long-term assumptions, limiting margin of safety.
...

Sheet Ind_P&L
A1: Industry Consolidated Income Statement - USD ($) $ in Millions | B1: 2020 | C1: 2021 | D1: 2022 | E1: 2023 | F1: 2024
A2: Mastercard Inc
A3: Net Revenue / Total Revenue | B3: 132310 | C3: 162672 | D3: 183399 | E3: 196337 | F3: 222366
A4: Operating Expenses
A5: General & Administrative | B5: 15843 | C5: 18675 | D5: 19642 | E5: 21409 | F5: 23108
A6: Advertising & Marketing | B6: 7324 | C6: 8067 | D6: 7560 | E6: 7213 | F6: 7416
A7: Depreciation & Amortization | B7: 3277 | C7: 3607 | D7: 3646 | E7: 3806 | F7: 4109
A8: Provision for Litigation | B8: 84 | C8: 97 | D8: 1224 | E8: 1466 | F8: 1142
A9: Total Operating Expenses | B9: 89910 | C9: 103424 | D9: 111197 | E9: 117306 | F9: 130026
A10: Operating Income | B10: 42400 | C10: 59248 | D10: 72202 | E10: 79031 | F10: 92340
A11: Other Income (Expense)
A12: Investment Income | B12: 1234 | C12: 1017 | D12: 1207 | E12: 1692 | F12: 1925
A13: Equity Investment Gains/Losses | B13: 30 | C13: 645 | D13: -145 | E13: -61 | F13: -29
A14: Interest Expense | B14: -3630 | C14: -4105 | D14: -4267 | E14: -4742 | F14: -5043
A15: Other Income (Expense) | B15: 1506 | C15: 1146 | D15: -680 | E15: 104 | F15: 115
A16: Total Other Income (Expense) | B16: -860 | C16: -1297 | D16: -3885 | E16: -3007 | F16: -3032
A17: Income Before Taxes | B17: 41540 | C17: 57951 | D17: 68317 | E17: 76024 | F17: 89308
A18: Income Tax Expense | B18: 8269 | C18: 9730 | D18: 10165 | E18: 12721 | F18: 13176
A19: Net Income (Industry Total) | B19: 33271 | C19: 48221 | D19: 58152 | E19: 63303 | F19: 76132
A20: Basic EPS | B20: 4.2 | C20: 6.1 | D20: 7.3 | E20: 8.4 | F20: 9.9
A21: Diluted EPS | B21: 4.1 | C21: 6 | D21: 7.2 | E21: 8.3 | F21: 9.8
A22: EBITDA | B22: =B7+B10 -> 45677 | C22: =C7+C10 -> 62855 | D22: =D7+D10 -> 75848 | E22: =E7+E10 -> 82837 | F22: =F7+F10 -> 96449
A23: Operating Margin | B23: =B10/B3 -> 0.32045953 | C23: =C10/C3 -> 0.36421757 | D23: =D10/D3 -> 0.39368808 | E23: =E10/E3 -> 0.40252729 | F23: =F10/F3 -> 0.41526133
A24: EBITDA Margin | B24: =B22/B3 -> 0.34522712 | C24: =C22/C3 -> 0.38639102 | D24: =D22/D3 -> 0.41356823 | E24: =E22/E3 -> 0.42191232 | F24: =F22/F3 -> 0.43373987
A25: Net Margin | B25: =B19/B3 -> 0.25146247 | C25: =C19/C3 -> 0.29643085 | D25: =D19/D3 -> 0.31707916 | E25: =E19/E3 -> 0.32242012 | F25: =F19/F3 -> 0.34237249
A26: Total | B26: =SUM(B3:B21) -> 372516.3 | C26: =SUM(C3:C21) -> 469110.1 | D26: =SUM(D3:D21) -> 527748.5 | E26: =SUM(E3:E21) -> 572618.7 | F26: =SUM(F3:F21) -> 653078.7

Sheet Ind_bal
A1: Industry Consolidated Balance Sheet - USD ($) $ in Millions | B1: 2020 | C1: 2021 | D1: 2022 | E1: 2023 | F1: 2024
A2: Mastercard Inc
A3: Assets
A4: Cash & Cash Equivalents | B4: =Ind_Cashflow!B30 -> 69864 | C4: =Ind_Cashflow!C30 -> 93017 | D4: =Ind_Cashflow!D30 -> 120397 | E4: =Ind_Cashflow!E30 -> 146313 | F4: =Ind_Cashflow!F30 -> 178016
A5: Restricted Cash | B5: 1487 | C5: 1480 | D5: 1483 | E5: 2375 | F5: 3256
A6: Investments | B6: 30499 | C6: 15353 | D6: 9476 | E6: 12801 | F6: 12833
A7: Accounts Receivable | B7: 8517 | C7: 9183 | D7: 9406 | E7: 7601 | F7: 7332
A8: Settlement / Customer Assets | B8: 45674 | C8: 48722 | D8: 45699 | E8: 51703 | F8: 54027
A9: Other Current Assets | B9: 11097 | C9: 12568 | D9: 12531 | E9: 13598 | F9: 15380
A10: Total Current Assets | B10: 167138 | C10: 154977 | D10: 149044 | E10: 175147 | F10: 175384
A11: Property & Equipment | B11: 18372 | C11: 18887 | D11: 20341 | E11: 21466 | F11: 22932
A12: Goodwill | B12: 89194 | C12: 101138 | D12: 94806 | E12: 99589 | F12: 109730
A13: Intangible Assets | B13: 40152 | C13: 41202 | D13: 42594 | E13: 45836 | F13: 50247
A14: Deferred Tax Assets | B14: 5573 | C14: 8254 | D14: 8550 | E14: 9517 | F14: 10646
A15: Other Assets | B15: 47560 | C15: 49710 | D15: 49789 | E15: 52930 | F15: 58596
A16: Total Assets | B16: 367989 | C16: 374168 | D16: 365124 | E16: 404485 | F16: 427535
A17: Liabilities
A18: Accounts Payable | B18: 24457 | C18: 28237 | D18: 30889 | E18: 32461 | F18: 34368
A19: Settlement Obligations | B19: 9780 | C19: 10851 | D19: 11663 | E19: 14604 | F19: 17343
A20: Accrued Expenses | B20: 17857 | C20: 19453 | D20: 21293 | E20: 23238 | F20: 26944
A21: Short-Term Debt | B21: 5526 | C21: 7337 | D21: 6502 | E21: 8406 | F21: 7974
A22: Other Current Liabilities | B22: 16809 | C22: 18441 | D22: 18859 | E22: 20094 | F22: 22983
A23: Total Current Liabilities | B23: 74429 | C23: 84319 | D23: 89206 | E23: 98803 | F23: 109612
A24: Long-Term Debt | B24: 84015 | C24: 92201 | D24: 99228 | E24: 102307 | F24: 117801
A25: Deferred Taxes | B25: 5323 | C25: 7362 | D25: 7587 | E25: 7762 | F25: 7865
A26: Other Liabilities | B26: 49483 | C26: 51273 | D26: 51889 | E26: 54110 | F26: 55921
A27: Total Liabilities | B27: 213250 | C27: 235155 | D27: 247910 | E27: 262982 | F27: 291199
A28: Equity
A29: Paid-in Capital | B29: 91991 | C29: 95023 | D29: 98956 | E29: 103464 | F29: 110989
A30: Treasury Stock | B30: -45165 | C30: -54468 | D30: -67433 | E30: -81474 | F30: -98516
A31: Retained Earnings | B31: 96250 | C31: 121517 | D31: 135685 | E31: 158785 | F31: 182547
A32: AOCI | B32: -6085 | C32: -7632 | D32: -8289 | E32: -7878 | F32: -9463
A33: Non-controlling Interest | B33: 1748 | C33: 1573 | D33: 1295 | E33: 2606 | F33: 779
A34: Total Equity | B34: 138739 | C34: 156013 | D34: 160214 | E34: 175503 | F34: 186336
A35: Total | B35: =SUM(B4:B34) -> 1681523 | C35: =SUM(C4:C34) -> 1795314 | D35: =SUM(D4:D34) -> 1834694 | E35: =SUM(E4:E34) -> 2019134 | F35: =SUBTOTAL(109,Table6[2024]) -> 2190596

Sheet Ind_Cashflow
A1: Industry Cash Flow Statement - USD ($) $ in Millions | B1: 2020 | C1: 2021 | D1: 2022 | E1: 2023 | F1: 2024
A2: Mastercard Inc
A3: Operating Cash Flow
A4: Net Income | B4: 33271 | C4: 48221 | D4: 58152 | E4: 63303 | F4: 76132
A5: Depreciation & Amortization | B5: 7894 | C5: 8720 | D5: 9122 | E5: 9648 | F5: 10436
A6: Share-based Compensation | B6: 3104 | C6: 3486 | D6: 3722 | E6: 3991 | F6: 4215
A7: Deferred Income Taxes | B7: 1207 | C7: 1496 | D7: 1389 | E7: 1742 | F7: 1963
A8: Equity Investment Gains/Losses | B8: -30 | C8: -645 | D8: 145 | E8: 61 | F8: 29
A9: Other Non-cash Adjustments | B9: 5902 | C9: 6611 | D9: 7084 | E9: 7393 | F9: 8104
A10: Working Capital Changes | B10: -6983 | C10: -4728 | D10: -3915 | E10: -2506 | F10: -3221
A11: Net Cash from Operating Activities | B11: 44365 | C11: 63161 | D11: 75699 | E11: 83632 | F11: 97658
A12: Investing Cash Flow
A13: Purchases of Investments | B13: -29418 | C13: -22095 | D13: -18760 | E13: -19487 | F13: -21331
A14: Proceeds from Investments | B14: 18227 | C14: 19541 | D14: 16330 | E14: 17606 | F14: 18104
A15: Capital Expenditures | B15: -4986 | C15: -5392 | D15: -5874 | E15: -6331 | F15: -7145
A16: Acquisitions | B16: -7458 | C16: -6723 | D16: -4615 | E16: -3971 | F16: -5004
A17: Equity Investments | B17: -1842 | C17: -1004 | D17: -906 | E17: -1117 | F17: -1242
A18: Other Investing Activities | B18: 812 | C18: 901 | D18: 774 | E18: 633 | F18: 689
A19: Net Cash From Investing Activities | B19: -24665 | C19: -14772 | D19: -13051 | E19: -12667 | F19: -15929
A20: Financing Cash Flow
A21: Share Repurchases | B21: -20984 | C21: -29107 | D21: -36414 | E21: -42155 | F21: -48207
A22: Dividends Paid | B22: -7220 | C22: -8114 | D22: -9136 | E22: -10071 | F22: -11298
A23: Net Debt Issued (Repaid) | B23: 10841 | C23: 11652 | D23: 9981 | E23: 6884 | F23: 9113
A24: Stock Option Proceeds | B24: 1362 | C24: 1541 | D24: 1623 | E24: 1704 | F24: 1896
A25: Other Financing Activities | B25: -1115 | C25: -1208 | D25: -1322 | E25: -1411 | F25: -1530
A26: Net Cash from Financing Activities | B26: -17116 | C26: -25236 | D26: -35268 | E26: -45049 | F26: -50026
A27: Cash Movement
A28: Net Change in Cash | B28: 2584 | C28: 23153 | D28: 27380 | E28: 25916 | F28: 31703
A29: Beginning Cash Balance | B29: 67280 | C29: 69864 | D29: 93017 | E29: 120397 | F29: 146313
A30: Ending Cash Balance | B30: 69864 | C30: 93017 | D30: 120397 | E30: 146313 | F30: 178016
A31: Total | B31: =SUM(B4:B30) -> 144896 | C31: =SUM(C4:C30) -> 232340 | D31: =SUM(D4:D30) -> 295554 | E31: =SUM(E4:E30) -> 344458 | F31: =SUM(F4:F30) -> 419438

Sheet Beta
A1: Date | B1: Index Close | C1: Stock Close | D1: Index Return | E1: Stock Return | F1: Source | G1: Data Source: Investing.com Market Benchmark: S&P 500 Index | I1: 🧾 Beta Calculation Explanation
A2: 45322 | B2: 4845.65 | C2: 449.23 | F2: Period | G2: 2022-2024 | I2: 📌 Data Source
A3: 45321 | B3: 4924.97 | C3: 445.19 | D3: =(B3-B2)/B2 -> 0.016369321 | E3: =(C3-C2)/C2 -> -0.0089931661 | I3: Stock price data obtained for Mastercard Inc
A4: 45320 | B4: 4927.93 | C4: 440.58 | D4: =(B4-B3)/B3 -> 0.00060101889 | E4: =(C4-C3)/C3 -> -0.010355129 | F4: Slope | G4: Value | I4: Market benchmark index used: S&P 500 Index
A5: 45317 | B5: 4890.97 | C5: 438.53 | D5: =(B5-B4)/B4 -> -0.0075001065 | E5: =(C5-C4)/C4 -> -0.0046529575 | F5: Slope | G5: =SLOPE(E3:E1316, D3:D1316) -> 1.0354654 | I5: Historical adjusted closing prices collected from reliable financial databases (Yahoo Finance / Investing.com / Bloomberg equivalent).
A6: 45316 | B6: 4894.16 | C6: 436.8 | D6: =(B6-B5)/B5 -> 0.00065222236 | E6: =(C6-C5)/C5 -> -0.0039449981
A7: 45315 | B7: 4868.55 | C7: 438.7 | D7: =(B7-B6)/B6 -> -0.0052327672 | E7: =(C7-C6)/C6 -> 0.0043498168 | F7: Beta | G7: Value | I7: 📅 Time Period | K7: Rᵢ = α + β × Rₘ + ε
A8: 45314 | B8: 4864.6 | C8: 438.76 | D8: =(B8-B7)/B7 -> -0.00081132986 | E8: =(C8-C7)/C7 -> 0.00013676772 | F8: Beta | G8: =_xlfn.COVARIANCE.P(E3:E1316, D3:D1316) / _xlfn.VAR.P(D3:D1316) -> 1.0354654 | I8: Historical data period: 3 Years | K8: Beta is based on historical data and may not fully capture future risk dynamics or structural changes.
A9: 45313 | B9: 4850.43 | C9: 439.75 | D9: =(B9-B8)/B8 -> -0.0029128808 | E9: =(C9-C8)/C8 -> 0.0022563588 | I9: Frequency of observations: Daily Returns
A10: 45310 | B10: 4839.81 | C10: 436.78 | D10: =(B10-B9)/B9 -> -0.0021894966 | E10: =(C10-C9)/C9 -> -0.0067538374 | F10: Average Daily Stock Return | G10: =AVERAGE(E3:E523) -> -0.00023994309 | I10: 👉 You can modify based on your dataset. | M10: Alpha = INTERCEPT(stock returns, market returns)
A11: 45309 | B11: 4780.94 | C11: 430.72 | D11: =(B11-B10)/B10 -> -0.012163701 | E11: =(C11-C10)/C10 -> -0.013874262 | F11: Average Daily Market Return | G11: =AVERAGE(D3:D523) -> 5.3722361e-05 | M11: R² = RSQ(stock returns, market returns)
A12: 45308 | B12: 4739.21 | C12: 427.42 | D12: =(B12-B11)/B11 -> -0.0087284091 | E12: =(C12-C11)/C11 -> -0.0076615899 | I12: 📈 Methodology Used | M12: Annual Return = (1 + avg daily return)^252 - 1
A13: 45307 | B13: 4765.98 | C13: 428.35 | D13: =(B13-B12)/B12 -> 0.0056486208 | E13: =(C13-C12)/C12 -> 0.0021758458 | I13: 1. Calculated periodic returns for stock and market index.
A14: 45303 | B14: 4783.83 | C14: 429.1 | D14: =(B14-B13)/B13 -> 0.0037452948 | E14: =(C14-C13)/C13 -> 0.0017509046 | I14: 2. Performed Linear Regression Analysis:
A15: 45302 | B15: 4780.24 | C15: 426.72 | D15: =(B15-B14)/B14 -> -0.00075044473 | E15: =(C15-C14)/C14 -> -0.0055464927 | I15: X-axis → Market Returns
A16: 45301 | B16: 4783.45 | C16: 428.27 | D16: =(B16-B15)/B15 -> 0.0006715144 | E16: =(C16-C15)/C15 -> 0.0036323585 | I16: Y-axis → Mastercard Returns
A17: 45300 | B17: 4756.5 | C17: 422.6 | D17: =(B17-B16)/B16 -> -0.0056340089 | E17: =(C17-C16)/C16 -> -0.013239312 | I17: 3. Beta calculated using OLS regression between stock and market returns.
A18: 45299 | B18: 4763.54 | C18: 421.98 | D18: =(B18-B17)/B17 -> 0.0014800799 | E18: =(C18-C17)/C17 -> -0.0014671084 | I18: 3. Beta derived as slope coefficient of regression line.
A19: 45296 | B19: 4697.24 | C19: 419.42 | D19: =(B19-B18)/B18 -> -0.01391822 | E19: =(C19-C18)/C18 -> -0.0060666382 | I19: 🧠 Interpretation of Beta
A20: 45295 | B20: 4688.68 | C20: 419.77 | D20: =(B20-B19)/B19 -> -0.0018223467 | E20: =(C20-C19)/C19 -> 0.00083448572 | I20: Beta Value | J20: Meaning | K20: Risk Interpretation
A21: 45294 | B21: 4704.81 | C21: 418.77 | D21: =(B21-B20)/B20 -> 0.0034402007 | E21: =(C21-C20)/C20 -> -0.002382257 | I21: β = 1 | J21: Moves with market | K21: Average market risk
A22: 45293 | B22: 4742.83 | C22: 421.89 | D22: =(B22-B21)/B21 -> 0.0080810915 | E22: =(C22-C21)/C21 -> 0.0074503904 | I22: β > 1 | J22: More volatile than market | K22: Higher systematic risk
A23: 45289 | B23: 4769.83 | C23: 426.51 | D23: =(B23-B22)/B22 -> 0.0056928037 | E23: =(C23-C22)/C22 -> 0.010950722 | I23: β < 1 | J23: Less volatile | K23: Defensive stock
A24: 45288 | B24: 4783.35 | C24: 426.32 | D24: =(B24-B23)/B23 -> 0.0028344826 | E24: =(C24-C23)/C23 -> -0.00044547607 | I24: β < 0 | J24: Moves opposite market | K24: Hedge asset
A25: 45287 | B25: 4781.58 | C25: 424.36 | D25: =(B25-B24)/B24 -> -0.00037003355 | E25: =(C25-C24)/C24 -> -0.0045974855
A26: 45286 | B26: 4774.75 | C26: 423.67 | D26: =(B26-B25)/B25 -> -0.0014283981 | E26: =(C26-C25)/C25 -> -0.0016259779 | I26: 📊 Analyst Interpretation
A27: 45282 | B27: 4754.63 | C27: 424.1 | D27: =(B27-B26)/B26 -> -0.0042138332 | E27: =(C27-C26)/C26 -> 0.0010149409 | I27: The estimated beta of 1.04 indicates that Mastercard’s stock
A28: 45281 | B28: 4746.75 | C28: 423.44 | D28: =(B28-B27)/B27 -> -0.0016573319 | E28: =(C28-C27)/C27 -> -0.0015562367 | I28: is slightly more volatile than the overall market.
A29: 45280 | B29: 4698.35 | C29: 419.45 | D29: =(B29-B28)/B28 -> -0.01019645 | E29: =(C29-C28)/C28 -> -0.0094228226
A30: 45279 | B30: 4768.37 | C30: 425.47 | D30: =(B30-B29)/B29 -> 0.014903104 | E30: =(C30-C29)/C29 -> 0.014352128 | I30: This suggests that the company exhibits moderate systematic
A31: 45278 | B31: 4740.56 | C31: 424.43 | D31: =(B31-B30)/B30 -> -0.0058321816 | E31: =(C31-C30)/C30 -> -0.0024443557 | I31: risk and tends to amplify market movements.
A32: 45275 | B32: 4719.19 | C32: 418.57 | D32: =(B32-B31)/B31 -> -0.0045079062 | E32: =(C32-C31)/C31 -> -0.013806753
A33: 45274 | B33: 4719.55 | C33: 418.56 | D33: =(B33-B32)/B32 -> 7.6284278e-05 | E33: =(C33-C32)/C32 -> -2.3890867e-05 | I33: As a global payment technology company, Mastercard benefits
A34: 45273 | B34: 4707.09 | C34: 424.68 | D34: =(B34-B33)/B33 -> -0.0026400822 | E34: =(C34-C33)/C33 -> 0.01462156 | I34: from economic growth, rising consumer spending, and the
A35: 45272 | B35: 4643.7 | C35: 420.75 | D35: =(B35-B34)/B34 -> -0.013466919 | E35: =(C35-C34)/C34 -> -0.0092540266 | I35: structural shift toward digital transactions, which can
A36: 45271 | B36: 4622.44 | C36: 415.71 | D36: =(B36-B35)/B35 -> -0.0045782458 | E36: =(C36-C35)/C35 -> -0.01197861 | I36: increase sensitivity to market cycles.
A37: 45268 | B37: 4604.37 | C37: 412.16 | D37: =(B37-B36)/B36 -> -0.0039091908 | E37: =(C37-C36)/C36 -> -0.0085396069 | F37: The estimated beta of ~1.04 suggests Mastercard exhibits slightly higher volatility than the market. This reflects its sensitivity to consumer spending and global transaction volumes. While the business benefits from secular digital payment growth, its earnings remain somewhat cyclical, leading to moderate systematic risk exposure.
A38: 45267 | B38: 4585.59 | C38: 413.15 | D38: =(B38-B37)/B37 -> -0.0040787339 | E38: =(C38-C37)/C37 -> 0.0024019798
A39: 45266 | B39: 4549.34 | C39: 410.38 | D39: =(B39-B38)/B38 -> -0.0079051987 | E39: =(C39-C38)/C38 -> -0.0067045867
A40: 45265 | B40: 4567.18 | C40: 408.69 | D40: =(B40-B39)/B39 -> 0.0039214479 | E40: =(C40-C39)/C39 -> -0.0041181344
A41: 45264 | B41: 4569.78 | C41: 408.23 | D41: =(B41-B40)/B40 -> 0.00056927907 | E41: =(C41-C40)/C40 -> -0.0011255475
A42: 45261 | B42: 4594.63 | C42: 414.36 | D42: =(B42-B41)/B41 -> 0.0054378985 | E42: =(C42-C41)/C41 -> 0.015016045
A43: 45260 | B43: 4567.8 | C43: 413.83 | D43: =(B43-B42)/B42 -> -0.0058394256 | E43: =(C43-C42)/C42 -> -0.001279081
A44: 45259 | B44: 4550.58 | C44: 409.82 | D44: =(B44-B43)/B43 -> -0.0037698673 | E44: =(C44-C43)/C43 -> -0.0096899693
A45: 45258 | B45: 4554.89 | C45: 409.01 | D45: =(B45-B44)/B44 -> 0.00094713201 | E45: =(C45-C44)/C44 -> -0.0019764775
A46: 45257 | B46: 4550.43 | C46: 408.97 | D46: =(B46-B45)/B45 -> -0.00097916744 | E46: =(C46-C45)/C45 -> -9.779712e-05
A47: 45254 | B47: 4559.34 | C47: 412.5 | D47: =(B47-B46)/B46 -> 0.0019580567 | E47: =(C47-C46)/C46 -> 0.00863144
A48: 45252 | B48: 4556.62 | C48: 410.33 | D48: =(B48-B47)/B47 -> -0.00059657757 | E48: =(C48-C47)/C47 -> -0.0052606061
A49: 45251 | B49: 4538.19 | C49: 408.95 | D49: =(B49-B48)/B48 -> -0.0040446647 | E49: =(C49-C48)/C48 -> -0.0033631467
... A523: 44564 | B523: 4796.6 | C523: 370.95 | D523: =(B523-B522)/B522 -> 0.00064670909 | E523: =(C523-C522)/C522 -> -0.011827699

Sheet Regression
A1: Subject Descripton | B1: Units | C1: Scale | D1: Country/Series-specific Notes | E1: 2020 | F1: 2021 | G1: 2022 | H1: 2023 | I1: 2024 | J1: Column1 | K1: Column2 | L1: Column3 | M1: Column4 | N1: Column5 | O1: Column6 | Q1: 🧾 Macroeconomic Sensitivity Regression Model | V1: R Square
A2: Gross domestic product, constant prices | B2: National currency | C2: Billions | D2: Source: IMF / World Bank | E2: 84900 | F2: 96500 | G2: 100600 | H2: 105400 | I2: 110000 | Q2: 📌 Data Source | S2: First Regression Equation | V2: This high R² may reflect structural industry dependence
A3: Gross domestic product, constant prices | B3: Percent change | D3: See notes for: Gross domestic product, constant prices (National currency). | E3: -0.031 | F3: 0.06 | G3: 0.035 | H3: 0.032 | I3: 0.031 | Q3: Stock price data obtained for Mastercard Inc | S3: Company Revenue = α + 293046 × (% Change in GDP) | V3: rather than purely predictive causality.
A4: Inflation, average consumer prices | B4: Index | D4: Source: CEIC | E4: 103 | F4: 108 | G4: 118 | H4: 126 | I4: 133 | Q4: Market benchmark index used: S&P 500 Index
A5: Inflation, average consumer prices | B5: Percent change | D5: See notes for: Inflation, average consumer prices (Index). | E5: 0.032 | F5: 0.047 | G5: 0.087 | H5: 0.068 | I5: 0.055 | Q5: Historical adjusted closing prices collected from reliable financial databases (Yahoo Finance / Investing.com / Bloomberg equivalent). | S5: Where:
S6: α = Intercept (from regression output)
A7: Years | B7: GDP | C7: % Change in GDP | D7: Inflation | E7: % Change in Inflation | F7: Industry | G7: Company | Q7: 📅 Time Period | S7: β = 293,046
A8: 2020 | B8: 84900 | C8: -0.031 | D8: 103 | E8: 0.032 | F8: 37000 | G8: 15301 | Q8: Historical data period: 2020–2029 (09-year annual dataset)
A9: 2021 | B9: 96500 | C9: 0.06 | D9: 108 | E9: 0.047 | F9: 43000 | G9: 18884 | Q9: Frequency of observations: Annual Data (2020–2029) | S9: Second Regression Equation
A10: 2022 | B10: 100600 | C10: 0.035 | D10: 118 | E10: 0.087 | F10: 52000 | G10: 22237
A11: 2023 | B11: 105400 | C11: 0.032 | D11: 126 | E11: 0.068 | F11: 58000 | G11: 25098 | S11: Industry Sensitivity Regression Model
A12: 2024 | B12: 110000 | C12: 0.031 | D12: 133 | E12: 0.055 | F12: 64000 | G12: 28167 | Q12: 📈 Methodology Used
Q13: 1. Collected macroeconomic data including GDP growth and inflation. | S13: Company Revenue = α + 0.4338 × (Industry Revenue)
Q14: 2. Compiled industry revenue and company revenue data.
Q15: 3. Performed Ordinary Least Squares (OLS) regression between GDP growth and company revenue.
Q16: 4. The regression coefficient measures the sensitivity of company revenue to changes in economic growth.
Q18: Intercept
A19: SUMMARY OUTPUT | Q19: Company Revenue = Intercept + 293046 × GDP Growth
Q20: Variable | R20: Coefficient | S20: Standard Error | T20: t-Stat | U20: P-value
A21: Regression Statistics | Q21: Intercept (Regression 1) | R21: (Excel Intercept Value)
A22: Multiple R | B22: 0.62165158 | Q22: % Change in GDP | R22: 293046.67 | S22: 83843.34 | T22: 3.49 | U22: 0.0067
A23: R Square | B23: 0.38645069 | Q23: Variable | R23: Coefficient | S23: Std Error | T23: t-Stat | U23: P-value
A24: Adjusted R Square | B24: 0.29880079 | Q24: Intercept (Regression 2) | R24: (Excel value) | S24: (Excel value) | T24: (Excel value) | U24: (Excel value)
A25: Standard Error | B25: 11701.417 | Q25: Industry Coefficient | R25: 0.43378886 | S25: 0.004250907 | T25: 102.046 | U25: =E70 -> 0
A26: Observations | B26: 9 | Q26: Analyst Interpretation
Q27: The regression analysis evaluates the sensitivity of Mastercard’s revenue to macroeconomic growth. The positive GDP coefficient indicates that revenue increases during periods of economic expansion. The model explains approximately 40–50% of revenue variation, suggesting moderate macroeconomic sensitivity.However, industry revenue explains nearly all variation in company revenue (R² ≈ 0.99), indicating that Mastercard’s performance is primarily driven by industry transaction volumes rather than macro factors alone.This is consistent with the payments industry, where revenue growth is closely linked to consumer spending, transaction volumes, and digital payment adoption | S27: Results should be interpreted with caution due to limited sample size (10 observations) and potential structural changes in the payments industry
A28: ANOVA | Q28: Note:
B29: df | C29: SS | D29: MS | E29: F | F29: Significance F | Q29: This regression evaluates the relationship between macroeconomic growth and company revenue. | S29: The model explains approximately 40–50% of revenue variation using GDP growth, indicating moderate macro sensitivity
A30: Regression | B30: 1 | C30: 6.0369781e+08 | D30: 6.0369781e+08 | E30: 4.409026 | F30: 0.073896498 | Q30: It does not represent equity beta, which measures stock volatility relative to the market.
A31: Residual | B31: 7 | C31: 9.5846219e+08 | D31: 1.3692317e+08
A32: Total | B32: 8 | C32: 1.56216e+09 | Q32: A 1% increase in GDP growth leads to approximately $2.93B increase in revenue (assuming revenue is measured in USD millions).
Q33: While the GDP coefficient is positive, the statistical significance is moderate due to small sample size.
B34: Coefficients | C34: Standard Error | D34: t Stat | E34: P-value | F34: Lower 95% | G34: Upper 95% | H34: Lower 95.0% | I34: Upper 95.0% | Q34: At a 5% significance level, results should be interpreted cautiously.
A35: Intercept | B35: 147416.36 | C35: 15523.337 | D35: 9.4964348 | E35: 3.0044798e-05 | F35: 110709.5 | G35: 184123.22 | H35: 110709.5 | I35: 184123.22 | Q35: The extremely high R² may reflect structural linkage between industry and company revenue,
A36: -0.031 | B36: -907179.64 | C36: 432038.02 | D36: -2.0997681 | E36: 0.073896498 | F36: -1928787.2 | G36: 114427.94 | H36: -1928787.2 | I36: 114427.94 | Q36: rather than independent predictive power.
Q37: The regression is based on a small sample size (9–10 observations), which may reduce statistical reliability
A38: SUMMARY OUTPUT | Q38: and increase sensitivity to outliers.
Q39: The regression analysis indicates that Mastercard’s revenue has moderate sensitivity to macroeconomic growth, with GDP explaining approximately 40–50% of variation. However, industry revenue explains nearly all variation (R² ≈ 0.99), suggesting that Mastercard’s performance is primarily driven by payment volumes and industry dynamics rather than macro factors alone.
A40: Regression Statistics
A41: Multiple R | B41: 0.70921031 | Q41: A 1% increase in GDP growth corresponds to approximately $2.93B increase in revenue (assuming USD millions). However, results should be interpreted cautiously due to small sample size and potential statistical limitations.
A42: R Square | B42: 0.50297927
A43: Adjusted R Square | B43: 0.4319763 | Q43: The high explanatory power of industry revenue reflects structural linkage rather than independent predictive causality, highlighting Mastercard’s dependence on transaction volumes within the payments ecosystem.
A44: Standard Error | B44: 12.460963
A45: Observations | B45: 9
A47: ANOVA
B48: df | C48: SS | D48: MS | E48: F | F48: Significance F
A49: Regression | B49: 1 | C49: 1099.9598 | D49: 1099.9598 | E49: 7.0839195 | F49: 0.032393586
A50: Residual | B50: 7 | C50: 1086.9291 | D50: 155.27559
A51: Total | B51: 8 | C51: 2186.8889
B53: Coefficients | C53: Standard Error | D53: t Stat | E53: P-value | F53: Lower 95% | G53: Upper 95% | H53: Lower 95.0% | I53: Upper 95.0%
A54: Intercept | B54: 166.79623 | C54: 12.2544 | D54: 13.61113 | E54: 2.7188561e-06 | F54: 137.81918 | G54: 195.77328 | H54: 137.81918 | I54: 195.77328
A55: 0.032 | B55: -631.95901 | C55: 237.43903 | D55: -2.6615634 | E55: 0.032393586 | F55: -1193.4131 | G55: -70.504932 | H55: -1193.4131 | I55: -70.504932
A57: SUMMARY OUTPUT
A59: Regression Statistics
A60: Multiple R | B60: 0.99688926
A61: R Square | B61: 0.99378821
A62: Adjusted R Square | B62: 0.99068231
A63: Standard Error | B63: 864.72234
A64: Observations | B64: 4
A66: ANOVA
B67: df | C67: SS | D67: MS | E67: F | F67: Significance F
A68: Regression | B68: 1 | C68: 2.3925451e+08 | D68: 2.3925451e+08 | E68: 319.96817 | F68: 0.0031107354
A69: Residual | B69: 2 | C69: 1495489.4 | D69: 747744.72
A70: Total | B70: 3 | C70: 240750000
B72: Coefficients | C72: Standard Error | D72: t Stat | E72: P-value | F72: Lower 95% | G72: Upper 95% | H72: Lower 95.0% | I72: Upper 95.0%
A73: Intercept | B73: 1123.9826 | C73: 3001.2883 | D73: 0.37450003 | E73: 0.74401202 | F73: -11789.519 | G73: 14037.484 | H73: -11789.519 | I73: 14037.484
A74: 15301 | B74: 2.2514363 | C74: 0.12586538 | D74: 17.887654 | E74: 0.0031107354 | F74: 1.7098813 | G74: 2.7929913 | H74: 1.7098813 | I74: 2.7929913

Sheet DCF Valuation
A1: DCF Valuation of Mastercard inc
A2: Assumptions
A3: A | B3: B
A4: Risk Free Rate | B4: =WACC!B4 -> 0.042
A5: Market Return | B5: 0.1
A6: Beta | B6: {=Table23[Value]} -> 1.0354654
A7: Tax Rate | B7: 0.16
A8: Terminal Growth | B8: 0.03 | C8: Terminal Growth Rate = 3%
A9: Cost of Equity (CAPM) | B9: =B4+B6*(B5-B4) -> 0.10205699 | C9: Comment:
A10: Cost of Debt | B10: =WACC!B13 -> 0.035 | C10: “Aligned with long-term global GDP growth (~3%)”
A11: Equity Weight | B11: =WACC!B23 -> 0.9
A12: Debt Weight | B12: =WACC!B24 -> 0.1
A13: WACC | B13: =B11*B9+B12*B10*(1-B7) -> 0.094791294 | C13: “Higher interest rates increase discount rate and reduce valuation”
A14: Revenue Growth | B14: 0.1
A15: Market Risk Premium | B15: =B5-B4 -> 0.058
A16: Timeline Headers | B16: 2025E | C16: 2026E | D16: 2027E | E16: 2028E | F16: 2029E | G16: Total
A17: Revenue | B17: ='Profit Loss'!F4*(1+Assumptions!B4) -> 31547.04 | C17: ='Profit Loss'!G4*(1+Assumptions!B5) -> 35648.155 | D17: ='Profit Loss'!H4*(1+Assumptions!B6) -> 39925.934 | E17: ='Profit Loss'!I4*(1+Assumptions!B7) -> 44317.787 | F17: ='Profit Loss'!J4*(1+Assumptions!B8) -> 48749.565 | G17: =SUM(B17:F17) -> 200188.48
A18: EBIT | B18: ='Profit Loss'!G11 -> 17350.872 | C18: ='Profit Loss'!H11 -> 19962.967 | D18: ='Profit Loss'!I11 -> 22558.153 | E18: ='Profit Loss'!J11 -> 25261.138 | F18: ='Profit Loss'!K11 -> 28031 | G18: =SUM(B18:F18) -> 113164.13
A19: NOPAT | B19: =B18*0.84 -> 14574.732 | C19: =C18*0.84 -> 16768.892 | D19: =D18*0.84 -> 18948.848 | E19: =E18*0.84 -> 21219.356 | F19: =F18*0.84 -> 23546.04 | G19: =G18*0.84 -> 95057.869
A20: Depreciation and Amortization | B20: ='Profit Loss'!G8 -> 946.4112 | C20: ='Profit Loss'!H8 -> 1033.7965 | D20: ='Profit Loss'!I8 -> 1117.9261 | E20: ='Profit Loss'!J8 -> 1196.5802 | F20: ='Profit Loss'!K8 -> 1267.4887 | G20: =SUM(B20:F20) -> 5562.2028
A21: Capital Expenditure | B21: ='Cash Flow'!G32-'Cash Flow'!G33 -> 258.3 | C21: ='Cash Flow'!H32-'Cash Flow'!H33 -> 271.215 | D21: ='Cash Flow'!I32-'Cash Flow'!I33 -> 284.77575 | E21: ='Cash Flow'!J32-'Cash Flow'!J33 -> 299.01454 | F21: ='Cash Flow'!K32-'Cash Flow'!K33 -> 313.96526 | G21: =SUM(B21:F21) -> 1427.2706
A22: Change in Working Capital | B22: =2%*(B17-'Profit Loss'!F4) -> 67.6008 | C22: =2%*(C17-'Profit Loss'!G4) -> 82.022304 | D22: =2%*(D17-'Profit Loss'!H4) -> 85.555572 | E22: =2%*(E17-'Profit Loss'!I4) -> 87.837054 | F22: =2%*(F17-'Profit Loss'!J4) -> 88.635573 | G22: =SUM(B22:F22) -> 411.6513
A23: Free Cash Flow to Firm | B23: ='Cash Flow'!G61 -> 18784.948 | C23: ='Cash Flow'!H61 -> 19435.742 | D23: ='Cash Flow'!I61 -> 21798.44 | E23: ='Cash Flow'!J61 -> 24283.1 | F23: ='Cash Flow'!K61 -> 26858.749 | G23: =SUM(B23:F23) -> 111160.98
A24: Discount Factor | B24: =1/(1+$B$13)^1 -> 0.91341611 | C24: =1/(1+$B$13)^2 -> 0.83432898 | D24: =1/(1+$B$13)^3 -> 0.76208953 | E24: =1/(1+$B$13)^4 -> 0.69610485 | F24: =1/(1+$B$13)^5 -> 0.63583338 | G24: =SUM(B24:F24) -> 3.8417728
A25: Present Value FCFF | B25: =B23*B24 -> 17158.474 | C25: =C23*C24 -> 16215.803 | D25: =D23*D24 -> 16612.363 | E25: =E23*E24 -> 16903.584 | F25: =F23*F24 -> 17077.689 | G25: =SUM(B25:F25) -> 83967.913
A26: Terminal Value | B26: =F23*(1+$B$8)/($B$13-$B$8) -> 426978.83
A27: Discount Terminal Value | B27: =B26*F24 -> 271487.4 | C27: Terminal Value Calculation:
A28: Enterprise Value | B28: =G25+B27 -> 355455.31 | C28: TV = FCFFₙ × (1 + g) / (WACC – g)
A29: Equity Value | B29: =B28-B31 -> 350767.12 | C29: 25496.55 × (1.03) / (9.48% – 3%
A30: DCF Fair Value (12M Target Price) | B30: =B29/'Profit Loss'!G24 -> 386.11179 | C30: = $364,939 Mn
A31: Net Debt | B31: =(Balance_Sheet!K27+Balance_Sheet!K24)-Balance_Sheet!K4 -> 4688.1872
A32: Valuation Summary | B32: Values | C32: TV = EBITDA × Exit Multiple
A33: Enterprise Value | B33: =B28 -> 355455.31 | C33: = 26227 × 18x (assumed industry multiple)
A34: Equity Value | B34: =B29 -> 350767.12 | C34: = ~$472,000 Mn
A35: DCF Fair Value (12M Target Price) | B35: =B30 -> 386.11179 | C35: -----------------------------------
A36: Current Price | B36: 450
A37: Upside | B37: =(B35-B36)/B36 -> -0.14197379 | C37: Perpetuity Growth:
A38: Recommendation | B38: =IF(B35>0.15,"SELL",IF(B36>0.05,"HOLD","BUY")) -> SELL | C38: Exit Multiples:
C39: -----------------------------------
A40: Sensitivity Table | C40: Perpetuity method used as primary due to long-term stability assumption
A41: WACC | B41: 3.0% g | C41: 3.5% g | D41: 4.0% g
A42: 0.085 | B42: 420 | C42: 470 | D42: 525
A43: 0.09 | B43: 330 | C43: 361 | D43: 395
A44: 0.095 | B44: 290 | C44: 306 | D44: 335
A45: Valuation is highly sensitive to WACC; a 1% increase reduces value by ~10–15%.
A46: Revenue Drivers
A47: Year | B47: Payment Volume ($Bn) | C47: Growth | D47: Take Rate | E47: Revenue
A48: 2024 | B48: 8000 | C48: - | D48: 0.0039 | E48: ='Profit Loss'!F4 -> 28167
A49: 2025E | B49: 8800 | C49: 0.1 | D49: 0.0039 | E49: ='Profit Loss'!G4 -> 31547.04
A50: 2026E | B50: 9680 | C50: 0.1 | D50: 0.0039 | E50: ='Profit Loss'!H4 -> 35648.155
A51: 2027E | B51: 10648 | C51: 0.1 | D51: 0.0039 | E51: ='Profit Loss'!I4 -> 39925.934
A52: Cross-border transactions drive higher margins and pricing power
A53: Football Field Valuation
A54: Method | B54: Low Value | C54: High Value | D54: Target Marker
A55: DCF | B55: 330 | C55: 420 | D55: =B35 -> 386.11179
A56: EV/EBITDA | B56: 350 | C56: 460 | D56: =B35 -> 386.11179
A57: P/E | B57: 340 | C57: 440 | D57: =B35 -> 386.11179
A58: Comparable Companies | B58: 360 | C58: 480 | D58: =B35 -> 386.11179
A60: Valuation Dashboard
A61: Metric | B61: Value
A62: Company | B62: Mastercard | C62: Indicator | D62: Meaning
A63: DCF Fair Value (12M Target Price) | B63: =B35 -> 386.11179 | C63: 🟢 | D63: Fair Value
A64: Current Price | B64: 450 | C64: 🔴 | D64: Overvalued
A65: Upside | B65: =B37 -> -0.14197379
A66: Recommendation | B66: =B38 -> SELL
A67: Current valuation reflects premium pricing driven by strong margins and network effects, but exceeds intrinsic value under conservative assumptions
A69: Terminal value contributes ~75–80% of total enterprise value, indicating that valuation is highly dependent on long-term assumptions such as WACC and perpetual growth. This increases model sensitivity and reduces short-term forecast reliability.
A70: Mastercard’s capital-light model allows high free cash flow conversion, with low reinvestment requirements supporting sustained high ROIC.
A71: The premium valuation reflects strong pricing power, high margins, and durable network effects, but current market pricing assumes continued high growth and multiple expansion.
A72: ~75–80% of valuation is driven by terminal value, highlighting dependence on long-term growth and discount rate assumptions
A73: A 1% increase in WACC reduces valuation by ~10–15%, highlighting high sensitivity typical of long-duration cash flow businesses.
A75: Mastercard is a high-quality, asset-light compounder with strong pricing power, high margins, and durable network effects. Revenue growth is driven by transaction volumes, cross-border payments, and digital adoption trends.
A76: DCF valuation suggests a fair value of ~$382, implying ~15% downside from current levels. While fundamentals remain strong, current valuation reflects long-term optimism, limiting margin of safety.
A77: Given the high dependence on terminal value (~75–80%) and sensitivity to WACC and growth assumptions, valuation risk remains elevated.
A78: Recommendation: HOLD, with a preference to accumulate on pullbacks.

Sheet DDM FCFF FCFE RelativeValuation
A1: Mastercard Inc — DDM,FCFF,FCFE,Relative Valuation Model (2026) | B1: Prepared by: [Talla Varun] | C1: All financial figures in USD Millions unless stated otherwise
A2: Dividend Discount Model (Reference Only) | B2: Amount | C2: 2020 | D2: 2021 | E2: 2022 | F2: 2023 | G2: 2024 | H2: 2025 | I2: 2026 | J2: 2027 | K2: 2028 | L2: 2029
A3: Dividend Per Share | C3: =K33/O22 -> 1.9175627 | D3: =K34/O22 -> 2.0800478 | E3: =K35/O22 -> 2.2735962 | F3: =K36/O22 -> 2.5782557 | G3: =K37/O22 -> 2.9247312 | H3: =K38/O22 -> 3.1003584 | I3: =K39/O22 -> 3.2867384 | J3: =K40/O22 -> 3.483871 | K3: =K41/O22 -> 3.692951 | L3: =K42/O22 -> 3.9139785
A4: Growth In Dividend | B4: =(D3/C3)-1 -> 0.084735202 | G4: =(G3/C3)^0.25-1 -> 0.11130711 | H4: =(G4-($G$4-$L$4)/5) -> 0.099045691 | I4: =(H4-($G$4-$L$4)/5) -> 0.086784268 | J4: =(I4-($G$4-$L$4)/5) -> 0.074522845 | K4: =(J4-($G$4-$L$4)/5) -> 0.062261423 | L4: 0.05
A5: Long Term Growth | B5: 0.035
A6: Long Term Ke | B6: =H47 -> 0.10212792 | D6: Note: Mastercard distributes capital primarily through share buybacks rather than dividends; therefore DDM significantly understates intrinsic value and is excluded from target price calculation.
A7: Terminal value (Do*(1+g)/(Ke-g)) | B7: =L3*(1+B5)/(B6-B5) -> 60.346984
A8: PV Of Terminal Value | B8: =B7/(1+$B$6)^5 -> 37.110392 | D8: DDM using dividends only is not reliable due to buyback-heavy capital return; adjusted DDM aligns closer to intrinsic value.
A9: PV Of Dividends | B9: =SUM(C3:L3) -> 29.252091
A10: Total PV Of Firm | B10: =B9+B8 -> 66.362483
A11: Intrinsic Value (DDM) | B11: =B10 -> 66.362483
A12: Traded price as on 31st March | B12: =B27 -> 450
A13: Diff | B13: =B11-B12 -> -383.63752
A14: Value of security | B14: =B11 -> 66.362483
A16: Legacy DDM Check | B16: Amount | C16: 2020 | D16: 2021 | E16: 2022 | F16: 2023 | G16: 2024 | H16: 2025 | I16: 2026 | J16: 2027 | K16: 2028 | L16: 2029 | N16: Column1 | O16: Column2
A17: DDM | C17: ='Cash Flow'!B25-('Cash Flow'!B32+'Cash Flow'!B33)+('Cash Flow'!B43-'Cash Flow'!B48) -> 11891 | D17: ='Cash Flow'!C25-('Cash Flow'!C32+'Cash Flow'!C33)+('Cash Flow'!C43-'Cash Flow'!C48) -> 12951 | E17: ='Cash Flow'!D25-('Cash Flow'!D32+'Cash Flow'!D33)+('Cash Flow'!D43-'Cash Flow'!D48) -> 14139 | F17: ='Cash Flow'!E25-('Cash Flow'!E32+'Cash Flow'!E33)+('Cash Flow'!E43-'Cash Flow'!E48) -> 14622 | G17: ='Cash Flow'!F25-('Cash Flow'!F32+'Cash Flow'!F33)+('Cash Flow'!F43-'Cash Flow'!F48) -> 21270 | H17: ='Cash Flow'!G25-('Cash Flow'!G32+'Cash Flow'!G33)+('Cash Flow'!G43-'Cash Flow'!G48) -> 20540.948 | I17: ='Cash Flow'!H25-('Cash Flow'!H32+'Cash Flow'!H33)+('Cash Flow'!H43-'Cash Flow'!H48) -> 21229.542 | J17: ='Cash Flow'!I25-('Cash Flow'!I32+'Cash Flow'!I33)+('Cash Flow'!I43-'Cash Flow'!I48) -> 23631.93 | ... L17: ='Cash Flow'!K25-('Cash Flow'!K32+'Cash Flow'!K33)+('Cash Flow'!K43-'Cash Flow'!K48) -> 28777.671 | N17: Required Return (Ke) | O17: 10.21
A18: Growth In DDM | C18: =(D17/C17)-1 -> 0.089143049 | G18: =C18 -> 0.089143049 | H18: =(G18-($G$18-$L$18)/5) -> 0.081314439 | I18: =(H18-($G$18-$L$18)/5) -> 0.07348583 | J18: =(I18-($G$18-$L$18)/5) -> 0.06565722 | K18: =(J18-($G$18-$L$18)/5) -> 0.05782861 | L18: 0.05 | N18: Long Term Growth (g) | O18: 3.5
A19: Long Term Growth Rate | B19: 0.035 | N19: Terminal Value | O19: 102.6279
A20: Long Term Ke(DDM) | B20: =H47 -> 0.10212792 | N20: PV of Terminal Value | O20: 43.3511
A21: Terminal value (DDM*(1+g)/(Ke-g)) | B21: =L17*(1+B19)/(B20-B19) -> 443703.43 | N21: Intrinsic Value Per Share (DCF) | O21: =B26 -> 433.21273
A22: PV Of Terminal Value | B22: =B21/(1+$B$20)^10 -> 167792.57 | N22: Outstanding Shares | O22: 837
A23: PV Of DDM | B23: =SUM(C17:L17) -> 195211.36
A24: Total PV Of Firm | B24: =B23+B22 -> 363003.92
A25: No OF Outstanding shares | B25: ='Profit Loss'!K24 -> 837.93458
A26: Intrinsic Value Per Share (DDM) | B26: =B24/B25 -> 433.21273
A27: Traded price as on 31st March | B27: 450
A28: Diff | B28: =B26-B27 -> -16.787272
A29: Value Of Security | B29: =B24/B25 -> 433.21273
A30: Previous Close | B30: -
A32: Relative Valuation | B32: Company | C32: Industry | D32: Implied | E32: Price | G32: Calculations | H32: Values | J32: Year | K32: Total Dividend | L32: Dividend Per Share (DPS) | M32: PV of DPS | N32: Implied Valuation:
A33: P/E | B33: =B27/Table18[[#This Row],[Values]] -> 32.332608 | C33: 30 | D33: =Table18[[#This Row],[Values]] -> 13.917838 | E33: =D33*C33 -> 417.53514 | G33: EPS | H33: ='Profit Loss'!F20/'Profit Loss'!F22 -> 13.917838 | J33: 2020 | K33: 1605 | L33: 1.9154 | M33: 1.7573 | N33: - EV/EBITDA Value: $XXX
A34: P/S | B34: =B27/H35 -> 14.777932 | C34: 14 | D34: =H35 -> 30.450811 | E34: =D34*C34 -> 426.31135 | G34: BVPS | H34: =Balance_Sheet!F40/'Profit Loss'!F22 -> 7.0432432 | J34: 2021 | K34: 1741 | L34: 2.0777 | M34: 1.7488 | N34: - P/E Value: $XXX
A35: EV/EBITA | B35: =H38 -> 25.853146 | C35: 24 | D35: =H39 -> 17.815135 | E35: =D35*C35 -> 427.56324 | G35: Sales Per Share | H35: ='Profit Loss'!F4/'Profit Loss'!F22 -> 30.450811 | J35: 2022 | K35: 1903 | L35: 2.2711 | M35: 1.7537
A36: EV/EBIT | B36: =H37 -> 27.34142 | C36: 26 | D36: =H40 -> 16.845405 | E36: =D36*C36 -> 437.98054 | G36: Enterprise Value | H36: =(B27*'Profit Loss'!F22)+'Common Size'!B93-Balance_Sheet!F4 -> 426034 | J36: 2023 | K36: 2158 | L36: 2.5754 | M36: 1.8245 | N36: [ NEW SECTION ]
D37: Target Price | E37: =AVERAGE(E33:E36) -> 427.34757 | G37: EV/EBIT | H37: =H36/'Profit Loss'!F11 -> 27.34142 | J37: 2024 | K37: 2448 | L37: 2.9215 | M37: 1.8988 | N37: Valuation Commentary:
G38: EV/EBITDA | H38: =H36/'Profit Loss'!F25 -> 25.853146 | J38: 2025 | K38: 2595 | L38: 3.0969 | M38: 1.8466 | N38: - Mastercard trades at a premium because:
A39: Residual Income Valuation (Sensitivity Check) | B39: Residual Valuation | C39: RELATIVE VALUATION | G39: EBITDA Per Share | H39: ='Profit Loss'!F25/'Profit Loss'!F22 -> 17.815135 | J39: 2026 | K39: 2751 | L39: 3.2831 | M39: 1.796 | N39: • High margins
A40: Networth | B40: =Balance_Sheet!F40 -> 6515 | G40: EBIT Per Share | H40: ='Profit Loss'!F11/'Profit Loss'!F22 -> 16.845405 | J40: 2027 | K40: 2916 | L40: 3.48 | M40: 1.7465 | N40: • Asset-light model
A41: g | B41: 0.04 | C41: [ NEW SECTION ] | G41: Cost of Equity Table | J41: 2028 | K41: 3091 | L41: 3.6889 | M41: 1.6985 | N41: • Network effects
A42: Ke | B42: =O17 -> 10.21 | C42: Multiple Selection Rationale: | G42: Input | H42: Value | J42: 2029 | K42: 3276 | L42: 3.9096 | M42: 1.6515
A43: Investor Expectation | B43: =B40*B42 -> 66518.15 | C43: - EV/EBITDA → capital structure neutral... | G43: Risk Free Rate | H43: 0.04
A44: NOPAT | B44: =H40*(1-D65) -> 14.150141 | C44: - P/E → equity perspective | G44: Beta | H44: {=Table23[Value]} -> 1.0354654
A45: PAT | B45: =B44*B50 -> 11856.892 | G45: Market Return | H45: 0.1
C46: ----------------------------------- | G46: Market Premium | H46: 0.06
A47: Residual Income | B47: =B45-B43 -> -54661.258 | C47: Peer Comparison Table | G47: Cost of Equity (Ke) (CAPM) | H47: =H43+(H44*H46) -> 0.10212792
A48: Terminal Value | B48: =B47/(B42-B41) -> -5374.755 | C48: ----------------------------------- | G48: sensitivity Table
A49: PV Of EVA | B49: =B48/(1+B42) -> -479.46075 | C49: Company | EV/EBITDA | P/E | ... | G49: g \ Ke | H49: 9% | I49: 10% | J49: 11%
A50: No of Outstanding Shares | B50: =B25 -> 837.93458 | C50: ----------------------------------- | G50: 0.12 | H50: 550 | I50: 500 | J50: 460
A51: Value OF Firm (EVA) | B51: =B52+B48 -> 1140.245 | G51: 0.14 | H51: 620 | I51: 615 | J51: 580
A52: Book Value | B52: =Balance_Sheet!F40 -> 6515 | G52: 0.16 | H52: 700 | I52: 690 | J52: 650
A53: Value Of Firm (Per Share) | B53: =B51/B50 -> 1.3607805 | G53: Note: Valuation is most sensitive to Cost of Equity assumptions; a 1% increase in discount rate reduces intrinsic value materially.
A54: Note: EVA undervalues asset-light fintech companies due to low invested capital base.
A55: Final Valuation Summary | E55: Valuation Weighting Table | H55: Added Investment Thesis Box | I55: Add Risk Factors
A56: Method | B56: Value | C56: Item | D56: Price Recommendation | E56: Method2 | F56: Role | G56: Weight | H56: Investment Thesis | I56: Risk Factors
A57: DDM | B57: =B14 -> 66.362483 | C57: Current Market Price | D57: 450 | E57: FCFE (Primary DCF) | F57: Core valuation | G57: 0.6 | H57: Strong payment network moat | I57: Regulation on interchange fees
A58: FCFF | B58: =B144 -> 394.4448 | C58: Target Price (12M) | D58: 350 | E58: Relative Valuation | F58: Market confirmation | G58: 0.4 | H58: High operating margins (~54%) | I58: Fintech competition
A59: Relative Valuation | B59: =E37 -> 427.34757 | C59: Recommendation | D59: SELL | E59: DDM | F59: Reference only | G59: 0 | H59: Stable long-term cash generation | I59: Global transaction slowdown
A60: FCFE | B60: =B99 -> 335.44643 | C60: Upside / Downside | D60: =(D58/D57)-1 -> -0.22222222 | E60: EVA | F60: Sensitivity Check | G60: 0
A61: Final Fair Value Range | B61: 315-370
A63: Year | B63: Revenue Growth | C63: EBIT Margin | D63: Tax Rate | E63: Dep % of Revenue | F63: Capex % of Revenue | G63: Working Capital % of Revenue | H63: FCFE Growth (if used) | J63: Year | K63: EBIT Growth | L63: Dep Growth | M63: Capex Growth | N63: WC Growth
A64: 2024 | B64: Actual | C64: Actual | D64: 0.156 | E64: Actual | F64: Actual | G64: Actual | H64: – | J64: 2025E | K64: 0.18 | L64: 0.08 | M64: 0.08 | N64: 0.1
A65: 2025E | B65: 0.18 | C65: 0.54 | D65: 0.16 | E65: 0.055 | F65: 0.07 | G65: 0.25 | H65: 0.18 | J65: 2026E | K65: 0.16 | L65: 0.08 | M65: 0.08 | N65: 0.1
A66: 2026E | B66: 0.12 | C66: 0.54 | D66: 0.16 | E66: 0.055 | F66: 0.07 | G66: 0.25 | H66: 0.16 | J66: 2027E | K66: 0.13 | L66: 0.08 | M66: 0.08 | N66: 0.1
A67: 2027E | B67: 0.13 | C67: 0.54 | D67: 0.16 | E67: 0.055 | F67: 0.07 | G67: 0.25 | H67: 0.13 | J67: 2028E | K67: 0.1 | L67: 0.08 | M67: 0.08 | N67: 0.1
A68: 2028E | B68: 0.1 | C68: 0.54 | D68: 0.16 | E68: 0.055 | F68: 0.07 | G68: 0.25 | H68: 0.1 | J68: 2029E | K68: 0.07 | L68: 0.08 | M68: 0.08 | N68: 0.1
A69: 2029E | B69: 0.07 | C69: 0.54 | D69: 0.16 | E69: 0.055 | F69: 0.07 | G69: 0.25 | H69: 0.07 | J69: Terminal | K69: 3.5 | L69: Stable | M69: Stable | N69: Stable
A70: Terminal | B70: 3.5 | C70: Stable | D70: 0.16 | E70: Stable | F70: Stable | G70: Stable | H70: 0.05
A71: FCFE DCF Assumptions
A72: Cell | B72: Item | C72: Value
A73: B2 | B73: Risk Free Rate | C73: ='DCF Valuation'!B4 -> 0.042
A74: B3 | B74: Market Return | C74: ='DCF Valuation'!B5 -> 0.1
A75: B4 | B75: Beta | C75: {=Table23[Value]} -> 1.0354654
A76: B5 | B76: Market Risk Premium | C76: ='DCF Valuation'!B15 -> 0.058
A77: B6 | B77: Cost of Equity | C77: ='DCF Valuation'!B9 -> 0.10205699
A78: B7 | B78: Terminal Growth Rate | C78: 0.03
A79: B8 | B79: Shares Outstanding | C79: =B50 -> 837.93458
A81: FCFE DCF (Equity Value) Calculation
A82: Year | B82: Net Income | C82: Depreciation | D82: Capex | E82: WC Change | F82: Net Borrowing | G82: FCFE
A83: 2025 | B83: ='Profit Loss'!G20 -> 14606.825 | C83: ='Cash Flow'!G7 -> 946.4112 | D83: =('Cash Flow'!G32-'Cash Flow'!G33) -> 258.3 | E83: ='Cash Flow'!G24 -> 716.36625 | F83: 0 | G83: =B83+C83-D83-E83+F83 -> 14578.57
A84: 2026 | B84: ='Profit Loss'!H20 -> 16827.111 | C84: ='Cash Flow'!H7 -> 1033.7965 | D84: =('Cash Flow'!H32-'Cash Flow'!H33) -> 271.215 | E84: ='Cash Flow'!H24 -> 716.36625 | F84: 0 | G84: =B84+C84-D84-E84+F84 -> 16873.326
A85: 2027 | B85: ='Profit Loss'!I20 -> 19033.651 | C85: ='Cash Flow'!I7 -> 1117.9261 | D85: =('Cash Flow'!I32-'Cash Flow'!I33) -> 284.77575 | E85: ='Cash Flow'!I24 -> 716.36625 | F85: 0 | G85: =B85+C85-D85-E85+F85 -> 19150.435
A86: 2028 | B86: ='Profit Loss'!J20 -> 21331.218 | C86: ='Cash Flow'!J7 -> 1196.5802 | D86: =('Cash Flow'!J32-'Cash Flow'!J33) -> 299.01454 | E86: ='Cash Flow'!J24 -> 716.36625 | F86: 0 | G86: =B86+C86-D86-E86+F86 -> 21512.417
A87: 2029 | B87: ='Profit Loss'!K20 -> 23685.455 | C87: ='Cash Flow'!K7 -> 1267.4887 | D87: =('Cash Flow'!K32-'Cash Flow'!K33) -> 313.96526 | E87: ='Cash Flow'!K24 -> 716.36625 | F87: 0 | G87: =B87+C87-D87-E87+F87 -> 23922.612
A89: Discounted FCFE
A90: Year | B90: FCFE | C90: Discount Factor | D90: Present Value of FCFE
A91: =A83 -> 2025 | B91: =G83 -> 14578.57 | C91: =1/(1+$C$77)^1 -> 0.90739409 | D91: =B91*C91 -> 13228.508
A92: =A84 -> 2026 | B92: =G84 -> 16873.326 | C92: =1/(1+$C$77)^2 -> 0.82336403 | D92: =B92*C92 -> 13892.89
A93: =A85 -> 2027 | B93: =G85 -> 19150.435 | C93: =1/(1+$C$77)^3 -> 0.74711565 | D93: =B93*C93 -> 14307.59
A94: =A86 -> 2028 | B94: =G86 -> 21512.417 | C94: =1/(1+$C$77)^4 -> 0.67792833 | D94: =B94*C94 -> 14583.877
A95: =A87 -> 2029 | B95: =G87 -> 23922.612 | C95: =1/(1+$C$77)^5 -> 0.61514816 | D95: =B95*C95 -> 14715.951
A96: Terminal Value | B96: =G87*(1+C78)/(C77-C78) -> 341955.58
A97: Discount Terminal Value | B97: =B96*C95 -> 210353.34
A98: Total Equity Value | B98: =SUM(D91:D95)+B97 -> 281082.16
A99: Intrinsic Share Price | B99: =B98/C79 -> 335.44643
A100: Current Market Value | B100: 450
A101: Investment Recommendation | B101: =IF(B99>B100,"BUY",IF(B99=B100,"HOLD","SELL")) -> SELL
A103: Recommendation Box | B103: Values
A104: Recommendation | B104: =B101 -> SELL
A105: Target Price | B105: =B99 -> 335.44643
A106: Current Price | B106: =B100 -> 450
...

Sheet Valuation Dashboard
A1: Equity Research Dashboard – Mastercard Inc | K1: Investment Call Header
A2: Company Overview | D2: SELL Recommendation | H2: Valuation Comparison Bar Chart | K2: Recommendation: SELL
A3: Item | B3: Value | D3: Metric | E3: Formula | H3: Metric | I3: Price | K3: Downside Potential: -14.20%
A4: Company | B4: Mastercard Inc | D4: Target Price | E4: ='DCF Valuation'!B35 -> 386.11179 | H4: Market Price | I4: 450 | K4: Risk Level: Moderate
A5: Industry | B5: Payment Technology | D5: Market Price | E5: ='DCF Valuation'!B36 -> 450 | H5: Intrinsic Price | I5: =B20 -> 386.11179 | K5: Investment Horizon: Long Term
A6: Model Type | B6: DCF Valuation | D6: Upside | E6: ='DCF Valuation'!B37 -> -0.14197379
A7: Analyst | B7: Varun | D7: Recommendation | E7: ='DCF Valuation'!B38 -> SELL | K7: Company | L7: P/E | M7: EV/EBITDA
A8: Date | B8: =TODAY() -> 46123 | K8: Visa Inc. | L8: ~30 | M8: ~22
K9: Mastercard Incorporated | L9: ~32 | M9: ~26
A10: KPI Cards | D10: Valuation Summary | K10: American Express | L10: ~19 | M10: ~14
A11: KPI | B11: Source | D11: Metric | E11: Link
A12: Revenue CAGR | B12: =('DCF Valuation'!F17/'DCF Valuation'!B17)^(1/4)-1 -> 0.11494394 | D12: Enterprise Value | E12: ='DCF Valuation'!B28 -> 355455.31
A13: EBIT Margin | B13: 0.55 | D13: Equity Value | E13: ='DCF Valuation'!B29 -> 350767.12
A14: FCFF Growth | B14: =('DCF Valuation'!F23/'DCF Valuation'!B23)^(1/4)-1 -> 0.093500391 | D14: DCF Fair Value | E14: ='DCF Valuation'!B35 -> 386.11179
A15: WACC | B15: ='DCF Valuation'!B13 -> 0.094791294 | D15: Net Debt | E15: ='DCF Valuation'!B31 -> 4688.1872
A16: Terminal Growth | B16: ='DCF Valuation'!B8 -> 0.03
D17: Prepared by:
A18: INVESTMENT CALL | D18: Talla Varun Goud
A19: Recommendation | B19: =E7 -> SELL | D19: PGDM – Finance & Business Analytics
A20: Target Price | B20: =E4 -> 386.11179 | D20: Equity Research Project | 2026
A21: Upside/Downside | B21: =E6 -> -0.14197379
A22: Confidence Level: Medium–High (based on stable cash flow visibility and sensitivity-tested assumptions)
A23: Revenue Forecast Line Chart | B23: ='DCF Valuation'!B16 -> 2025E | C23: ='DCF Valuation'!C16 -> 2026E | D23: ='DCF Valuation'!D16 -> 2027E | E23: ='DCF Valuation'!E16 -> 2028E | F23: ='DCF Valuation'!F16 -> 2029E | H23: Enterprise Water Fall Chart
A24: Revenue | B24: ='DCF Valuation'!B17 -> 31547.04 | C24: ='DCF Valuation'!C17 -> 35648.155 | D24: ='DCF Valuation'!D17 -> 39925.934 | E24: ='DCF Valuation'!E17 -> 44317.787 | F24: ='DCF Valuation'!F17 -> 48749.565 | H24: Step | I24: Value
H25: Enterprise Value | I25: =E12 -> 355455.31
H26: Net Debt | I26: =E15 -> 4688.1872
H27: Equity Value | I27: =E13 -> 350767.12
A40: Free Cash Flow Clustered Column Chart | B40: ='DCF Valuation'!B16 -> 2025E | C40: ='DCF Valuation'!C16 -> 2026E | D40: ='DCF Valuation'!D16 -> 2027E | E40: ='DCF Valuation'!E16 -> 2028E | F40: ='DCF Valuation'!F16 -> 2029E
A41: ='DCF Valuation'!A23 -> Free Cash Flow to Firm | B41: ='DCF Valuation'!B23 -> 18784.948 | C41: ='DCF Valuation'!C23 -> 19435.742 | D41: ='DCF Valuation'!D23 -> 21798.44 | E41: ='DCF Valuation'!E23 -> 24283.1 | F41: ='DCF Valuation'!F23 -> 26858.749
A61: Food Ball Field Valuation Method | B61: Low | C61: High | D61: Range | E61: Key Risks
A62: DCF | B62: 350 | C62: 420 | D62: =C62-B62 -> 70 | E62: Faster digital payments adoption
A63: P/E Multiple | B63: 320 | C63: 420 | D63: =C63-B63 -> 100 | E63: Cross-border transaction recovery
A64: EV/EBITDA | B64: 300 | C64: 410 | D64: =C64-B64 -> 110 | E64: Margin expansion potential
A65: Analyst Consensus | B65: 350 | C65: 480 | D65: =C65-B65 -> 130 | E65: Interest rate sensitivity
A66: Current Market Price | B66: 450 | C66: 450 | D66: =C66-B66 -> 0
A67: Current Market Price ($450) | B67: Disclaimer:This report is prepared for academic purposes only and does not constitute investment advice.
A90: 🧠 Investment Thesis
A91: ✅ 1. Strong Global Payment Network
A92: Mastercard Inc operates one of the world’s largest electronic payment networks, benefiting from increasing global adoption of cashless transactions and digital payments.
A94: ✅ 2. High-Margin Asset-Light Business Model
A95: The company does not issue credit or take lending risk, allowing it to maintain exceptionally high operating margins and strong free cash flow generation.
A97: ✅ 3. Cross-Border Payments Drive Growth
A98: International travel recovery and rising cross-border transactions remain key revenue drivers, supporting long-term earnings expansion.
A100: ✅ 4. Competitive Positioning vs Peers
A101: Compared with Visa Inc. and American Express, Mastercard demonstrates strong innovation capability through fintech partnerships, cybersecurity services, and digital payment solutions.
A103: ⚠️ 5. Valuation Concern (Reason for SELL Recommendation)
A104: Despite strong fundamentals, current market price trades significantly above intrinsic value estimated through DCF analysis, implying limited upside and potential valuation correction risk.
A106: ⭐ One-Line Analyst Conclusion
... A111: Fundamentally strong business… but valuation stretched relative to intrinsic value

Sheet Competition
A1: Comparable Company Analysis (Comps) | B1: Last Price | C1: Market Cap ($ mn) | D1: Sales ($ mn) | E1: Net Profit ($ mn) | F1: Total Assets ($ mn) | G1: P/E | H1: P/S | I1: EV/Sales | J1: EV/EBITDA | K1: Net Profit Margin | L1: ROA | M1: ROE | N1: EBITDA | O1: EV | R1: Key Multiples Comparison
A2: Mastercard | B2: 548 | C2: 510000 | D2: 28167 | E2: 12874 | F2: 48081 | G2: =Table28[[#This Row],[Market Cap ($ mn)]]/Table28[[#This Row],[Net Profit ($ mn)]] -> 39.614727 | H2: =Table28[[#This Row],[Market Cap ($ mn)]]/Table28[[#This Row],[Sales ($ mn)]] -> 18.106295 | I2: =Table28[[#This Row],[EV]]/Table28[[#This Row],[Sales ($ mn)]] -> 18.109987 | J2: =Table28[[#This Row],[Market Cap ($ mn)]]/(Table28[[#This Row],[Net Profit ($ mn)]]*1.25) -> 31.691782 | K2: =Table28[[#This Row],[Net Profit ($ mn)]]/Table28[[#This Row],[Sales ($ mn)]] -> 0.45705968 | L2: =Table28[[#This Row],[Net Profit ($ mn)]]/Table28[[#This Row],[Total Assets ($ mn)]] -> 0.26775649 | M2: =Table28[[#This Row],[Net Profit ($ mn)]]/(Table28[[#This Row],[Total Assets ($ mn)]])*0.5 -> 0.13387825 | N2: 16096 | O2: 510104 | R2: P/E | S2: EV/EBITDA
A3: Visa | B3: 331 | C3: 690000 | D3: 40000 | E3: 20058 | F3: 99627 | G3: =Table28[[#This Row],[Market Cap ($ mn)]]/Table28[[#This Row],[Net Profit ($ mn)]] -> 34.400239 | H3: =Table28[[#This Row],[Market Cap ($ mn)]]/Table28[[#This Row],[Sales ($ mn)]] -> 17.25 | I3: =Table28[[#This Row],[EV]]/Table28[[#This Row],[Sales ($ mn)]] -> 17.25 | J3: =Table28[[#This Row],[Market Cap ($ mn)]]/(Table28[[#This Row],[Net Profit ($ mn)]]*1.25) -> 27.520191 | K3: =Table28[[#This Row],[Net Profit ($ mn)]]/Table28[[#This Row],[Sales ($ mn)]] -> 0.50145 | L3: =Table28[[#This Row],[Net Profit ($ mn)]]/Table28[[#This Row],[Total Assets ($ mn)]] -> 0.20133096 | M3: =Table28[[#This Row],[Net Profit ($ mn)]]/(Table28[[#This Row],[Total Assets ($ mn)]])*0.5 -> 0.10066548 | N3: 25073 | O3: 690000 | R3: =G2 -> 39.614727 | S3: =J2 -> 31.691782
A4: American Express | B4: 359.15 | C4: 255000 | D4: 72229 | E4: 10833 | F4: 271461 | G4: =Table28[[#This Row],[Market Cap ($ mn)]]/Table28[[#This Row],[Net Profit ($ mn)]] -> 23.539186 | H4: =Table28[[#This Row],[Market Cap ($ mn)]]/Table28[[#This Row],[Sales ($ mn)]] -> 3.5304379 | I4: =Table28[[#This Row],[EV]]/Table28[[#This Row],[Sales ($ mn)]] -> 3.5299949 | J4: =Table28[[#This Row],[Market Cap ($ mn)]]/(Table28[[#This Row],[Net Profit ($ mn)]]*1.25) -> 18.831349 | K4: =Table28[[#This Row],[Net Profit ($ mn)]]/Table28[[#This Row],[Sales ($ mn)]] -> 0.14998131 | L4: =Table28[[#This Row],[Net Profit ($ mn)]]/Table28[[#This Row],[Total Assets ($ mn)]] -> 0.039906285 | M4: =Table28[[#This Row],[Net Profit ($ mn)]]/(Table28[[#This Row],[Total Assets ($ mn)]])*0.5 -> 0.019953142 | N4: 13541 | O4: 254968 | R4: =G3 -> 34.400239 | S4: =J3 -> 27.520191
A5: PayPal | B5: 40.42 | C5: 42000 | D5: 33172 | E5: 5233 | F5: 80173 | G5: =Table28[[#This Row],[Market Cap ($ mn)]]/Table28[[#This Row],[Net Profit ($ mn)]] -> 8.0259889 | H5: =Table28[[#This Row],[Market Cap ($ mn)]]/Table28[[#This Row],[Sales ($ mn)]] -> 1.2661281 | I5: =Table28[[#This Row],[EV]]/Table28[[#This Row],[Sales ($ mn)]] -> 1.2699867 | J5: =Table28[[#This Row],[Market Cap ($ mn)]]/(Table28[[#This Row],[Net Profit ($ mn)]]*1.25) -> 6.4207911 | K5: =Table28[[#This Row],[Net Profit ($ mn)]]/Table28[[#This Row],[Sales ($ mn)]] -> 0.15775353 | L5: =Table28[[#This Row],[Net Profit ($ mn)]]/Table28[[#This Row],[Total Assets ($ mn)]] -> 0.065271351 | M5: =Table28[[#This Row],[Net Profit ($ mn)]]/(Table28[[#This Row],[Total Assets ($ mn)]])*0.5 -> 0.032635675 | N5: 6561 | O5: 42128 | R5: =G4 -> 23.539186 | S5: =J4 -> 18.831349
A6: Block inc | B6: 49.8 | C6: 29800 | D6: 24121 | E6: 2897 | F6: 36777 | G6: =Table28[[#This Row],[Market Cap ($ mn)]]/Table28[[#This Row],[Net Profit ($ mn)]] -> 10.286503 | H6: =Table28[[#This Row],[Market Cap ($ mn)]]/Table28[[#This Row],[Sales ($ mn)]] -> 1.235438 | I6: =Table28[[#This Row],[EV]]/Table28[[#This Row],[Sales ($ mn)]] -> 1.2399983 | J6: =Table28[[#This Row],[Market Cap ($ mn)]]/(Table28[[#This Row],[Net Profit ($ mn)]]*1.25) -> 8.2292026 | K6: =Table28[[#This Row],[Net Profit ($ mn)]]/Table28[[#This Row],[Sales ($ mn)]] -> 0.12010281 | L6: =Table28[[#This Row],[Net Profit ($ mn)]]/Table28[[#This Row],[Total Assets ($ mn)]] -> 0.078772059 | M6: =Table28[[#This Row],[Net Profit ($ mn)]]/(Table28[[#This Row],[Total Assets ($ mn)]])*0.5 -> 0.039386029 | N6: 3634 | O6: 29910 | R6: =G5 -> 8.0259889 | S6: =J5 -> 6.4207911
A7: Global Payments | B7: 120 | C7: 31000 | D7: 9700 | E7: 1200 | F7: 52000 | G7: =Table28[[#This Row],[Market Cap ($ mn)]]/Table28[[#This Row],[Net Profit ($ mn)]] -> 25.833333 | H7: =Table28[[#This Row],[Market Cap ($ mn)]]/Table28[[#This Row],[Sales ($ mn)]] -> 3.1958763 | I7: =Table28[[#This Row],[EV]]/Table28[[#This Row],[Sales ($ mn)]] -> 3.2 | J7: =Table28[[#This Row],[Market Cap ($ mn)]]/(Table28[[#This Row],[Net Profit ($ mn)]]*1.25) -> 20.666667 | K7: =Table28[[#This Row],[Net Profit ($ mn)]]/Table28[[#This Row],[Sales ($ mn)]] -> 0.12371134 | L7: =Table28[[#This Row],[Net Profit ($ mn)]]/Table28[[#This Row],[Total Assets ($ mn)]] -> 0.023076923 | M7: =Table28[[#This Row],[Net Profit ($ mn)]]/(Table28[[#This Row],[Total Assets ($ mn)]])*0.5 -> 0.011538462 | N7: 1501 | O7: 31040 | R7: =G6 -> 10.286503 | S7: =J6 -> 8.2292026
C8: =SUM(Table28[Market Cap ($ mn)]) -> 1557800 | E8: =SUBTOTAL(109,Table28[Net Profit ($ mn)]) -> 53095 | F8: Industry Averages | G8: =AVERAGE(G3:G7) -> 20.41705 | H8: =AVERAGE(H3:H7) -> 5.2955761 | I8: =AVERAGE(Table28[EV/Sales]) -> 7.4333278 | J8: =AVERAGE(J3:J7) -> 16.33364 | K8: =AVERAGE(K3:K7) -> 0.2105998 | L8: =AVERAGE(L3:L7) -> 0.081671516 | M8: =(M3+M4+M5+M6+M7)/5 -> 0.040835758 | N8: =AVERAGE(N3:N7) -> 10062 | O8: =AVERAGE(O3:O7) -> 209609.2 | R8: =G7 -> 25.833333 | S8: =J7 -> 20.666667
F9: Industry Median | G9: =MEDIAN(Table28[P/E]) -> 24.68626 | H9: =MEDIAN(Table28[P/S]) -> 3.3631571 | I9: =MEDIAN(Table28[EV/Sales]) -> 3.3649974 | J9: =MEDIAN(Table28[EV/EBITDA]) -> 19.749008 | K9: =MEDIAN(Table28[Net Profit Margin]) -> 0.15386742 | L9: =MEDIAN(Table28[ROA]) -> 0.072021705 | M9: =MEDIAN(Table28[ROE]) -> 0.036010852 | N9: =MEDIAN(Table28[[#Headers],[#Data],[EBITDA]]) -> 10051 | O9: =MEDIAN(Table28[EV]) -> 148548 | R9: =Table28[[#Totals],[P/E]] -> 20.41705 | S9: =Table28[[#Totals],[EV/EBITDA]] -> 16.33364
A10: Valuation Conclusion | E10: Company | F10: Revenue Growth | R10: =G9 -> 24.68626 | S10: =J9 -> 19.749008
A11: Mastercard trades at premium multiples due to: | E11: Mastercard | F11: ~12%
A12: • Strong network effect | E12: Visa | F12: ~10%
A13: • High margins | E13: PayPal | F13: ~7%
A14: • Asset-light model
A15: • Stable cash flows | E15: Company | F15: Operating Margin
A16: Industry Players Considered | E16: Visa | F16: ~65%
A17: Main global competitors: | E17: Mastercard | F17: ~58%
A18: Mastercard Inc | E18: PayPal | F18: ~18%
A19: Visa Inc.
A20: American Express | E20: Network | F20: Global share
A21: PayPal Holdings | E21: Visa | F21: ~50%
A22: These companies dominate global digital payment infrastructure. | E22: Mastercard | F22: ~25%
E23: American Express | F23: ~8%
A24: 1. Market Leadership Position
A25: Company | B25: Market Position | C25: Business Model | D25: Competitive Advantage | F25: Valuation Conclusion | L25: Why Premium is Justified: | N25: Why Premium is Risky:
A26: Visa | B26: 🥇 Market Leader | C26: Open payment network | D26: Largest transaction volume worldwide | F26: Valuation Metric | G26: Industry | H26: Mastercard | J26: Company | K26: Operating Margin | L26: Strong network effects | N26: Limited upside at current valuation
A27: Mastercard | B27: 🥈 Strong Challenger | C27: Open network | D27: Faster innovation & partnerships | F27: P/E | G27: 23.62 | H27: 39.61 | J27: Visa | K27: ~65% | L27: High margins (55%+) | N27: Regulatory pressure on fees
A28: American Express | B28: 🏆 Premium Niche | C28: Closed-loop system | D28: High-income customer base | F28: EV/EBITDA | G28: 18.89 | H28: 31.69 | J28: Mastercard | K28: ~58% | L28: Asset-light scalable model | N28: Fintech competition (PayPal, Block)
A29: PayPal | B29: 🚀 Digital Growth Player | C29: Wallet ecosystem | D29: Strong online payments | F29: P/S | G29: 7.43 | H29: 18.11 | J29: PayPal | K29: ~18% | L29: Global duopoly with Visa | N29: Growth normalization
F30: Conclusion | G30: Why Premium is Justified:
A31: Insight | F31: Mastercard trades at a significant premium to industry peers. | J31: Metric | K31: Average | L31: Median
A32: 👉 Visa leads by scale, | F32: Reason: | G32: Strong network effects | J32: P/E | K32: 28x | L32: 27x
A33: 👉 Mastercard competes through technology & global expansion, | F33: Industry-leading margins (~55%) | J33: EV/EBITDA | K33: 18x | L33: 17x
A34: 👉 AmEx focuses on premium profitability, | F34: Strong brand | G34: High margins (55%+)
A35: 👉 PayPal dominates digital wallet ecosystem. | F35: Global payment network dominance
G36: Asset-light scalable model
A37: 2. Growth Comparison (Revenue Expansion)
A38: Company | B38: Growth Profile | C38: Reason | F38: PREMIUM / DISCOUNT % | G38: Global duopoly with Visa
A39: Mastercard | B39: ⭐ High Growth | C39: Cross-border payments recovery + fintech partnerships | F39: Metric | G39: Mastercard | H39: Industry | I39: Premium
A40: Visa | B40: Stable Growth | C40: Mature market dominance | F40: P/E | G40: 39.61 | H40: 23.62 | I40: 0.68
A41: PayPal | B41: Volatile Growth | C41: E-commerce dependence | F41: EV/EBITDA | G41: 31.69 | H41: 18.89 | I41: 0.68
A42: American Express | B42: Moderate Growth | C42: Premium customer concentration | F42: P/S | G42: 18.11 | H42: 7.43 | I42: 1.44
F43: Mastercard trades at ~60–140% premium to industry multiples
A44: Analyst Insight
A45: ✅ Mastercard shows stronger international growth momentum compared to Visa.
A47: 3. Margin Comparison (Profitability Power) | E47: High-quality compounder trading at premium valuation with limited near-term upside.
A48: Company | B48: Margin Strength | C48: Explanation | E48: Visa & Mastercard operate a global duopoly with high barriers to entry due to network effects and regulatory infrastructure
A49: Mastercard | B49: 🔥 Very High | C49: Asset-light network model | E49: Relative premium aligns with strong ROE, margins, and cash flow assumptions used in DCF valuation.
A50: Visa | B50: 🔥 Extremely High | C50: Scale advantage | E50: Compared to peers, Mastercard combines Visa-like margins with higher growth exposure, justifying premium positioning
A51: American Express | B51: Medium-High | C51: Credit risk exposure | E51: Mastercard trades at a 60–140% premium to peers, driven by superior margins, network effects, and scalable economics, but current valuation limits near-term upside
A52: PayPal | B52: Lower | C52: Heavy operating expenses | E52: Visa remains the scale leader, while Mastercard differentiates through growth and partnerships, positioning it as the strongest challenger
A54: Key Insight
A55: 👉 Mastercard & Visa operate near-monopoly network economics
A56: 👉 High operating leverage → Exceptional margins.
A58: 4. Strategic Positioning Matrix
A59: Market Leader:
A60: Visa → Scale Dominance
A62: Innovation Challenger:
A63: Mastercard → Partnerships + Technology
A65: Premium Specialist:
A66: American Express → High-value customers
A68: Digital Disruptor:
A69: PayPal → Online wallet ecosystem
... A74: Mastercard’s P/E (~39x) vs industry (~24x) implies ~68% premium

Sheet Credit Ratio
A1: Credit Ratios of Mastercard Inc | C1: Credit Rating Model based on 5-Year Average Financial Metrics
A2: Rating Grid | B2: Take Average of Five Years for the GRID Rating | J2: Ratio | K2: Weight | M2: KPI Dashboard Box
J3: Debt/EBITDA | K3: 0.25 | M3: Revenue CAGR → 16%
A4: Credit Rating | B4: AAA | C4: AA | F4: A | G4: BBB | J4: Interest Coverage | K4: 0.25 | M4: EBITDA Margin → 55%
A5: Operating Margin | B5: 0.245 | C5: 0.165 | F5: 0.1 | G5: 0.075 | J5: FCF/Debt | K5: 0.2 | M5: ROE → 34%
A6: Debt / EBITDA | B6: 1.3 X | C6: 1.8 X | F6: 2.2 X | G6: 2.5 X | J6: Margin | K6: 0.15 | M6: Target vs Price → -18%
A7: EBITDA / Interest | B7: 25.0x | C7: 20.0 x | F7: 17.5 x | G7: 15.0 x | J7: Debt/Capital | K7: 0.15
A8: FCF / Debt | B8: 0.3 | C8: 0.24 | F8: 0.2 | G8: 0.17
A9: Debt / Capital | B9: 0.25 | C9: 0.3 | F9: 0.35 | G9: 0.4
A11: Particulars | B11: 2020 | C11: 2021 | D11: 2022 | E11: 2023 | F11: 2024 | G11: AVERAGE | H11: RATING | J11: Metric | K11: Rating | L11: Score | M11: Weight | N11: Weighted Score
A12: EBITDA | B12: ='Profit Loss'!B25 -> 8661 | C12: ='Profit Loss'!C25 -> 10808 | D12: ='Profit Loss'!D25 -> 13014 | E12: ='Profit Loss'!E25 -> 14807 | F12: ='Profit Loss'!F25 -> 16479 | G12: =AVERAGE(B12:F12) -> 12753.8 | J12: Debt/EBITDA | K12: AAA | L12: 4 | M12: 0.25 | N12: 1
A13: FCF after Dividends | B13: ='Common Size'!B89-'Common Size'!B56 -> 3019.119 | C13: ='Common Size'!C89-'Common Size'!C56 -> 766.36002 | D13: ='Common Size'!D89-'Common Size'!D56 -> 2940.4466 | E13: ='Common Size'!E89-'Common Size'!E56 -> 1966.9461 | F13: ='Common Size'!F89-'Common Size'!F56 -> 4255.2571 | G13: =AVERAGE(B13:F13) -> 2589.6257 | J13: Interest Coverage | K13: AA | L13: 3 | M13: 0.25 | N13: 0.75
A14: Operating Margin | B14: ='Common Size'!B10 -> 0.52813542 | C14: ='Common Size'!C10 -> 0.53389112 | D14: ='Common Size'!D10 -> 0.55151324 | E14: ='Common Size'!E10 -> 0.55813212 | F14: ='Common Size'!F10 -> 0.55320055 | G14: =AVERAGE(B14:F14) -> 0.54497449 | H14: AAA | J14: FCF/Debt | K14: AAA | L14: 4 | M14: 0.2 | N14: 0.8
A15: Debt / EBITDA | B15: ='Common Size'!B44/'Common Size'!B74 -> 1.4631105 | C15: ='Common Size'!C44/'Common Size'!C74 -> 1.2861769 | D15: ='Common Size'!D44/'Common Size'!D74 -> 1.0775319 | E15: ='Common Size'!E44/'Common Size'!E74 -> 1.0590261 | F15: ='Common Size'!F44/'Common Size'!F74 -> 1.169683 | G15: =AVERAGE(B15:F15) -> 1.2111057 | H15: AAA | J15: Margin | K15: AAA | L15: 4 | M15: 0.15 | N15: 0.6
A16: EBITDA / Interest | B16: =Table10[[#This Row],[2020]]/-'Common Size'!B12 -> 16.871053 | C16: =Table10[[#This Row],[2020]]/-'Common Size'!C12 -> 18.357887 | D16: =Table10[[#This Row],[2020]]/-'Common Size'!D12 -> 19.781592 | E16: =Table10[[#This Row],[2020]]/-'Common Size'!E12 -> 18.288464 | F16: =Table10[[#This Row],[2020]]/-'Common Size'!F12 -> 18.268969 | G16: =AVERAGE(B16:F16) -> 18.313593 | H16: AA | J16: Debt/Capital | K16: BB | L16: 1 | M16: 0.15 | N16: 0.15
A17: FCF / DEBT | B17: ='Common Size'!B87/'Common Size'!B44 -> 0.74592566 | C17: ='Common Size'!C87/'Common Size'!C44 -> 0.86916448 | D17: ='Common Size'!D87/'Common Size'!D44 -> 1.0598366 | E17: ='Common Size'!E87/'Common Size'!E44 -> 1.0816086 | F17: ='Common Size'!F87/'Common Size'!F44 -> 1.1755088 | G17: =AVERAGE(B17:F17) -> 0.98640882 | H17: AAA | N17: 3.3
A18: DEBT / Capital | B18: ='Common Size'!B44/('Common Size'!B44+Balance_Sheet!F40) -> 0.66044718 | C18: ='Common Size'!C44/('Common Size'!C44+Balance_Sheet!G40) -> 0.57950232 | D18: ='Common Size'!D44/('Common Size'!D44+Balance_Sheet!H40) -> 0.53258416 | E18: ='Common Size'!E44/('Common Size'!E44+Balance_Sheet!I40) -> 0.5193304 | F18: ='Common Size'!F44/('Common Size'!F44+Balance_Sheet!J40) -> 0.5201897 | G18: =AVERAGE(B18:F18) -> 0.56241075 | H18: BB
A19: Debt / EBITDA | B19: ='Common Size'!B44/'Profit Loss'!F25 -> 0.7689787 | C19: ='Common Size'!C44/'Profit Loss'!G25 -> 0.75973028 | D19: ='Common Size'!D44/'Profit Loss'!H25 -> 0.66786484 | E19: ='Common Size'!E44/'Profit Loss'!I25 -> 0.66231407 | F19: ='Common Size'!F44/'Profit Loss'!J25 -> 0.6888727 | G19: =AVERAGE(B19:F19) -> 0.70955212 | H19: AAA
A20: Final Credit Rating | B20: AA
A21: Outlook | B21: Stable
A23: Strong cash flows and high interest coverage support a high-grade credit profile, with moderate leverage slightly constraining a AAA rating.
A25: Key Insights:
A26: Superior margins vs industry → strong moat
A27: ROE expansion driven by profitability + leverage
A28: Multiple compression indicates normalization from premium levels, limiting near-term upside.
A30: Investment view driven primarily by valuation disconnect rather than business weakness
A32: Valuation is most sensitive to WACC and terminal growth assumptions.
A34: All projections based on management guidance, industry trends, and historical performance.
A36: All figures in USD millions unless stated otherwise.
A38: Mastercard is a high-quality, asset-light compounder with strong margins and network effects, but current valuation limits upside, leading to a SELL recommendation.
A40: Key downside risks include regulatory pressure on fees, fintech competition, and global transaction slowdown
A42: Attractive re-entry zone: $300–$320 (based on margin of safety)
... A50: Overall, while Mastercard remains a fundamentally strong business with durable competitive advantages, the current market price reflects long-term optimism. As a result, the risk-reward profile is unfavorable at current levels, supporting a HOLD/SELL recommendation with a preference to accumulate on pullbacks near the $300–$320 range.

Sheet Ratios
A1: Fundamental & Financial Ratio Analysis — Mastercard Inc | C1: “Five-Year Fundamental Trend Analysis”
A2: Column1 | B2: Column2 | C2: Column3 | D2: Column4 | E2: Column5 | F2: Column6 | G2: Column7 | H2: Column8 | I2: Column9 | J2: Column10 | K2: Column11 | L2: Column12 | M2: Column13 | N2: Column14 | O2: Key Fundamental Conclusion
A3: Year End | B3: Computation Formula | C3: Company | I3: Industry | O3: Superior profitability vs industry
A4: Operational & Financial Ratios | C4: 2020 | D4: 2021 | E4: 2022 | F4: 2023 | G4: 2024 | I4: =C4 -> 2020 | J4: 2021 | K4: 2022 | L4: 2023 | M4: 2024 | N4: Analyst Interpretation | O4: Strong cash generation
A5: Earnings Per Share (Rs) | B5: PAT/Number of Shares | C5: ='Profit Loss'!B20/'Profit Loss'!B24 -> 6.3727634 | D5: ='Profit Loss'!C20/'Profit Loss'!C24 -> 8.7570565 | E5: ='Profit Loss'!D20/'Profit Loss'!D24 -> 10.226571 | F5: ='Profit Loss'!E20/'Profit Loss'!E24 -> 11.834038 | G5: ='Profit Loss'!F20/'Profit Loss'!F24 -> 13.88781 | I5: N/A | J5: N/A | K5: N/A | L5: N/A | M5: N/A | N5: Consistent EPS growth indicates strong earnings expansion and shareholder value creation. | O5: High valuation premium justified by margins
A6: DPS(Rs) | B6: Dividend/Number of Shares | C6: =-'Cash Flow'!B42/'Profit Loss'!B24 -> 1.5954274 | D6: =-'Cash Flow'!C42/'Profit Loss'!C24 -> 1.7550403 | E6: =-'Cash Flow'!D42/'Profit Loss'!D24 -> 1.9598352 | F6: =-'Cash Flow'!E42/'Profit Loss'!E24 -> 2.2811839 | G6: =-'Cash Flow'!F42/'Profit Loss'!F24 -> 2.6407767 | I6: N/A | J6: N/A | K6: N/A | L6: N/A | M6: N/A | N6: Rising dividends reflect stable cash flows and shareholder-friendly capital allocation. | O6: Growth normalizing
A7: Book Value Per share | B7: Share holders Equity/Number of Shares | C7: =Balance_Sheet!B40/'Profit Loss'!B24 -> 6.4493042 | D7: =Balance_Sheet!C40/'Profit Loss'!C24 -> 7.4425403 | E7: =Balance_Sheet!D40/'Profit Loss'!D24 -> 6.545829 | F7: =Balance_Sheet!E40/'Profit Loss'!E24 -> 7.3731501 | G7: =Balance_Sheet!F40/'Profit Loss'!F24 -> 7.0280475 | I7: N/A | J7: N/A | K7: N/A | L7: N/A | M7: N/A | N7: Stable equity base supports long-term financial strength despite growth investments. | O7: Quality compounder stock
A8: Effective Tax Rate(%) | B8: Tax/PBT | C8: ='Profit Loss'!B19/'Profit Loss'!B18 -> 0.17384021 | D8: ='Profit Loss'!C19/'Profit Loss'!C18 -> 0.15717474 | E8: ='Profit Loss'!D19/'Profit Loss'!D18 -> 0.153597 | F8: ='Profit Loss'!E19/'Profit Loss'!E18 -> 0.17919202 | G8: ='Profit Loss'!F19/'Profit Loss'!F18 -> 0.15602465 | I8: ='Ind_P&L'!B18/'Ind_P&L'!B17 -> 0.19906115 | J8: ='Ind_P&L'!C18/'Ind_P&L'!C17 -> 0.16790047 | K8: ='Ind_P&L'!D18/'Ind_P&L'!D17 -> 0.14879166 | L8: ='Ind_P&L'!E18/'Ind_P&L'!E17 -> 0.16732874 | M8: ='Ind_P&L'!F18/'Ind_P&L'!F17 -> 0.14753438 | N8: Tax rate remains stable and aligned with industry averages. | O8: This makes report executive-ready.
A9: Dividend Pay Out Ratio(%) | B9: DPS/EPS | C9: ='DDM FCFF FCFE RelativeValuation'!C3/'Profit Loss'!B23 -> 0.30103025 | D9: ='DDM FCFF FCFE RelativeValuation'!D3/'Profit Loss'!C23 -> 0.23744838 | E9: ='DDM FCFF FCFE RelativeValuation'!E3/'Profit Loss'!D23 -> 0.22246538 | F9: ='DDM FCFF FCFE RelativeValuation'!F3/'Profit Loss'!E23 -> 0.21794215 | G9: ='DDM FCFF FCFE RelativeValuation'!G3/'Profit Loss'!F23 -> 0.2105638 | I9: N/A | J9: N/A | K9: N/A | L9: N/A | M9: N/A | N9: Moderate payout indicates balanced strategy between dividends and reinvestment.
A10: Retention Ratio | B10: 1-Dividend Payout Ratio | C10: =1-C9 -> 0.69896975 | D10: =1-D9 -> 0.76255162 | E10: =1-E9 -> 0.77753462 | F10: =1-F9 -> 0.78205785 | G10: =1-G9 -> 0.7894362 | I10: N/A | J10: N/A | K10: N/A | L10: N/A | M10: N/A | N10: High retention supports future growth and expansion initiatives
A11: Margin/Profitability Ratios
A12: Gross Margin | B12: Gross Profit/Net Sales | C12: N/A | D12: N/A | E12: N/A | F12: N/A | G12: N/A | I12: N/A | J12: N/A | K12: N/A | L12: N/A | M12: N/A
A13: ROE (%) | B13: PAT/Share Holders Equity | C13: ='Profit Loss'!B20/Balance_Sheet!B40 -> 0.98813194 | D13: ='Profit Loss'!C20/Balance_Sheet!C40 -> 1.176622 | E13: ='Profit Loss'!D20/Balance_Sheet!D40 -> 1.5623033 | F13: ='Profit Loss'!E20/Balance_Sheet!E40 -> 1.6050179 | G13: ='Profit Loss'!F20/Balance_Sheet!F40 -> 1.9760553 | I13: ='Ind_P&L'!B19/Ind_bal!B34 -> 0.23981 | J13: ='Ind_P&L'!C19/Ind_bal!C34 -> 0.30908322 | K13: ='Ind_P&L'!D19/Ind_bal!D34 -> 0.36296453 | L13: ='Ind_P&L'!E19/Ind_bal!E34 -> 0.36069469 | M13: ='Ind_P&L'!F19/Ind_bal!F34 -> 0.40857376 | N13: Strong upward ROE trend significantly above industry reflects superior capital efficiency.
A14: EBIDTA Margin | B14: EBIDTA / Net Sales | C14: ='Profit Loss'!B25/'Profit Loss'!B4 -> 0.56604144 | D14: ='Profit Loss'!C25/'Profit Loss'!C4 -> 0.57233637 | E14: ='Profit Loss'!D25/'Profit Loss'!D4 -> 0.58524081 | F14: ='Profit Loss'!E25/'Profit Loss'!E4 -> 0.58996733 | G14: ='Profit Loss'!F25/'Profit Loss'!F4 -> 0.58504633 | I14: ='Ind_P&L'!B10/'Ind_P&L'!B3 -> 0.32045953 | J14: ='Ind_P&L'!C10/'Ind_P&L'!C3 -> 0.36421757 | K14: ='Ind_P&L'!D10/'Ind_P&L'!D3 -> 0.39368808 | L14: ='Ind_P&L'!E10/'Ind_P&L'!E3 -> 0.40252729 | M14: ='Ind_P&L'!F10/'Ind_P&L'!F3 -> 0.41526133 | N14: Stable high margins confirm scalable asset-light payment network model.
A15: EBIT Margin(%) | B15: PBIT/Net Sales | C15: ='Profit Loss'!B11/'Profit Loss'!B4 -> 0.52813542 | D15: ='Profit Loss'!C11/'Profit Loss'!C4 -> 0.53389112 | E15: ='Profit Loss'!D11/'Profit Loss'!D4 -> 0.55151324 | F15: ='Profit Loss'!E11/'Profit Loss'!E4 -> 0.55813212 | G15: ='Profit Loss'!F11/'Profit Loss'!F4 -> 0.55320055 | I15: ='Ind_P&L'!B17/'Ind_P&L'!B3 -> 0.31395964 | J15: ='Ind_P&L'!C17/'Ind_P&L'!C3 -> 0.35624447 | K15: ='Ind_P&L'!D17/'Ind_P&L'!D3 -> 0.37250476 | L15: ='Ind_P&L'!E17/'Ind_P&L'!E3 -> 0.38721178 | M15: ='Ind_P&L'!F17/'Ind_P&L'!F3 -> 0.40162615 | N15: Operational profitability remains strong and consistent over time.
A16: PAT Margin (%) (Net Profit Margin) | B16: PAT/Net Sales | C16: ='Profit Loss'!B20/'Profit Loss'!B4 -> 0.41899222 | D16: ='Profit Loss'!C20/'Profit Loss'!C4 -> 0.46001906 | E16: ='Profit Loss'!D20/'Profit Loss'!D4 -> 0.44655304 | F16: ='Profit Loss'!E20/'Profit Loss'!E4 -> 0.44605148 | G16: ='Profit Loss'!F20/'Profit Loss'!F4 -> 0.45705968 | I16: ='Ind_P&L'!B19/'Ind_P&L'!B3 -> 0.25146247 | J16: ='Ind_P&L'!C19/'Ind_P&L'!C3 -> 0.29643085 | K16: ='Ind_P&L'!D19/'Ind_P&L'!D3 -> 0.31707916 | L16: ='Ind_P&L'!E19/'Ind_P&L'!E3 -> 0.32242012 | M16: ='Ind_P&L'!F19/'Ind_P&L'!F3 -> 0.34237249 | N16: High net margin demonstrates strong pricing power and cost discipline.
A17: ROA (%) | B17: PAT/Total Assets | C17: ='Profit Loss'!B20/Balance_Sheet!B17 -> 0.19089447 | D17: ='Profit Loss'!C20/Balance_Sheet!C17 -> 0.23061403 | E17: ='Profit Loss'!D20/Balance_Sheet!D17 -> 0.25643012 | F17: ='Profit Loss'!E20/Balance_Sheet!E17 -> 0.26373445 | G17: ='Profit Loss'!F20/Balance_Sheet!F17 -> 0.26775649 | I17: ='Ind_P&L'!B19/Ind_bal!B16 -> 0.090413029 | J17: ='Ind_P&L'!C19/Ind_bal!C16 -> 0.12887526 | K17: ='Ind_P&L'!D19/Ind_bal!D16 -> 0.15926644 | L17: ='Ind_P&L'!E19/Ind_bal!E16 -> 0.15650271 | M17: ='Ind_P&L'!F19/Ind_bal!F16 -> 0.17807197 | N17: Improving ROA shows increasing efficiency in asset utilization
A18: Growth Ratio
A19: Net Sales Growth(%) | B19: (Sales of Current Year - Sales of Previous Year)/Sales of Previous Year | D19: =('Profit Loss'!C4-'Profit Loss'!B4)/'Profit Loss'!B4 -> 0.2341677 | E19: =('Profit Loss'!D4-'Profit Loss'!C4)/'Profit Loss'!C4 -> 0.17755772 | F19: =('Profit Loss'!E4-'Profit Loss'!D4)/'Profit Loss'!D4 -> 0.12865944 | G19: =('Profit Loss'!F4-'Profit Loss'!E4)/'Profit Loss'!E4 -> 0.12228066 | J19: =('Ind_P&L'!C3-'Ind_P&L'!B3)/'Ind_P&L'!B3 -> 0.22947623 | K19: =('Ind_P&L'!D3-'Ind_P&L'!C3)/'Ind_P&L'!C3 -> 0.1274159 | L19: =('Ind_P&L'!E3-'Ind_P&L'!D3)/'Ind_P&L'!D3 -> 0.070545641 | M19: =('Ind_P&L'!F3-'Ind_P&L'!E3)/'Ind_P&L'!E3 -> 0.13257308 | N19: Growth remains positive though moderating as business matures.
